Workbook

Sheet Read Me
A1: Read Me
A2: What this is: a cleaned, analysis-ready version of the CMS Transparency in Coverage Public Use File (PUF) for plan year 2026, reorganized around how fixable each claim denial is.
A3: Source: CMS Exchange Public Use Files, https://download.cms.gov/marketplace-puf/2026/transparency-in-coverage-puf.zip (downloaded 2026-09-28). Covers HealthCare.gov states (30) only; data self-reported by insurers.
A5: Tabs
A6: Fixability — start here. Pick a market in the yellow cell; shows headline rates, then all 10 CMS denial reasons ranked by fixability tier.
A7: By State / By Plan Type / By Metal Level — the same tiers and reason mix broken out, with heat-map shading. Follow the market picked on Fixability.
A8: Issuers — one row per insurer per market: claims, denial rates (total / OON / in-network), appeals and overturn rates, and fixability tiers rolled up from its plans.
A9: Plans — one row per plan: plan-level claims, denials by reason (columns ordered and colored by fixability tier), tier subtotals.
A11: How the data was cleaned
A12: • Three source tabs (Individual Medical QHP, Individual Dental SADP, SHOP) stacked into one table with a Market column.
A13: • Issuer-level fields (repeated on every plan row in the source) moved to the Issuers tab, one row each.
A14: • CMS placeholder codes converted to blank cells so numbers sum correctly: * not available, ** suppressed for small numbers, *** not required for plan type, N/A new to the Exchange. The Data Notes column on Issuers records which codes were present.
... A22: • CMS publishes no dollar amounts. See the Ferry project doc "CMS Claims Denial Data" for cost estimates.

Sheet Fixability
A1: Claim Denials by Fixability — CMS Transparency in Coverage, Plan Year 2026
A3: Market (choose): | C3: Individual Medical | D3: ← every number on this tab and the "By ..." tabs follows this cell
A5: Claims received | C5: =SUMIFS(Issuers!$I$2:$I$375,Issuers!$A$2:$A$375,$C$3) -> 495646850 | D5: Issuer-level totals. Suppressed cells excluded, so figures are minimums.
A6: Claims denied | C6: =SUMIFS(Issuers!$L$2:$L$375,Issuers!$A$2:$A$375,$C$3) -> 100974402
A7: Overall denial rate | C7: =IFERROR(C6/C5,"") -> 0.20372247
A8: Out-of-network denial rate | C8: =IFERROR(SUMIFS(Issuers!$J$2:$J$375,Issuers!$A$2:$A$375,$C$3)/SUMIFS(Issuers!$G$2:$G$375,Issuers!$A$2:$A$375,$C$3),"") -> 0.37100776
A9: In-network denial rate | C9: =IFERROR(SUMIFS(Issuers!$K$2:$K$375,Issuers!$A$2:$A$375,$C$3)/SUMIFS(Issuers!$H$2:$H$375,Issuers!$A$2:$A$375,$C$3),"") -> 0.1872638
A10: Internal appeals filed | C10: =SUMIFS(Issuers!$R$2:$R$375,Issuers!$A$2:$A$375,$C$3) -> 263021
A11: Internal appeal overturn rate | C11: =IFERROR(SUMIFS(Issuers!$S$2:$S$375,Issuers!$A$2:$A$375,$C$3)/C10,"") -> 0.32623631
A12: Appeals filed per 1,000 denials | C12: =IFERROR((C10+SUMIFS(Issuers!$U$2:$U$375,Issuers!$A$2:$A$375,$C$3))/C6*1000,"") -> 2.663071
A14: Denial reasons ranked by how fixable they are
A15: Rank | B15: Fixability Tier | C15: Denial Reason | D15: What It Usually Means | E15: Typical Fix Path | F15: Who Can Fix It | G15: Denials (plan-level) | H15: Share of Denials | I15: Cumulative Share | J15: Patient Cost to Fight
A16: 1 | B16: High | C16: Administrative | D16: Paperwork or data problem: missing/invalid codes, NPI, dates, duplicate or incomplete claim. | E16: Correct and resubmit; usually no appeal needed. | F16: Patient or Ferry with provider info | G16: =SUMIFS(Plans!$Q$2:$Q$4957,Plans!$A$2:$A$4957,$C$3) -> 19612209 | H16: =IFERROR(G16/$G$26,"") -> 0.22497948 | I16: =IFERROR(SUM($G$16:G16)/$G$26,"") -> 0.22497948 | J16: Resubmission: free.
A17: 2 | B17: Medium-High | C17: Not medically necessary (medical) | D17: Insurer says care was not needed. | E17: Internal appeal with clinical notes and a letter of medical necessity; external review if denied again. | F17: Provider documentation + patient appeal | G17: =SUMIFS(Plans!$R$2:$R$4957,Plans!$A$2:$A$4957,$C$3) -> 3594527 | H17: =IFERROR(G17/$G$26,"") -> 0.041234254 | I17: =IFERROR(SUM($G$16:G17)/$G$26,"") -> 0.26621373 | J17: Internal appeal: free. External review: free (federal) or ≤ $25 (state).
A18: 3 | B18: Medium-High | C18: Not medically necessary (behavioral health) | D18: Same, for mental health / substance use care. Parity rules add leverage. | E18: Appeal with treatment notes; cite mental health parity rules. | F18: Provider documentation + patient appeal | G18: =SUMIFS(Plans!$S$2:$S$4957,Plans!$A$2:$A$4957,$C$3) -> 374394 | H18: =IFERROR(G18/$G$26,"") -> 0.004294823 | I18: =IFERROR(SUM($G$16:G18)/$G$26,"") -> 0.27050856 | J18: Internal appeal: free. External review: free (federal) or ≤ $25 (state).
A19: 4 | B19: Medium | C19: Referral required | D19: Plan needed a PCP referral or prior authorization. | E19: Request a retroactive referral/authorization, then resubmit or appeal. | F19: Patient + PCP | G19: =SUMIFS(Plans!$T$2:$T$4957,Plans!$A$2:$A$4957,$C$3) -> 7304650 | H19: =IFERROR(G19/$G$26,"") -> 0.083794556 | I19: =IFERROR(SUM($G$16:G19)/$G$26,"") -> 0.35430311 | J19: Resubmission: free.
A20: 5 | B20: Medium | C20: Member not covered | D20: Eligibility problem: wrong member ID, lapsed coverage, coordination of benefits. | E20: Verify eligibility, fix member info or COB, resubmit. | F20: Patient | G20: =SUMIFS(Plans!$U$2:$U$4957,Plans!$A$2:$A$4957,$C$3) -> 5729108 | H20: =IFERROR(G20/$G$26,"") -> 0.065720885 | I20: =IFERROR(SUM($G$16:G20)/$G$26,"") -> 0.420024 | J20: Internal appeal: free. External review: free (federal) or ≤ $25 (state).
A21: 6 | B21: Medium | C21: Out-of-network | D21: Provider is not in the plan network. | E21: PPO/POS: appeal or reprocess at OON benefit. HMO/EPO: usually no OON benefit (low fixability) unless emergency, network gap or No Surprises Act applies. | F21: Patient; depends on plan type | G21: =SUMIFS(Plans!$V$2:$V$4957,Plans!$A$2:$A$4957,$C$3) -> 8567575 | H21: =IFERROR(G21/$G$26,"") -> 0.098282073 | I21: =IFERROR(SUM($G$16:G21)/$G$26,"") -> 0.51830607 | J21: Internal appeal: free. External review: free (federal) or ≤ $25 (state).
A22: 7 | B22: Low | C22: Benefit limit reached | D22: Visit or dollar cap for the year was used up. | E22: Rarely fixable; medical-necessity exception request sometimes works. | F22: Patient + provider | G22: =SUMIFS(Plans!$W$2:$W$4957,Plans!$A$2:$A$4957,$C$3) -> 3646507 | H22: =IFERROR(G22/$G$26,"") -> 0.041830538 | I22: =IFERROR(SUM($G$16:G22)/$G$26,"") -> 0.56013661 | J22: Internal appeal: free. External review: free (federal) or ≤ $25 (state).
A23: 8 | B23: Low | C23: Service excluded | D23: The plan does not cover this service at all. | E23: Usually final unless the service was miscoded; check for a coding fix. | F23: Provider coding review | G23: =SUMIFS(Plans!$X$2:$X$4957,Plans!$A$2:$A$4957,$C$3) -> 10129111 | H23: =IFERROR(G23/$G$26,"") -> 0.11619508 | I23: =IFERROR(SUM($G$16:G23)/$G$26,"") -> 0.67633168 | J23: Internal appeal: free. External review: free (federal) or ≤ $25 (state).
A24: 9 | B24: Low | C24: Experimental / cosmetic | D24: Treatment considered investigational or cosmetic. | E24: Appeal with clinical evidence; external review can overturn but odds are low. | F24: Provider + patient | G24: =SUMIFS(Plans!$Y$2:$Y$4957,Plans!$A$2:$A$4957,$C$3) -> 101612 | H24: =IFERROR(G24/$G$26,"") -> 0.0011656318 | I24: =IFERROR(SUM($G$16:G24)/$G$26,"") -> 0.67749732 | J24: Internal appeal: free. External review: free (federal) or ≤ $25 (state).
A25: 10 | B25: Unknown | C25: Other / unspecified | D25: Insurer did not classify the reason. | E25: Read the reason code (CARC/RARC) on the EOB, then route to the right fix. | F25: Needs EOB review | G25: =SUMIFS(Plans!$Z$2:$Z$4957,Plans!$A$2:$A$4957,$C$3) -> 28113631 | H25: =IFERROR(G25/$G$26,"") -> 0.32250268 | I25: =IFERROR(SUM($G$16:G25)/$G$26,"") -> 1 | J25: Depends on true reason.
C26: Total | G26: =SUM(G16:G25) -> 87173324 | H26: =IFERROR(G26/G26,"") -> 1
A28: Summary by fixability tier
A29: Tier | B29: Fixability | C29: Denials | D29: Share | E29: Definition
A30: 1 | B30: High | C30: =SUMIFS($G$16:$G$25,$B$16:$B$25,B30) -> 19612209 | D30: =IFERROR(C30/$G$26,"") -> 0.22497948 | E30: Fixable by correcting and resubmitting; no clinical argument needed.
A31: 2 | B31: Medium-High | C31: =SUMIFS($G$16:$G$25,$B$16:$B$25,B31) -> 3968921 | D31: =IFERROR(C31/$G$26,"") -> 0.045529077 | E31: Winnable on appeal with documentation; external review often overturns.
A32: 3 | B32: Medium | C32: =SUMIFS($G$16:$G$25,$B$16:$B$25,B32) -> 21601333 | D32: =IFERROR(C32/$G$26,"") -> 0.24779751 | E32: Fixable if the underlying fact is wrong (eligibility, referral, network status, plan type).
A33: 4 | B33: Low | C33: =SUMIFS($G$16:$G$25,$B$16:$B$25,B33) -> 13877230 | D33: =IFERROR(C33/$G$26,"") -> 0.15919125 | E33: Usually a true coverage limit; succeeds only with a coding error or exception.
A34: 5 | B34: Unknown | C34: =SUMIFS($G$16:$G$25,$B$16:$B$25,B34) -> 28113631 | D34: =IFERROR(C34/$G$26,"") -> 0.32250268 | E34: Reason not classified by insurer; read the EOB reason code first.
B35: Total | C35: =SUM(C30:C34) -> 87173324
A37: Fixability tiers are Ferry judgments based on how each denial type is normally resolved, not CMS data. Out-of-network is rated Medium overall but is Low for HMO/EPO plans (no OON benefit) and Medium for PPO/POS.

Sheet By State
A1: Denial reasons by State — market: | D1: =Fixability!$C$3 -> Individual Medical
A2: Counts by fixability tier, then each reason as a share of that row's classified denials. Change the market on the Fixability tab.
A4: State | B4: Denials With Reason | C4: Tier 1 High | D4: Tier 2 Medium-High | E4: Tier 3 Medium | F4: Tier 4 Low | G4: Tier 5 Unknown | H4: % Fixable (High + Med-High) | I4: % Administrative | J4: % Not medically necessary (medical) | K4: % Not medically necessary (behavioral health) | L4: % Referral required | M4: % Member not covered | N4: % Out-of-network | O4: % Benefit limit reached | P4: % Service excluded | Q4: % Experimental / cosmetic | R4: % Other / unspecified
A5: TX | B5: =SUM(C5:G5) -> 25649845 | C5: =SUMIFS(Plans!$AA$2:$AA$4957,Plans!$A$2:$A$4957,Fixability!$C$3,Plans!$B$2:$B$4957,$A5) -> 3089691 | D5: =SUMIFS(Plans!$AB$2:$AB$4957,Plans!$A$2:$A$4957,Fixability!$C$3,Plans!$B$2:$B$4957,$A5) -> 1082079 | E5: =SUMIFS(Plans!$AC$2:$AC$4957,Plans!$A$2:$A$4957,Fixability!$C$3,Plans!$B$2:$B$4957,$A5) -> 6927343 | F5: =SUMIFS(Plans!$AD$2:$AD$4957,Plans!$A$2:$A$4957,Fixability!$C$3,Plans!$B$2:$B$4957,$A5) -> 4631476 | G5: =SUMIFS(Plans!$AE$2:$AE$4957,Plans!$A$2:$A$4957,Fixability!$C$3,Plans!$B$2:$B$4957,$A5) -> 9919256 | H5: =IFERROR((C5+D5)/B5,"") -> 0.16264309 | I5: =IFERROR(SUMIFS(Plans!$Q$2:$Q$4957,Plans!$A$2:$A$4957,Fixability!$C$3,Plans!$B$2:$B$4957,$A5)/$B5,"") -> 0.12045652 | J5: =IFERROR(SUMIFS(Plans!$R$2:$R$4957,Plans!$A$2:$A$4957,Fixability!$C$3,Plans!$B$2:$B$4957,$A5)/$B5,"") -> 0.038869046 | K5: =IFERROR(SUMIFS(Plans!$S$2:$S$4957,Plans!$A$2:$A$4957,Fixability!$C$3,Plans!$B$2:$B$4957,$A5)/$B5,"") -> 0.0033175249 | L5: =IFERROR(SUMIFS(Plans!$T$2:$T$4957,Plans!$A$2:$A$4957,Fixability!$C$3,Plans!$B$2:$B$4957,$A5)/$B5,"") -> 0.096018124 | M5: =IFERROR(SUMIFS(Plans!$U$2:$U$4957,Plans!$A$2:$A$4957,Fixability!$C$3,Plans!$B$2:$B$4957,$A5)/$B5,"") -> 0.0598758 | N5: =IFERROR(SUMIFS(Plans!$V$2:$V$4957,Plans!$A$2:$A$4957,Fixability!$C$3,Plans!$B$2:$B$4957,$A5)/$B5,"") -> 0.11417956 | O5: =IFERROR(SUMIFS(Plans!$W$2:$W$4957,Plans!$A$2:$A$4957,Fixability!$C$3,Plans!$B$2:$B$4957,$A5)/$B5,"") -> 0.0185244 | P5: =IFERROR(SUMIFS(Plans!$X$2:$X$4957,Plans!$A$2:$A$4957,Fixability!$C$3,Plans!$B$2:$B$4957,$A5)/$B5,"") -> 0.16137255 | Q5: =IFERROR(SUMIFS(Plans!$Y$2:$Y$4957,Plans!$A$2:$A$4957,Fixability!$C$3,Plans!$B$2:$B$4957,$A5)/$B5,"") -> 0.00066850307 | R5: =IFERROR(SUMIFS(Plans!$Z$2:$Z$4957,Plans!$A$2:$A$4957,Fixability!$C$3,Plans!$B$2:$B$4957,$A5)/$B5,"") -> 0.38671797
A6: FL | B6: =SUM(C6:G6) -> 16682663 | C6: =SUMIFS(Plans!$AA$2:$AA$4957,Plans!$A$2:$A$4957,Fixability!$C$3,Plans!$B$2:$B$4957,$A6) -> 7085644 | D6: =SUMIFS(Plans!$AB$2:$AB$4957,Plans!$A$2:$A$4957,Fixability!$C$3,Plans!$B$2:$B$4957,$A6) -> 351017 | E6: =SUMIFS(Plans!$AC$2:$AC$4957,Plans!$A$2:$A$4957,Fixability!$C$3,Plans!$B$2:$B$4957,$A6) -> 1528571 | F6: =SUMIFS(Plans!$AD$2:$AD$4957,Plans!$A$2:$A$4957,Fixability!$C$3,Plans!$B$2:$B$4957,$A6) -> 587809 | G6: =SUMIFS(Plans!$AE$2:$AE$4957,Plans!$A$2:$A$4957,Fixability!$C$3,Plans!$B$2:$B$4957,$A6) -> 7129622 | H6: =IFERROR((C6+D6)/B6,"") -> 0.44577182 | I6: =IFERROR(SUMIFS(Plans!$Q$2:$Q$4957,Plans!$A$2:$A$4957,Fixability!$C$3,Plans!$B$2:$B$4957,$A6)/$B6,"") -> 0.42473099 | J6: =IFERROR(SUMIFS(Plans!$R$2:$R$4957,Plans!$A$2:$A$4957,Fixability!$C$3,Plans!$B$2:$B$4957,$A6)/$B6,"") -> 0.01756644 | K6: =IFERROR(SUMIFS(Plans!$S$2:$S$4957,Plans!$A$2:$A$4957,Fixability!$C$3,Plans!$B$2:$B$4957,$A6)/$B6,"") -> 0.0034743854 | L6: =IFERROR(SUMIFS(Plans!$T$2:$T$4957,Plans!$A$2:$A$4957,Fixability!$C$3,Plans!$B$2:$B$4957,$A6)/$B6,"") -> 0.024610819 | M6: =IFERROR(SUMIFS(Plans!$U$2:$U$4957,Plans!$A$2:$A$4957,Fixability!$C$3,Plans!$B$2:$B$4957,$A6)/$B6,"") -> 0.010446174 | N6: =IFERROR(SUMIFS(Plans!$V$2:$V$4957,Plans!$A$2:$A$4957,Fixability!$C$3,Plans!$B$2:$B$4957,$A6)/$B6,"") -> 0.056569326 | O6: =IFERROR(SUMIFS(Plans!$W$2:$W$4957,Plans!$A$2:$A$4957,Fixability!$C$3,Plans!$B$2:$B$4957,$A6)/$B6,"") -> 0.01529492 | P6: =IFERROR(SUMIFS(Plans!$X$2:$X$4957,Plans!$A$2:$A$4957,Fixability!$C$3,Plans!$B$2:$B$4957,$A6)/$B6,"") -> 0.018463419 | Q6: =IFERROR(SUMIFS(Plans!$Y$2:$Y$4957,Plans!$A$2:$A$4957,Fixability!$C$3,Plans!$B$2:$B$4957,$A6)/$B6,"") -> 0.001476383 | R6: =IFERROR(SUMIFS(Plans!$Z$2:$Z$4957,Plans!$A$2:$A$4957,Fixability!$C$3,Plans!$B$2:$B$4957,$A6)/$B6,"") -> 0.42736714
A7: AL | B7: =SUM(C7:G7) -> 5200796 | C7: =SUMIFS(Plans!$AA$2:$AA$4957,Plans!$A$2:$A$4957,Fixability!$C$3,Plans!$B$2:$B$4957,$A7) -> 1030205 | D7: =SUMIFS(Plans!$AB$2:$AB$4957,Plans!$A$2:$A$4957,Fixability!$C$3,Plans!$B$2:$B$4957,$A7) -> 90401 | E7: =SUMIFS(Plans!$AC$2:$AC$4957,Plans!$A$2:$A$4957,Fixability!$C$3,Plans!$B$2:$B$4957,$A7) -> 2233266 | F7: =SUMIFS(Plans!$AD$2:$AD$4957,Plans!$A$2:$A$4957,Fixability!$C$3,Plans!$B$2:$B$4957,$A7) -> 1337080 | G7: =SUMIFS(Plans!$AE$2:$AE$4957,Plans!$A$2:$A$4957,Fixability!$C$3,Plans!$B$2:$B$4957,$A7) -> 509844 | H7: =IFERROR((C7+D7)/B7,"") -> 0.21546817 | I7: =IFERROR(SUMIFS(Plans!$Q$2:$Q$4957,Plans!$A$2:$A$4957,Fixability!$C$3,Plans!$B$2:$B$4957,$A7)/$B7,"") -> 0.19808602 | J7: =IFERROR(SUMIFS(Plans!$R$2:$R$4957,Plans!$A$2:$A$4957,Fixability!$C$3,Plans!$B$2:$B$4957,$A7)/$B7,"") -> 0.016904528 | K7: =IFERROR(SUMIFS(Plans!$S$2:$S$4957,Plans!$A$2:$A$4957,Fixability!$C$3,Plans!$B$2:$B$4957,$A7)/$B7,"") -> 0.0004776192 | L7: =IFERROR(SUMIFS(Plans!$T$2:$T$4957,Plans!$A$2:$A$4957,Fixability!$C$3,Plans!$B$2:$B$4957,$A7)/$B7,"") -> 0.1041679 | M7: =IFERROR(SUMIFS(Plans!$U$2:$U$4957,Plans!$A$2:$A$4957,Fixability!$C$3,Plans!$B$2:$B$4957,$A7)/$B7,"") -> 0.12412062 | N7: =IFERROR(SUMIFS(Plans!$V$2:$V$4957,Plans!$A$2:$A$4957,Fixability!$C$3,Plans!$B$2:$B$4957,$A7)/$B7,"") -> 0.20111998 | O7: =IFERROR(SUMIFS(Plans!$W$2:$W$4957,Plans!$A$2:$A$4957,Fixability!$C$3,Plans!$B$2:$B$4957,$A7)/$B7,"") -> 0.079233833 | P7: =IFERROR(SUMIFS(Plans!$X$2:$X$4957,Plans!$A$2:$A$4957,Fixability!$C$3,Plans!$B$2:$B$4957,$A7)/$B7,"") -> 0.17782739 | Q7: =IFERROR(SUMIFS(Plans!$Y$2:$Y$4957,Plans!$A$2:$A$4957,Fixability!$C$3,Plans!$B$2:$B$4957,$A7)/$B7,"") -> 3.0187687e-05 | R7: =IFERROR(SUMIFS(Plans!$Z$2:$Z$4957,Plans!$A$2:$A$4957,Fixability!$C$3,Plans!$B$2:$B$4957,$A7)/$B7,"") -> 0.098031917
A8: NC | B8: =SUM(C8:G8) -> 4780663 | C8: =SUMIFS(Plans!$AA$2:$AA$4957,Plans!$A$2:$A$4957,Fixability!$C$3,Plans!$B$2:$B$4957,$A8) -> 988831 | D8: =SUMIFS(Plans!$AB$2:$AB$4957,Plans!$A$2:$A$4957,Fixability!$C$3,Plans!$B$2:$B$4957,$A8) -> 183837 | E8: =SUMIFS(Plans!$AC$2:$AC$4957,Plans!$A$2:$A$4957,Fixability!$C$3,Plans!$B$2:$B$4957,$A8) -> 1357446 | F8: =SUMIFS(Plans!$AD$2:$AD$4957,Plans!$A$2:$A$4957,Fixability!$C$3,Plans!$B$2:$B$4957,$A8) -> 1001028 | G8: =SUMIFS(Plans!$AE$2:$AE$4957,Plans!$A$2:$A$4957,Fixability!$C$3,Plans!$B$2:$B$4957,$A8) -> 1249521 | H8: =IFERROR((C8+D8)/B8,"") -> 0.24529401 | I8: =IFERROR(SUMIFS(Plans!$Q$2:$Q$4957,Plans!$A$2:$A$4957,Fixability!$C$3,Plans!$B$2:$B$4957,$A8)/$B8,"") -> 0.20683972 | J8: =IFERROR(SUMIFS(Plans!$R$2:$R$4957,Plans!$A$2:$A$4957,Fixability!$C$3,Plans!$B$2:$B$4957,$A8)/$B8,"") -> 0.035802775 | K8: =IFERROR(SUMIFS(Plans!$S$2:$S$4957,Plans!$A$2:$A$4957,Fixability!$C$3,Plans!$B$2:$B$4957,$A8)/$B8,"") -> 0.0026515151 | L8: =IFERROR(SUMIFS(Plans!$T$2:$T$4957,Plans!$A$2:$A$4957,Fixability!$C$3,Plans!$B$2:$B$4957,$A8)/$B8,"") -> 0.087065539 | M8: =IFERROR(SUMIFS(Plans!$U$2:$U$4957,Plans!$A$2:$A$4957,Fixability!$C$3,Plans!$B$2:$B$4957,$A8)/$B8,"") -> 0.122697 | N8: =IFERROR(SUMIFS(Plans!$V$2:$V$4957,Plans!$A$2:$A$4957,Fixability!$C$3,Plans!$B$2:$B$4957,$A8)/$B8,"") -> 0.074182598 | O8: =IFERROR(SUMIFS(Plans!$W$2:$W$4957,Plans!$A$2:$A$4957,Fixability!$C$3,Plans!$B$2:$B$4957,$A8)/$B8,"") -> 0.057149814 | P8: =IFERROR(SUMIFS(Plans!$X$2:$X$4957,Plans!$A$2:$A$4957,Fixability!$C$3,Plans!$B$2:$B$4957,$A8)/$B8,"") -> 0.15165198 | Q8: =IFERROR(SUMIFS(Plans!$Y$2:$Y$4957,Plans!$A$2:$A$4957,Fixability!$C$3,Plans!$B$2:$B$4957,$A8)/$B8,"") -> 0.00058924881 | R8: =IFERROR(SUMIFS(Plans!$Z$2:$Z$4957,Plans!$A$2:$A$4957,Fixability!$C$3,Plans!$B$2:$B$4957,$A8)/$B8,"") -> 0.26136981
A9: SC | B9: =SUM(C9:G9) -> 4052114 | C9: =SUMIFS(Plans!$AA$2:$AA$4957,Plans!$A$2:$A$4957,Fixability!$C$3,Plans!$B$2:$B$4957,$A9) -> 598016 | D9: =SUMIFS(Plans!$AB$2:$AB$4957,Plans!$A$2:$A$4957,Fixability!$C$3,Plans!$B$2:$B$4957,$A9) -> 469831 | E9: =SUMIFS(Plans!$AC$2:$AC$4957,Plans!$A$2:$A$4957,Fixability!$C$3,Plans!$B$2:$B$4957,$A9) -> 1165348 | F9: =SUMIFS(Plans!$AD$2:$AD$4957,Plans!$A$2:$A$4957,Fixability!$C$3,Plans!$B$2:$B$4957,$A9) -> 826694 | G9: =SUMIFS(Plans!$AE$2:$AE$4957,Plans!$A$2:$A$4957,Fixability!$C$3,Plans!$B$2:$B$4957,$A9) -> 992225 | H9: =IFERROR((C9+D9)/B9,"") -> 0.26352837 | I9: =IFERROR(SUMIFS(Plans!$Q$2:$Q$4957,Plans!$A$2:$A$4957,Fixability!$C$3,Plans!$B$2:$B$4957,$A9)/$B9,"") -> 0.14758124 | J9: =IFERROR(SUMIFS(Plans!$R$2:$R$4957,Plans!$A$2:$A$4957,Fixability!$C$3,Plans!$B$2:$B$4957,$A9)/$B9,"") -> 0.10707374 | K9: =IFERROR(SUMIFS(Plans!$S$2:$S$4957,Plans!$A$2:$A$4957,Fixability!$C$3,Plans!$B$2:$B$4957,$A9)/$B9,"") -> 0.008873393 | L9: =IFERROR(SUMIFS(Plans!$T$2:$T$4957,Plans!$A$2:$A$4957,Fixability!$C$3,Plans!$B$2:$B$4957,$A9)/$B9,"") -> 0.11352247 | M9: =IFERROR(SUMIFS(Plans!$U$2:$U$4957,Plans!$A$2:$A$4957,Fixability!$C$3,Plans!$B$2:$B$4957,$A9)/$B9,"") -> 0.1005759 | N9: =IFERROR(SUMIFS(Plans!$V$2:$V$4957,Plans!$A$2:$A$4957,Fixability!$C$3,Plans!$B$2:$B$4957,$A9)/$B9,"") -> 0.073491763 | O9: =IFERROR(SUMIFS(Plans!$W$2:$W$4957,Plans!$A$2:$A$4957,Fixability!$C$3,Plans!$B$2:$B$4957,$A9)/$B9,"") -> 0.10839453 | P9: =IFERROR(SUMIFS(Plans!$X$2:$X$4957,Plans!$A$2:$A$4957,Fixability!$C$3,Plans!$B$2:$B$4957,$A9)/$B9,"") -> 0.093556351 | Q9: =IFERROR(SUMIFS(Plans!$Y$2:$Y$4957,Plans!$A$2:$A$4957,Fixability!$C$3,Plans!$B$2:$B$4957,$A9)/$B9,"") -> 0.0020646013 | R9: =IFERROR(SUMIFS(Plans!$Z$2:$Z$4957,Plans!$A$2:$A$4957,Fixability!$C$3,Plans!$B$2:$B$4957,$A9)/$B9,"") -> 0.24486601
A10: TN | B10: =SUM(C10:G10) -> 3760723 | C10: =SUMIFS(Plans!$AA$2:$AA$4957,Plans!$A$2:$A$4957,Fixability!$C$3,Plans!$B$2:$B$4957,$A10) -> 1068753 | D10: =SUMIFS(Plans!$AB$2:$AB$4957,Plans!$A$2:$A$4957,Fixability!$C$3,Plans!$B$2:$B$4957,$A10) -> 271545 | E10: =SUMIFS(Plans!$AC$2:$AC$4957,Plans!$A$2:$A$4957,Fixability!$C$3,Plans!$B$2:$B$4957,$A10) -> 1075308 | F10: =SUMIFS(Plans!$AD$2:$AD$4957,Plans!$A$2:$A$4957,Fixability!$C$3,Plans!$B$2:$B$4957,$A10) -> 575712 | G10: =SUMIFS(Plans!$AE$2:$AE$4957,Plans!$A$2:$A$4957,Fixability!$C$3,Plans!$B$2:$B$4957,$A10) -> 769405 | H10: =IFERROR((C10+D10)/B10,"") -> 0.3563937 | I10: =IFERROR(SUMIFS(Plans!$Q$2:$Q$4957,Plans!$A$2:$A$4957,Fixability!$C$3,Plans!$B$2:$B$4957,$A10)/$B10,"") -> 0.28418817 | J10: =IFERROR(SUMIFS(Plans!$R$2:$R$4957,Plans!$A$2:$A$4957,Fixability!$C$3,Plans!$B$2:$B$4957,$A10)/$B10,"") -> 0.059653689 | K10: =IFERROR(SUMIFS(Plans!$S$2:$S$4957,Plans!$A$2:$A$4957,Fixability!$C$3,Plans!$B$2:$B$4957,$A10)/$B10,"") -> 0.012551842 | L10: =IFERROR(SUMIFS(Plans!$T$2:$T$4957,Plans!$A$2:$A$4957,Fixability!$C$3,Plans!$B$2:$B$4957,$A10)/$B10,"") -> 0.091541174 | M10: =IFERROR(SUMIFS(Plans!$U$2:$U$4957,Plans!$A$2:$A$4957,Fixability!$C$3,Plans!$B$2:$B$4957,$A10)/$B10,"") -> 0.068225445 | N10: =IFERROR(SUMIFS(Plans!$V$2:$V$4957,Plans!$A$2:$A$4957,Fixability!$C$3,Plans!$B$2:$B$4957,$A10)/$B10,"") -> 0.12616457 | O10: =IFERROR(SUMIFS(Plans!$W$2:$W$4957,Plans!$A$2:$A$4957,Fixability!$C$3,Plans!$B$2:$B$4957,$A10)/$B10,"") -> 0.035837524 | P10: =IFERROR(SUMIFS(Plans!$X$2:$X$4957,Plans!$A$2:$A$4957,Fixability!$C$3,Plans!$B$2:$B$4957,$A10)/$B10,"") -> 0.11671984 | Q10: =IFERROR(SUMIFS(Plans!$Y$2:$Y$4957,Plans!$A$2:$A$4957,Fixability!$C$3,Plans!$B$2:$B$4957,$A10)/$B10,"") -> 0.00052808994 | R10: =IFERROR(SUMIFS(Plans!$Z$2:$Z$4957,Plans!$A$2:$A$4957,Fixability!$C$3,Plans!$B$2:$B$4957,$A10)/$B10,"") -> 0.20458965
A11: OH | B11: =SUM(C11:G11) -> 3605643 | C11: =SUMIFS(Plans!$AA$2:$AA$4957,Plans!$A$2:$A$4957,Fixability!$C$3,Plans!$B$2:$B$4957,$A11) -> 951084 | D11: =SUMIFS(Plans!$AB$2:$AB$4957,Plans!$A$2:$A$4957,Fixability!$C$3,Plans!$B$2:$B$4957,$A11) -> 404913 | E11: =SUMIFS(Plans!$AC$2:$AC$4957,Plans!$A$2:$A$4957,Fixability!$C$3,Plans!$B$2:$B$4957,$A11) -> 1221570 | F11: =SUMIFS(Plans!$AD$2:$AD$4957,Plans!$A$2:$A$4957,Fixability!$C$3,Plans!$B$2:$B$4957,$A11) -> 669726 | G11: =SUMIFS(Plans!$AE$2:$AE$4957,Plans!$A$2:$A$4957,Fixability!$C$3,Plans!$B$2:$B$4957,$A11) -> 358350 | H11: =IFERROR((C11+D11)/B11,"") -> 0.37607633 | I11: =IFERROR(SUMIFS(Plans!$Q$2:$Q$4957,Plans!$A$2:$A$4957,Fixability!$C$3,Plans!$B$2:$B$4957,$A11)/$B11,"") -> 0.26377653 | J11: =IFERROR(SUMIFS(Plans!$R$2:$R$4957,Plans!$A$2:$A$4957,Fixability!$C$3,Plans!$B$2:$B$4957,$A11)/$B11,"") -> 0.10058622 | K11: =IFERROR(SUMIFS(Plans!$S$2:$S$4957,Plans!$A$2:$A$4957,Fixability!$C$3,Plans!$B$2:$B$4957,$A11)/$B11,"") -> 0.011713583 | L11: =IFERROR(SUMIFS(Plans!$T$2:$T$4957,Plans!$A$2:$A$4957,Fixability!$C$3,Plans!$B$2:$B$4957,$A11)/$B11,"") -> 0.11759761 | M11: =IFERROR(SUMIFS(Plans!$U$2:$U$4957,Plans!$A$2:$A$4957,Fixability!$C$3,Plans!$B$2:$B$4957,$A11)/$B11,"") -> 0.069484417 | N11: =IFERROR(SUMIFS(Plans!$V$2:$V$4957,Plans!$A$2:$A$4957,Fixability!$C$3,Plans!$B$2:$B$4957,$A11)/$B11,"") -> 0.15171191 | O11: =IFERROR(SUMIFS(Plans!$W$2:$W$4957,Plans!$A$2:$A$4957,Fixability!$C$3,Plans!$B$2:$B$4957,$A11)/$B11,"") -> 0.083672455 | P11: =IFERROR(SUMIFS(Plans!$X$2:$X$4957,Plans!$A$2:$A$4957,Fixability!$C$3,Plans!$B$2:$B$4957,$A11)/$B11,"") -> 0.097896825 | Q11: =IFERROR(SUMIFS(Plans!$Y$2:$Y$4957,Plans!$A$2:$A$4957,Fixability!$C$3,Plans!$B$2:$B$4957,$A11)/$B11,"") -> 0.0041745675 | R11: =IFERROR(SUMIFS(Plans!$Z$2:$Z$4957,Plans!$A$2:$A$4957,Fixability!$C$3,Plans!$B$2:$B$4957,$A11)/$B11,"") -> 0.099385879
A12: AR | B12: =SUM(C12:G12) -> 3119026 | C12: =SUMIFS(Plans!$AA$2:$AA$4957,Plans!$A$2:$A$4957,Fixability!$C$3,Plans!$B$2:$B$4957,$A12) -> 707653 | D12: =SUMIFS(Plans!$AB$2:$AB$4957,Plans!$A$2:$A$4957,Fixability!$C$3,Plans!$B$2:$B$4957,$A12) -> 192732 | E12: =SUMIFS(Plans!$AC$2:$AC$4957,Plans!$A$2:$A$4957,Fixability!$C$3,Plans!$B$2:$B$4957,$A12) -> 759708 | F12: =SUMIFS(Plans!$AD$2:$AD$4957,Plans!$A$2:$A$4957,Fixability!$C$3,Plans!$B$2:$B$4957,$A12) -> 838316 | G12: =SUMIFS(Plans!$AE$2:$AE$4957,Plans!$A$2:$A$4957,Fixability!$C$3,Plans!$B$2:$B$4957,$A12) -> 620617 | H12: =IFERROR((C12+D12)/B12,"") -> 0.28867505 | I12: =IFERROR(SUMIFS(Plans!$Q$2:$Q$4957,Plans!$A$2:$A$4957,Fixability!$C$3,Plans!$B$2:$B$4957,$A12)/$B12,"") -> 0.22688269 | J12: =IFERROR(SUMIFS(Plans!$R$2:$R$4957,Plans!$A$2:$A$4957,Fixability!$C$3,Plans!$B$2:$B$4957,$A12)/$B12,"") -> 0.059442595 | K12: =IFERROR(SUMIFS(Plans!$S$2:$S$4957,Plans!$A$2:$A$4957,Fixability!$C$3,Plans!$B$2:$B$4957,$A12)/$B12,"") -> 0.002349772 | L12: =IFERROR(SUMIFS(Plans!$T$2:$T$4957,Plans!$A$2:$A$4957,Fixability!$C$3,Plans!$B$2:$B$4957,$A12)/$B12,"") -> 0.13731338 | M12: =IFERROR(SUMIFS(Plans!$U$2:$U$4957,Plans!$A$2:$A$4957,Fixability!$C$3,Plans!$B$2:$B$4957,$A12)/$B12,"") -> 0.094380746 | N12: =IFERROR(SUMIFS(Plans!$V$2:$V$4957,Plans!$A$2:$A$4957,Fixability!$C$3,Plans!$B$2:$B$4957,$A12)/$B12,"") -> 0.011878067 | O12: =IFERROR(SUMIFS(Plans!$W$2:$W$4957,Plans!$A$2:$A$4957,Fixability!$C$3,Plans!$B$2:$B$4957,$A12)/$B12,"") -> 0.18423796 | P12: =IFERROR(SUMIFS(Plans!$X$2:$X$4957,Plans!$A$2:$A$4957,Fixability!$C$3,Plans!$B$2:$B$4957,$A12)/$B12,"") -> 0.084536968 | Q12: =IFERROR(SUMIFS(Plans!$Y$2:$Y$4957,Plans!$A$2:$A$4957,Fixability!$C$3,Plans!$B$2:$B$4957,$A12)/$B12,"") -> 0 | R12: =IFERROR(SUMIFS(Plans!$Z$2:$Z$4957,Plans!$A$2:$A$4957,Fixability!$C$3,Plans!$B$2:$B$4957,$A12)/$B12,"") -> 0.19897782
A13: OK | B13: =SUM(C13:G13) -> 2365896 | C13: =SUMIFS(Plans!$AA$2:$AA$4957,Plans!$A$2:$A$4957,Fixability!$C$3,Plans!$B$2:$B$4957,$A13) -> 564496 | D13: =SUMIFS(Plans!$AB$2:$AB$4957,Plans!$A$2:$A$4957,Fixability!$C$3,Plans!$B$2:$B$4957,$A13) -> 86168 | E13: =SUMIFS(Plans!$AC$2:$AC$4957,Plans!$A$2:$A$4957,Fixability!$C$3,Plans!$B$2:$B$4957,$A13) -> 546675 | F13: =SUMIFS(Plans!$AD$2:$AD$4957,Plans!$A$2:$A$4957,Fixability!$C$3,Plans!$B$2:$B$4957,$A13) -> 389902 | G13: =SUMIFS(Plans!$AE$2:$AE$4957,Plans!$A$2:$A$4957,Fixability!$C$3,Plans!$B$2:$B$4957,$A13) -> 778655 | H13: =IFERROR((C13+D13)/B13,"") -> 0.27501801 | I13: =IFERROR(SUMIFS(Plans!$Q$2:$Q$4957,Plans!$A$2:$A$4957,Fixability!$C$3,Plans!$B$2:$B$4957,$A13)/$B13,"") -> 0.23859713 | J13: =IFERROR(SUMIFS(Plans!$R$2:$R$4957,Plans!$A$2:$A$4957,Fixability!$C$3,Plans!$B$2:$B$4957,$A13)/$B13,"") -> 0.034070813 | K13: =IFERROR(SUMIFS(Plans!$S$2:$S$4957,Plans!$A$2:$A$4957,Fixability!$C$3,Plans!$B$2:$B$4957,$A13)/$B13,"") -> 0.002350061 | L13: =IFERROR(SUMIFS(Plans!$T$2:$T$4957,Plans!$A$2:$A$4957,Fixability!$C$3,Plans!$B$2:$B$4957,$A13)/$B13,"") -> 0.1094748 | M13: =IFERROR(SUMIFS(Plans!$U$2:$U$4957,Plans!$A$2:$A$4957,Fixability!$C$3,Plans!$B$2:$B$4957,$A13)/$B13,"") -> 0.091860335 | N13: =IFERROR(SUMIFS(Plans!$V$2:$V$4957,Plans!$A$2:$A$4957,Fixability!$C$3,Plans!$B$2:$B$4957,$A13)/$B13,"") -> 0.02972954 | O13: =IFERROR(SUMIFS(Plans!$W$2:$W$4957,Plans!$A$2:$A$4957,Fixability!$C$3,Plans!$B$2:$B$4957,$A13)/$B13,"") -> 0.020143743 | P13: =IFERROR(SUMIFS(Plans!$X$2:$X$4957,Plans!$A$2:$A$4957,Fixability!$C$3,Plans!$B$2:$B$4957,$A13)/$B13,"") -> 0.14322058 | Q13: =IFERROR(SUMIFS(Plans!$Y$2:$Y$4957,Plans!$A$2:$A$4957,Fixability!$C$3,Plans!$B$2:$B$4957,$A13)/$B13,"") -> 0.001436665 | R13: =IFERROR(SUMIFS(Plans!$Z$2:$Z$4957,Plans!$A$2:$A$4957,Fixability!$C$3,Plans!$B$2:$B$4957,$A13)/$B13,"") -> 0.32911633
A14: UT | B14: =SUM(C14:G14) -> 2306364 | C14: =SUMIFS(Plans!$AA$2:$AA$4957,Plans!$A$2:$A$4957,Fixability!$C$3,Plans!$B$2:$B$4957,$A14) -> 282148 | D14: =SUMIFS(Plans!$AB$2:$AB$4957,Plans!$A$2:$A$4957,Fixability!$C$3,Plans!$B$2:$B$4957,$A14) -> 26211 | E14: =SUMIFS(Plans!$AC$2:$AC$4957,Plans!$A$2:$A$4957,Fixability!$C$3,Plans!$B$2:$B$4957,$A14) -> 319884 | F14: =SUMIFS(Plans!$AD$2:$AD$4957,Plans!$A$2:$A$4957,Fixability!$C$3,Plans!$B$2:$B$4957,$A14) -> 345017 | G14: =SUMIFS(Plans!$AE$2:$AE$4957,Plans!$A$2:$A$4957,Fixability!$C$3,Plans!$B$2:$B$4957,$A14) -> 1333104 | H14: =IFERROR((C14+D14)/B14,"") -> 0.13369919 | I14: =IFERROR(SUMIFS(Plans!$Q$2:$Q$4957,Plans!$A$2:$A$4957,Fixability!$C$3,Plans!$B$2:$B$4957,$A14)/$B14,"") -> 0.12233455 | J14: =IFERROR(SUMIFS(Plans!$R$2:$R$4957,Plans!$A$2:$A$4957,Fixability!$C$3,Plans!$B$2:$B$4957,$A14)/$B14,"") -> 0.0092530927 | K14: =IFERROR(SUMIFS(Plans!$S$2:$S$4957,Plans!$A$2:$A$4957,Fixability!$C$3,Plans!$B$2:$B$4957,$A14)/$B14,"") -> 0.0021115487 | L14: =IFERROR(SUMIFS(Plans!$T$2:$T$4957,Plans!$A$2:$A$4957,Fixability!$C$3,Plans!$B$2:$B$4957,$A14)/$B14,"") -> 0.042494593 | M14: =IFERROR(SUMIFS(Plans!$U$2:$U$4957,Plans!$A$2:$A$4957,Fixability!$C$3,Plans!$B$2:$B$4957,$A14)/$B14,"") -> 0.046968302 | N14: =IFERROR(SUMIFS(Plans!$V$2:$V$4957,Plans!$A$2:$A$4957,Fixability!$C$3,Plans!$B$2:$B$4957,$A14)/$B14,"") -> 0.049233339 | O14: =IFERROR(SUMIFS(Plans!$W$2:$W$4957,Plans!$A$2:$A$4957,Fixability!$C$3,Plans!$B$2:$B$4957,$A14)/$B14,"") -> 0.026315447 | P14: =IFERROR(SUMIFS(Plans!$X$2:$X$4957,Plans!$A$2:$A$4957,Fixability!$C$3,Plans!$B$2:$B$4957,$A14)/$B14,"") -> 0.11989825 | Q14: =IFERROR(SUMIFS(Plans!$Y$2:$Y$4957,Plans!$A$2:$A$4957,Fixability!$C$3,Plans!$B$2:$B$4957,$A14)/$B14,"") -> 0.0033797787 | R14: =IFERROR(SUMIFS(Plans!$Z$2:$Z$4957,Plans!$A$2:$A$4957,Fixability!$C$3,Plans!$B$2:$B$4957,$A14)/$B14,"") -> 0.5780111
A15: MS | B15: =SUM(C15:G15) -> 2186942 | C15: =SUMIFS(Plans!$AA$2:$AA$4957,Plans!$A$2:$A$4957,Fixability!$C$3,Plans!$B$2:$B$4957,$A15) -> 454259 | D15: =SUMIFS(Plans!$AB$2:$AB$4957,Plans!$A$2:$A$4957,Fixability!$C$3,Plans!$B$2:$B$4957,$A15) -> 217897 | E15: =SUMIFS(Plans!$AC$2:$AC$4957,Plans!$A$2:$A$4957,Fixability!$C$3,Plans!$B$2:$B$4957,$A15) -> 566971 | F15: =SUMIFS(Plans!$AD$2:$AD$4957,Plans!$A$2:$A$4957,Fixability!$C$3,Plans!$B$2:$B$4957,$A15) -> 320572 | G15: =SUMIFS(Plans!$AE$2:$AE$4957,Plans!$A$2:$A$4957,Fixability!$C$3,Plans!$B$2:$B$4957,$A15) -> 627243 | H15: =IFERROR((C15+D15)/B15,"") -> 0.30734971 | I15: =IFERROR(SUMIFS(Plans!$Q$2:$Q$4957,Plans!$A$2:$A$4957,Fixability!$C$3,Plans!$B$2:$B$4957,$A15)/$B15,"") -> 0.20771424 | J15: =IFERROR(SUMIFS(Plans!$R$2:$R$4957,Plans!$A$2:$A$4957,Fixability!$C$3,Plans!$B$2:$B$4957,$A15)/$B15,"") -> 0.084876508 | K15: =IFERROR(SUMIFS(Plans!$S$2:$S$4957,Plans!$A$2:$A$4957,Fixability!$C$3,Plans!$B$2:$B$4957,$A15)/$B15,"") -> 0.014758965 | L15: =IFERROR(SUMIFS(Plans!$T$2:$T$4957,Plans!$A$2:$A$4957,Fixability!$C$3,Plans!$B$2:$B$4957,$A15)/$B15,"") -> 0.077963659 | M15: =IFERROR(SUMIFS(Plans!$U$2:$U$4957,Plans!$A$2:$A$4957,Fixability!$C$3,Plans!$B$2:$B$4957,$A15)/$B15,"") -> 0.07327995 | N15: =IFERROR(SUMIFS(Plans!$V$2:$V$4957,Plans!$A$2:$A$4957,Fixability!$C$3,Plans!$B$2:$B$4957,$A15)/$B15,"") -> 0.10800927 | O15: =IFERROR(SUMIFS(Plans!$W$2:$W$4957,Plans!$A$2:$A$4957,Fixability!$C$3,Plans!$B$2:$B$4957,$A15)/$B15,"") -> 0.046530726 | P15: =IFERROR(SUMIFS(Plans!$X$2:$X$4957,Plans!$A$2:$A$4957,Fixability!$C$3,Plans!$B$2:$B$4957,$A15)/$B15,"") -> 0.1000278 | Q15: =IFERROR(SUMIFS(Plans!$Y$2:$Y$4957,Plans!$A$2:$A$4957,Fixability!$C$3,Plans!$B$2:$B$4957,$A15)/$B15,"") -> 2.6063791e-05 | R15: =IFERROR(SUMIFS(Plans!$Z$2:$Z$4957,Plans!$A$2:$A$4957,Fixability!$C$3,Plans!$B$2:$B$4957,$A15)/$B15,"") -> 0.28681282
A16: MO | B16: =SUM(C16:G16) -> 1823967 | C16: =SUMIFS(Plans!$AA$2:$AA$4957,Plans!$A$2:$A$4957,Fixability!$C$3,Plans!$B$2:$B$4957,$A16) -> 456519 | D16: =SUMIFS(Plans!$AB$2:$AB$4957,Plans!$A$2:$A$4957,Fixability!$C$3,Plans!$B$2:$B$4957,$A16) -> 127816 | E16: =SUMIFS(Plans!$AC$2:$AC$4957,Plans!$A$2:$A$4957,Fixability!$C$3,Plans!$B$2:$B$4957,$A16) -> 683065 | F16: =SUMIFS(Plans!$AD$2:$AD$4957,Plans!$A$2:$A$4957,Fixability!$C$3,Plans!$B$2:$B$4957,$A16) -> 331656 | G16: =SUMIFS(Plans!$AE$2:$AE$4957,Plans!$A$2:$A$4957,Fixability!$C$3,Plans!$B$2:$B$4957,$A16) -> 224911 | H16: =IFERROR((C16+D16)/B16,"") -> 0.3203649 | I16: =IFERROR(SUMIFS(Plans!$Q$2:$Q$4957,Plans!$A$2:$A$4957,Fixability!$C$3,Plans!$B$2:$B$4957,$A16)/$B16,"") -> 0.25028907 | J16: =IFERROR(SUMIFS(Plans!$R$2:$R$4957,Plans!$A$2:$A$4957,Fixability!$C$3,Plans!$B$2:$B$4957,$A16)/$B16,"") -> 0.067477646 | K16: =IFERROR(SUMIFS(Plans!$S$2:$S$4957,Plans!$A$2:$A$4957,Fixability!$C$3,Plans!$B$2:$B$4957,$A16)/$B16,"") -> 0.002598183 | L16: =IFERROR(SUMIFS(Plans!$T$2:$T$4957,Plans!$A$2:$A$4957,Fixability!$C$3,Plans!$B$2:$B$4957,$A16)/$B16,"") -> 0.11255851 | M16: =IFERROR(SUMIFS(Plans!$U$2:$U$4957,Plans!$A$2:$A$4957,Fixability!$C$3,Plans!$B$2:$B$4957,$A16)/$B16,"") -> 0.095611927 | N16: =IFERROR(SUMIFS(Plans!$V$2:$V$4957,Plans!$A$2:$A$4957,Fixability!$C$3,Plans!$B$2:$B$4957,$A16)/$B16,"") -> 0.16632373 | O16: =IFERROR(SUMIFS(Plans!$W$2:$W$4957,Plans!$A$2:$A$4957,Fixability!$C$3,Plans!$B$2:$B$4957,$A16)/$B16,"") -> 0.054354602 | P16: =IFERROR(SUMIFS(Plans!$X$2:$X$4957,Plans!$A$2:$A$4957,Fixability!$C$3,Plans!$B$2:$B$4957,$A16)/$B16,"") -> 0.12714265 | Q16: =IFERROR(SUMIFS(Plans!$Y$2:$Y$4957,Plans!$A$2:$A$4957,Fixability!$C$3,Plans!$B$2:$B$4957,$A16)/$B16,"") -> 0.00033498413 | R16: =IFERROR(SUMIFS(Plans!$Z$2:$Z$4957,Plans!$A$2:$A$4957,Fixability!$C$3,Plans!$B$2:$B$4957,$A16)/$B16,"") -> 0.1233087
... A34: ND | B34: =SUM(C34:G34) -> 156713 | C34: =SUMIFS(Plans!$AA$2:$AA$4957,Plans!$A$2:$A$4957,Fixability!$C$3,Plans!$B$2:$B$4957,$A34) -> 10624 | D34: =SUMIFS(Plans!$AB$2:$AB$4957,Plans!$A$2:$A$4957,Fixability!$C$3,Plans!$B$2:$B$4957,$A34) -> 30484 | E34: =SUMIFS(Plans!$AC$2:$AC$4957,Plans!$A$2:$A$4957,Fixability!$C$3,Plans!$B$2:$B$4957,$A34) -> 22214 | F34: =SUMIFS(Plans!$AD$2:$AD$4957,Plans!$A$2:$A$4957,Fixability!$C$3,Plans!$B$2:$B$4957,$A34) -> 8530 | G34: =SUMIFS(Plans!$AE$2:$AE$4957,Plans!$A$2:$A$4957,Fixability!$C$3,Plans!$B$2:$B$4957,$A34) -> 84861 | H34: =IFERROR((C34+D34)/B34,"") -> 0.26231391 | I34: =IFERROR(SUMIFS(Plans!$Q$2:$Q$4957,Plans!$A$2:$A$4957,Fixability!$C$3,Plans!$B$2:$B$4957,$A34)/$B34,"") -> 0.067792717 | J34: =IFERROR(SUMIFS(Plans!$R$2:$R$4957,Plans!$A$2:$A$4957,Fixability!$C$3,Plans!$B$2:$B$4957,$A34)/$B34,"") -> 0.16911807 | K34: =IFERROR(SUMIFS(Plans!$S$2:$S$4957,Plans!$A$2:$A$4957,Fixability!$C$3,Plans!$B$2:$B$4957,$A34)/$B34,"") -> 0.025403125 | L34: =IFERROR(SUMIFS(Plans!$T$2:$T$4957,Plans!$A$2:$A$4957,Fixability!$C$3,Plans!$B$2:$B$4957,$A34)/$B34,"") -> 0.024624632 | M34: =IFERROR(SUMIFS(Plans!$U$2:$U$4957,Plans!$A$2:$A$4957,Fixability!$C$3,Plans!$B$2:$B$4957,$A34)/$B34,"") -> 0.029965606 | N34: =IFERROR(SUMIFS(Plans!$V$2:$V$4957,Plans!$A$2:$A$4957,Fixability!$C$3,Plans!$B$2:$B$4957,$A34)/$B34,"") -> 0.087159329 | O34: =IFERROR(SUMIFS(Plans!$W$2:$W$4957,Plans!$A$2:$A$4957,Fixability!$C$3,Plans!$B$2:$B$4957,$A34)/$B34,"") -> 0.016022921 | P34: =IFERROR(SUMIFS(Plans!$X$2:$X$4957,Plans!$A$2:$A$4957,Fixability!$C$3,Plans!$B$2:$B$4957,$A34)/$B34,"") -> 0.032039461 | Q34: =IFERROR(SUMIFS(Plans!$Y$2:$Y$4957,Plans!$A$2:$A$4957,Fixability!$C$3,Plans!$B$2:$B$4957,$A34)/$B34,"") -> 0.0063683294 | R34: =IFERROR(SUMIFS(Plans!$Z$2:$Z$4957,Plans!$A$2:$A$4957,Fixability!$C$3,Plans!$B$2:$B$4957,$A34)/$B34,"") -> 0.54150581
A35: All | B35: =SUM(B5:B34) -> 87173324 | C35: =SUM(C5:C34) -> 19612209 | D35: =SUM(D5:D34) -> 3968921 | E35: =SUM(E5:E34) -> 21601333 | F35: =SUM(F5:F34) -> 13877230 | G35: =SUM(G5:G34) -> 28113631 | H35: =IFERROR((C35+D35)/B35,"") -> 0.27050856 | I35: =IFERROR(SUMIFS(Plans!$Q$2:$Q$4957,Plans!$A$2:$A$4957,Fixability!$C$3)/$B35,"") -> 0.22497948 | J35: =IFERROR(SUMIFS(Plans!$R$2:$R$4957,Plans!$A$2:$A$4957,Fixability!$C$3)/$B35,"") -> 0.041234254 | K35: =IFERROR(SUMIFS(Plans!$S$2:$S$4957,Plans!$A$2:$A$4957,Fixability!$C$3)/$B35,"") -> 0.004294823 | L35: =IFERROR(SUMIFS(Plans!$T$2:$T$4957,Plans!$A$2:$A$4957,Fixability!$C$3)/$B35,"") -> 0.083794556 | M35: =IFERROR(SUMIFS(Plans!$U$2:$U$4957,Plans!$A$2:$A$4957,Fixability!$C$3)/$B35,"") -> 0.065720885 | N35: =IFERROR(SUMIFS(Plans!$V$2:$V$4957,Plans!$A$2:$A$4957,Fixability!$C$3)/$B35,"") -> 0.098282073 | O35: =IFERROR(SUMIFS(Plans!$W$2:$W$4957,Plans!$A$2:$A$4957,Fixability!$C$3)/$B35,"") -> 0.041830538 | P35: =IFERROR(SUMIFS(Plans!$X$2:$X$4957,Plans!$A$2:$A$4957,Fixability!$C$3)/$B35,"") -> 0.11619508 | Q35: =IFERROR(SUMIFS(Plans!$Y$2:$Y$4957,Plans!$A$2:$A$4957,Fixability!$C$3)/$B35,"") -> 0.0011656318 | R35: =IFERROR(SUMIFS(Plans!$Z$2:$Z$4957,Plans!$A$2:$A$4957,Fixability!$C$3)/$B35,"") -> 0.32250268

Sheet By Plan Type
A1: Denial reasons by Plan Type — market: | D1: =Fixability!$C$3 -> Individual Medical
A2: Counts by fixability tier, then each reason as a share of that row's classified denials. Change the market on the Fixability tab.
A4: Plan Type | B4: Denials With Reason | C4: Tier 1 High | D4: Tier 2 Medium-High | E4: Tier 3 Medium | F4: Tier 4 Low | G4: Tier 5 Unknown | H4: % Fixable (High + Med-High) | I4: % Administrative | J4: % Not medically necessary (medical) | K4: % Not medically necessary (behavioral health) | L4: % Referral required | M4: % Member not covered | N4: % Out-of-network | O4: % Benefit limit reached | P4: % Service excluded | Q4: % Experimental / cosmetic | R4: % Other / unspecified
A5: PPO | B5: =SUM(C5:G5) -> 10772145 | C5: =SUMIFS(Plans!$AA$2:$AA$4957,Plans!$A$2:$A$4957,Fixability!$C$3,Plans!$G$2:$G$4957,$A5) -> 2451175 | D5: =SUMIFS(Plans!$AB$2:$AB$4957,Plans!$A$2:$A$4957,Fixability!$C$3,Plans!$G$2:$G$4957,$A5) -> 354899 | E5: =SUMIFS(Plans!$AC$2:$AC$4957,Plans!$A$2:$A$4957,Fixability!$C$3,Plans!$G$2:$G$4957,$A5) -> 2376345 | F5: =SUMIFS(Plans!$AD$2:$AD$4957,Plans!$A$2:$A$4957,Fixability!$C$3,Plans!$G$2:$G$4957,$A5) -> 2700208 | G5: =SUMIFS(Plans!$AE$2:$AE$4957,Plans!$A$2:$A$4957,Fixability!$C$3,Plans!$G$2:$G$4957,$A5) -> 2889518 | H5: =IFERROR((C5+D5)/B5,"") -> 0.26049352 | I5: =IFERROR(SUMIFS(Plans!$Q$2:$Q$4957,Plans!$A$2:$A$4957,Fixability!$C$3,Plans!$G$2:$G$4957,$A5)/$B5,"") -> 0.22754753 | J5: =IFERROR(SUMIFS(Plans!$R$2:$R$4957,Plans!$A$2:$A$4957,Fixability!$C$3,Plans!$G$2:$G$4957,$A5)/$B5,"") -> 0.030848267 | K5: =IFERROR(SUMIFS(Plans!$S$2:$S$4957,Plans!$A$2:$A$4957,Fixability!$C$3,Plans!$G$2:$G$4957,$A5)/$B5,"") -> 0.0020977252 | L5: =IFERROR(SUMIFS(Plans!$T$2:$T$4957,Plans!$A$2:$A$4957,Fixability!$C$3,Plans!$G$2:$G$4957,$A5)/$B5,"") -> 0.079689328 | M5: =IFERROR(SUMIFS(Plans!$U$2:$U$4957,Plans!$A$2:$A$4957,Fixability!$C$3,Plans!$G$2:$G$4957,$A5)/$B5,"") -> 0.11043065 | N5: =IFERROR(SUMIFS(Plans!$V$2:$V$4957,Plans!$A$2:$A$4957,Fixability!$C$3,Plans!$G$2:$G$4957,$A5)/$B5,"") -> 0.03048093 | O5: =IFERROR(SUMIFS(Plans!$W$2:$W$4957,Plans!$A$2:$A$4957,Fixability!$C$3,Plans!$G$2:$G$4957,$A5)/$B5,"") -> 0.088521367 | P5: =IFERROR(SUMIFS(Plans!$X$2:$X$4957,Plans!$A$2:$A$4957,Fixability!$C$3,Plans!$G$2:$G$4957,$A5)/$B5,"") -> 0.16091902 | Q5: =IFERROR(SUMIFS(Plans!$Y$2:$Y$4957,Plans!$A$2:$A$4957,Fixability!$C$3,Plans!$G$2:$G$4957,$A5)/$B5,"") -> 0.0012253827 | R5: =IFERROR(SUMIFS(Plans!$Z$2:$Z$4957,Plans!$A$2:$A$4957,Fixability!$C$3,Plans!$G$2:$G$4957,$A5)/$B5,"") -> 0.2682398
A6: EPO | B6: =SUM(C6:G6) -> 24537628 | C6: =SUMIFS(Plans!$AA$2:$AA$4957,Plans!$A$2:$A$4957,Fixability!$C$3,Plans!$G$2:$G$4957,$A6) -> 6620195 | D6: =SUMIFS(Plans!$AB$2:$AB$4957,Plans!$A$2:$A$4957,Fixability!$C$3,Plans!$G$2:$G$4957,$A6) -> 1371995 | E6: =SUMIFS(Plans!$AC$2:$AC$4957,Plans!$A$2:$A$4957,Fixability!$C$3,Plans!$G$2:$G$4957,$A6) -> 6722238 | F6: =SUMIFS(Plans!$AD$2:$AD$4957,Plans!$A$2:$A$4957,Fixability!$C$3,Plans!$G$2:$G$4957,$A6) -> 3476768 | G6: =SUMIFS(Plans!$AE$2:$AE$4957,Plans!$A$2:$A$4957,Fixability!$C$3,Plans!$G$2:$G$4957,$A6) -> 6346432 | H6: =IFERROR((C6+D6)/B6,"") -> 0.3257116 | I6: =IFERROR(SUMIFS(Plans!$Q$2:$Q$4957,Plans!$A$2:$A$4957,Fixability!$C$3,Plans!$G$2:$G$4957,$A6)/$B6,"") -> 0.26979768 | J6: =IFERROR(SUMIFS(Plans!$R$2:$R$4957,Plans!$A$2:$A$4957,Fixability!$C$3,Plans!$G$2:$G$4957,$A6)/$B6,"") -> 0.049585681 | K6: =IFERROR(SUMIFS(Plans!$S$2:$S$4957,Plans!$A$2:$A$4957,Fixability!$C$3,Plans!$G$2:$G$4957,$A6)/$B6,"") -> 0.00632824 | L6: =IFERROR(SUMIFS(Plans!$T$2:$T$4957,Plans!$A$2:$A$4957,Fixability!$C$3,Plans!$G$2:$G$4957,$A6)/$B6,"") -> 0.079846878 | M6: =IFERROR(SUMIFS(Plans!$U$2:$U$4957,Plans!$A$2:$A$4957,Fixability!$C$3,Plans!$G$2:$G$4957,$A6)/$B6,"") -> 0.065781012 | N6: =IFERROR(SUMIFS(Plans!$V$2:$V$4957,Plans!$A$2:$A$4957,Fixability!$C$3,Plans!$G$2:$G$4957,$A6)/$B6,"") -> 0.12832842 | O6: =IFERROR(SUMIFS(Plans!$W$2:$W$4957,Plans!$A$2:$A$4957,Fixability!$C$3,Plans!$G$2:$G$4957,$A6)/$B6,"") -> 0.048131343 | P6: =IFERROR(SUMIFS(Plans!$X$2:$X$4957,Plans!$A$2:$A$4957,Fixability!$C$3,Plans!$G$2:$G$4957,$A6)/$B6,"") -> 0.092945088 | Q6: =IFERROR(SUMIFS(Plans!$Y$2:$Y$4957,Plans!$A$2:$A$4957,Fixability!$C$3,Plans!$G$2:$G$4957,$A6)/$B6,"") -> 0.00061485161 | R6: =IFERROR(SUMIFS(Plans!$Z$2:$Z$4957,Plans!$A$2:$A$4957,Fixability!$C$3,Plans!$G$2:$G$4957,$A6)/$B6,"") -> 0.25864081
A7: HMO | B7: =SUM(C7:G7) -> 48033806 | C7: =SUMIFS(Plans!$AA$2:$AA$4957,Plans!$A$2:$A$4957,Fixability!$C$3,Plans!$G$2:$G$4957,$A7) -> 9736506 | D7: =SUMIFS(Plans!$AB$2:$AB$4957,Plans!$A$2:$A$4957,Fixability!$C$3,Plans!$G$2:$G$4957,$A7) -> 2189272 | E7: =SUMIFS(Plans!$AC$2:$AC$4957,Plans!$A$2:$A$4957,Fixability!$C$3,Plans!$G$2:$G$4957,$A7) -> 12021127 | F7: =SUMIFS(Plans!$AD$2:$AD$4957,Plans!$A$2:$A$4957,Fixability!$C$3,Plans!$G$2:$G$4957,$A7) -> 7130628 | G7: =SUMIFS(Plans!$AE$2:$AE$4957,Plans!$A$2:$A$4957,Fixability!$C$3,Plans!$G$2:$G$4957,$A7) -> 16956273 | H7: =IFERROR((C7+D7)/B7,"") -> 0.24827885 | I7: =IFERROR(SUMIFS(Plans!$Q$2:$Q$4957,Plans!$A$2:$A$4957,Fixability!$C$3,Plans!$G$2:$G$4957,$A7)/$B7,"") -> 0.20270111 | J7: =IFERROR(SUMIFS(Plans!$R$2:$R$4957,Plans!$A$2:$A$4957,Fixability!$C$3,Plans!$G$2:$G$4957,$A7)/$B7,"") -> 0.04160016 | K7: =IFERROR(SUMIFS(Plans!$S$2:$S$4957,Plans!$A$2:$A$4957,Fixability!$C$3,Plans!$G$2:$G$4957,$A7)/$B7,"") -> 0.0039775736 | L7: =IFERROR(SUMIFS(Plans!$T$2:$T$4957,Plans!$A$2:$A$4957,Fixability!$C$3,Plans!$G$2:$G$4957,$A7)/$B7,"") -> 0.090829176 | M7: =IFERROR(SUMIFS(Plans!$U$2:$U$4957,Plans!$A$2:$A$4957,Fixability!$C$3,Plans!$G$2:$G$4957,$A7)/$B7,"") -> 0.054448652 | N7: =IFERROR(SUMIFS(Plans!$V$2:$V$4957,Plans!$A$2:$A$4957,Fixability!$C$3,Plans!$G$2:$G$4957,$A7)/$B7,"") -> 0.10498606 | O7: =IFERROR(SUMIFS(Plans!$W$2:$W$4957,Plans!$A$2:$A$4957,Fixability!$C$3,Plans!$G$2:$G$4957,$A7)/$B7,"") -> 0.028257036 | P7: =IFERROR(SUMIFS(Plans!$X$2:$X$4957,Plans!$A$2:$A$4957,Fixability!$C$3,Plans!$G$2:$G$4957,$A7)/$B7,"") -> 0.1187222 | Q7: =IFERROR(SUMIFS(Plans!$Y$2:$Y$4957,Plans!$A$2:$A$4957,Fixability!$C$3,Plans!$G$2:$G$4957,$A7)/$B7,"") -> 0.001470964 | R7: =IFERROR(SUMIFS(Plans!$Z$2:$Z$4957,Plans!$A$2:$A$4957,Fixability!$C$3,Plans!$G$2:$G$4957,$A7)/$B7,"") -> 0.35300707
A8: POS | B8: =SUM(C8:G8) -> 3829745 | C8: =SUMIFS(Plans!$AA$2:$AA$4957,Plans!$A$2:$A$4957,Fixability!$C$3,Plans!$G$2:$G$4957,$A8) -> 804333 | D8: =SUMIFS(Plans!$AB$2:$AB$4957,Plans!$A$2:$A$4957,Fixability!$C$3,Plans!$G$2:$G$4957,$A8) -> 52755 | E8: =SUMIFS(Plans!$AC$2:$AC$4957,Plans!$A$2:$A$4957,Fixability!$C$3,Plans!$G$2:$G$4957,$A8) -> 481623 | F8: =SUMIFS(Plans!$AD$2:$AD$4957,Plans!$A$2:$A$4957,Fixability!$C$3,Plans!$G$2:$G$4957,$A8) -> 569626 | G8: =SUMIFS(Plans!$AE$2:$AE$4957,Plans!$A$2:$A$4957,Fixability!$C$3,Plans!$G$2:$G$4957,$A8) -> 1921408 | H8: =IFERROR((C8+D8)/B8,"") -> 0.22379767 | I8: =IFERROR(SUMIFS(Plans!$Q$2:$Q$4957,Plans!$A$2:$A$4957,Fixability!$C$3,Plans!$G$2:$G$4957,$A8)/$B8,"") -> 0.2100226 | J8: =IFERROR(SUMIFS(Plans!$R$2:$R$4957,Plans!$A$2:$A$4957,Fixability!$C$3,Plans!$G$2:$G$4957,$A8)/$B8,"") -> 0.012349647 | K8: =IFERROR(SUMIFS(Plans!$S$2:$S$4957,Plans!$A$2:$A$4957,Fixability!$C$3,Plans!$G$2:$G$4957,$A8)/$B8,"") -> 0.0014254213 | L8: =IFERROR(SUMIFS(Plans!$T$2:$T$4957,Plans!$A$2:$A$4957,Fixability!$C$3,Plans!$G$2:$G$4957,$A8)/$B8,"") -> 0.032404507 | M8: =IFERROR(SUMIFS(Plans!$U$2:$U$4957,Plans!$A$2:$A$4957,Fixability!$C$3,Plans!$G$2:$G$4957,$A8)/$B8,"") -> 0.080957609 | N8: =IFERROR(SUMIFS(Plans!$V$2:$V$4957,Plans!$A$2:$A$4957,Fixability!$C$3,Plans!$G$2:$G$4957,$A8)/$B8,"") -> 0.012396387 | O8: =IFERROR(SUMIFS(Plans!$W$2:$W$4957,Plans!$A$2:$A$4957,Fixability!$C$3,Plans!$G$2:$G$4957,$A8)/$B8,"") -> 0.040373445 | P8: =IFERROR(SUMIFS(Plans!$X$2:$X$4957,Plans!$A$2:$A$4957,Fixability!$C$3,Plans!$G$2:$G$4957,$A8)/$B8,"") -> 0.10766696 | Q8: =IFERROR(SUMIFS(Plans!$Y$2:$Y$4957,Plans!$A$2:$A$4957,Fixability!$C$3,Plans!$G$2:$G$4957,$A8)/$B8,"") -> 0.00069691324 | R8: =IFERROR(SUMIFS(Plans!$Z$2:$Z$4957,Plans!$A$2:$A$4957,Fixability!$C$3,Plans!$G$2:$G$4957,$A8)/$B8,"") -> 0.50170651
A9: Indemnity | B9: =SUM(C9:G9) -> 0 | C9: =SUMIFS(Plans!$AA$2:$AA$4957,Plans!$A$2:$A$4957,Fixability!$C$3,Plans!$G$2:$G$4957,$A9) -> 0 | D9: =SUMIFS(Plans!$AB$2:$AB$4957,Plans!$A$2:$A$4957,Fixability!$C$3,Plans!$G$2:$G$4957,$A9) -> 0 | E9: =SUMIFS(Plans!$AC$2:$AC$4957,Plans!$A$2:$A$4957,Fixability!$C$3,Plans!$G$2:$G$4957,$A9) -> 0 | F9: =SUMIFS(Plans!$AD$2:$AD$4957,Plans!$A$2:$A$4957,Fixability!$C$3,Plans!$G$2:$G$4957,$A9) -> 0 | G9: =SUMIFS(Plans!$AE$2:$AE$4957,Plans!$A$2:$A$4957,Fixability!$C$3,Plans!$G$2:$G$4957,$A9) -> 0 | H9: =IFERROR((C9+D9)/B9,"") | I9: =IFERROR(SUMIFS(Plans!$Q$2:$Q$4957,Plans!$A$2:$A$4957,Fixability!$C$3,Plans!$G$2:$G$4957,$A9)/$B9,"") | J9: =IFERROR(SUMIFS(Plans!$R$2:$R$4957,Plans!$A$2:$A$4957,Fixability!$C$3,Plans!$G$2:$G$4957,$A9)/$B9,"") | K9: =IFERROR(SUMIFS(Plans!$S$2:$S$4957,Plans!$A$2:$A$4957,Fixability!$C$3,Plans!$G$2:$G$4957,$A9)/$B9,"") | L9: =IFERROR(SUMIFS(Plans!$T$2:$T$4957,Plans!$A$2:$A$4957,Fixability!$C$3,Plans!$G$2:$G$4957,$A9)/$B9,"") | M9: =IFERROR(SUMIFS(Plans!$U$2:$U$4957,Plans!$A$2:$A$4957,Fixability!$C$3,Plans!$G$2:$G$4957,$A9)/$B9,"") | N9: =IFERROR(SUMIFS(Plans!$V$2:$V$4957,Plans!$A$2:$A$4957,Fixability!$C$3,Plans!$G$2:$G$4957,$A9)/$B9,"") | O9: =IFERROR(SUMIFS(Plans!$W$2:$W$4957,Plans!$A$2:$A$4957,Fixability!$C$3,Plans!$G$2:$G$4957,$A9)/$B9,"") | P9: =IFERROR(SUMIFS(Plans!$X$2:$X$4957,Plans!$A$2:$A$4957,Fixability!$C$3,Plans!$G$2:$G$4957,$A9)/$B9,"") | Q9: =IFERROR(SUMIFS(Plans!$Y$2:$Y$4957,Plans!$A$2:$A$4957,Fixability!$C$3,Plans!$G$2:$G$4957,$A9)/$B9,"") | R9: =IFERROR(SUMIFS(Plans!$Z$2:$Z$4957,Plans!$A$2:$A$4957,Fixability!$C$3,Plans!$G$2:$G$4957,$A9)/$B9,"")
A10: All | B10: =SUM(B5:B9) -> 87173324 | C10: =SUM(C5:C9) -> 19612209 | D10: =SUM(D5:D9) -> 3968921 | E10: =SUM(E5:E9) -> 21601333 | F10: =SUM(F5:F9) -> 13877230 | G10: =SUM(G5:G9) -> 28113631 | H10: =IFERROR((C10+D10)/B10,"") -> 0.27050856 | I10: =IFERROR(SUMIFS(Plans!$Q$2:$Q$4957,Plans!$A$2:$A$4957,Fixability!$C$3)/$B10,"") -> 0.22497948 | J10: =IFERROR(SUMIFS(Plans!$R$2:$R$4957,Plans!$A$2:$A$4957,Fixability!$C$3)/$B10,"") -> 0.041234254 | K10: =IFERROR(SUMIFS(Plans!$S$2:$S$4957,Plans!$A$2:$A$4957,Fixability!$C$3)/$B10,"") -> 0.004294823 | L10: =IFERROR(SUMIFS(Plans!$T$2:$T$4957,Plans!$A$2:$A$4957,Fixability!$C$3)/$B10,"") -> 0.083794556 | M10: =IFERROR(SUMIFS(Plans!$U$2:$U$4957,Plans!$A$2:$A$4957,Fixability!$C$3)/$B10,"") -> 0.065720885 | N10: =IFERROR(SUMIFS(Plans!$V$2:$V$4957,Plans!$A$2:$A$4957,Fixability!$C$3)/$B10,"") -> 0.098282073 | O10: =IFERROR(SUMIFS(Plans!$W$2:$W$4957,Plans!$A$2:$A$4957,Fixability!$C$3)/$B10,"") -> 0.041830538 | P10: =IFERROR(SUMIFS(Plans!$X$2:$X$4957,Plans!$A$2:$A$4957,Fixability!$C$3)/$B10,"") -> 0.11619508 | Q10: =IFERROR(SUMIFS(Plans!$Y$2:$Y$4957,Plans!$A$2:$A$4957,Fixability!$C$3)/$B10,"") -> 0.0011656318 | R10: =IFERROR(SUMIFS(Plans!$Z$2:$Z$4957,Plans!$A$2:$A$4957,Fixability!$C$3)/$B10,"") -> 0.32250268

Sheet By Metal Level
A1: Denial reasons by Metal Level — market: | D1: =Fixability!$C$3 -> Individual Medical
A2: Counts by fixability tier, then each reason as a share of that row's classified denials. Change the market on the Fixability tab.
A4: Metal Level | B4: Denials With Reason | C4: Tier 1 High | D4: Tier 2 Medium-High | E4: Tier 3 Medium | F4: Tier 4 Low | G4: Tier 5 Unknown | H4: % Fixable (High + Med-High) | I4: % Administrative | J4: % Not medically necessary (medical) | K4: % Not medically necessary (behavioral health) | L4: % Referral required | M4: % Member not covered | N4: % Out-of-network | O4: % Benefit limit reached | P4: % Service excluded | Q4: % Experimental / cosmetic | R4: % Other / unspecified
A5: Bronze | B5: =SUM(C5:G5) -> 21903982 | C5: =SUMIFS(Plans!$AA$2:$AA$4957,Plans!$A$2:$A$4957,Fixability!$C$3,Plans!$H$2:$H$4957,$A5) -> 5505622 | D5: =SUMIFS(Plans!$AB$2:$AB$4957,Plans!$A$2:$A$4957,Fixability!$C$3,Plans!$H$2:$H$4957,$A5) -> 680817 | E5: =SUMIFS(Plans!$AC$2:$AC$4957,Plans!$A$2:$A$4957,Fixability!$C$3,Plans!$H$2:$H$4957,$A5) -> 5818565 | F5: =SUMIFS(Plans!$AD$2:$AD$4957,Plans!$A$2:$A$4957,Fixability!$C$3,Plans!$H$2:$H$4957,$A5) -> 3042801 | G5: =SUMIFS(Plans!$AE$2:$AE$4957,Plans!$A$2:$A$4957,Fixability!$C$3,Plans!$H$2:$H$4957,$A5) -> 6856177 | H5: =IFERROR((C5+D5)/B5,"") -> 0.28243445 | I5: =IFERROR(SUMIFS(Plans!$Q$2:$Q$4957,Plans!$A$2:$A$4957,Fixability!$C$3,Plans!$H$2:$H$4957,$A5)/$B5,"") -> 0.25135256 | J5: =IFERROR(SUMIFS(Plans!$R$2:$R$4957,Plans!$A$2:$A$4957,Fixability!$C$3,Plans!$H$2:$H$4957,$A5)/$B5,"") -> 0.027512167 | K5: =IFERROR(SUMIFS(Plans!$S$2:$S$4957,Plans!$A$2:$A$4957,Fixability!$C$3,Plans!$H$2:$H$4957,$A5)/$B5,"") -> 0.0035697162 | L5: =IFERROR(SUMIFS(Plans!$T$2:$T$4957,Plans!$A$2:$A$4957,Fixability!$C$3,Plans!$H$2:$H$4957,$A5)/$B5,"") -> 0.06708141 | M5: =IFERROR(SUMIFS(Plans!$U$2:$U$4957,Plans!$A$2:$A$4957,Fixability!$C$3,Plans!$H$2:$H$4957,$A5)/$B5,"") -> 0.070291237 | N5: =IFERROR(SUMIFS(Plans!$V$2:$V$4957,Plans!$A$2:$A$4957,Fixability!$C$3,Plans!$H$2:$H$4957,$A5)/$B5,"") -> 0.12826695 | O5: =IFERROR(SUMIFS(Plans!$W$2:$W$4957,Plans!$A$2:$A$4957,Fixability!$C$3,Plans!$H$2:$H$4957,$A5)/$B5,"") -> 0.033215787 | P5: =IFERROR(SUMIFS(Plans!$X$2:$X$4957,Plans!$A$2:$A$4957,Fixability!$C$3,Plans!$H$2:$H$4957,$A5)/$B5,"") -> 0.10482478 | Q5: =IFERROR(SUMIFS(Plans!$Y$2:$Y$4957,Plans!$A$2:$A$4957,Fixability!$C$3,Plans!$H$2:$H$4957,$A5)/$B5,"") -> 0.00087486376 | R5: =IFERROR(SUMIFS(Plans!$Z$2:$Z$4957,Plans!$A$2:$A$4957,Fixability!$C$3,Plans!$H$2:$H$4957,$A5)/$B5,"") -> 0.31301053
A6: Silver | B6: =SUM(C6:G6) -> 52457939 | C6: =SUMIFS(Plans!$AA$2:$AA$4957,Plans!$A$2:$A$4957,Fixability!$C$3,Plans!$H$2:$H$4957,$A6) -> 12097390 | D6: =SUMIFS(Plans!$AB$2:$AB$4957,Plans!$A$2:$A$4957,Fixability!$C$3,Plans!$H$2:$H$4957,$A6) -> 2743383 | E6: =SUMIFS(Plans!$AC$2:$AC$4957,Plans!$A$2:$A$4957,Fixability!$C$3,Plans!$H$2:$H$4957,$A6) -> 12740161 | F6: =SUMIFS(Plans!$AD$2:$AD$4957,Plans!$A$2:$A$4957,Fixability!$C$3,Plans!$H$2:$H$4957,$A6) -> 8582811 | G6: =SUMIFS(Plans!$AE$2:$AE$4957,Plans!$A$2:$A$4957,Fixability!$C$3,Plans!$H$2:$H$4957,$A6) -> 16294194 | H6: =IFERROR((C6+D6)/B6,"") -> 0.28290805 | I6: =IFERROR(SUMIFS(Plans!$Q$2:$Q$4957,Plans!$A$2:$A$4957,Fixability!$C$3,Plans!$H$2:$H$4957,$A6)/$B6,"") -> 0.23061123 | J6: =IFERROR(SUMIFS(Plans!$R$2:$R$4957,Plans!$A$2:$A$4957,Fixability!$C$3,Plans!$H$2:$H$4957,$A6)/$B6,"") -> 0.047540888 | K6: =IFERROR(SUMIFS(Plans!$S$2:$S$4957,Plans!$A$2:$A$4957,Fixability!$C$3,Plans!$H$2:$H$4957,$A6)/$B6,"") -> 0.0047559246 | L6: =IFERROR(SUMIFS(Plans!$T$2:$T$4957,Plans!$A$2:$A$4957,Fixability!$C$3,Plans!$H$2:$H$4957,$A6)/$B6,"") -> 0.088672756 | M6: =IFERROR(SUMIFS(Plans!$U$2:$U$4957,Plans!$A$2:$A$4957,Fixability!$C$3,Plans!$H$2:$H$4957,$A6)/$B6,"") -> 0.064259349 | N6: =IFERROR(SUMIFS(Plans!$V$2:$V$4957,Plans!$A$2:$A$4957,Fixability!$C$3,Plans!$H$2:$H$4957,$A6)/$B6,"") -> 0.089932203 | O6: =IFERROR(SUMIFS(Plans!$W$2:$W$4957,Plans!$A$2:$A$4957,Fixability!$C$3,Plans!$H$2:$H$4957,$A6)/$B6,"") -> 0.047790231 | P6: =IFERROR(SUMIFS(Plans!$X$2:$X$4957,Plans!$A$2:$A$4957,Fixability!$C$3,Plans!$H$2:$H$4957,$A6)/$B6,"") -> 0.11457362 | Q6: =IFERROR(SUMIFS(Plans!$Y$2:$Y$4957,Plans!$A$2:$A$4957,Fixability!$C$3,Plans!$H$2:$H$4957,$A6)/$B6,"") -> 0.0012493438 | R6: =IFERROR(SUMIFS(Plans!$Z$2:$Z$4957,Plans!$A$2:$A$4957,Fixability!$C$3,Plans!$H$2:$H$4957,$A6)/$B6,"") -> 0.31061445
A7: Gold | B7: =SUM(C7:G7) -> 12352677 | C7: =SUMIFS(Plans!$AA$2:$AA$4957,Plans!$A$2:$A$4957,Fixability!$C$3,Plans!$H$2:$H$4957,$A7) -> 1874771 | D7: =SUMIFS(Plans!$AB$2:$AB$4957,Plans!$A$2:$A$4957,Fixability!$C$3,Plans!$H$2:$H$4957,$A7) -> 542489 | E7: =SUMIFS(Plans!$AC$2:$AC$4957,Plans!$A$2:$A$4957,Fixability!$C$3,Plans!$H$2:$H$4957,$A7) -> 2994015 | F7: =SUMIFS(Plans!$AD$2:$AD$4957,Plans!$A$2:$A$4957,Fixability!$C$3,Plans!$H$2:$H$4957,$A7) -> 2218952 | G7: =SUMIFS(Plans!$AE$2:$AE$4957,Plans!$A$2:$A$4957,Fixability!$C$3,Plans!$H$2:$H$4957,$A7) -> 4722450 | H7: =IFERROR((C7+D7)/B7,"") -> 0.19568714 | I7: =IFERROR(SUMIFS(Plans!$Q$2:$Q$4957,Plans!$A$2:$A$4957,Fixability!$C$3,Plans!$H$2:$H$4957,$A7)/$B7,"") -> 0.15177042 | J7: =IFERROR(SUMIFS(Plans!$R$2:$R$4957,Plans!$A$2:$A$4957,Fixability!$C$3,Plans!$H$2:$H$4957,$A7)/$B7,"") -> 0.040173964 | K7: =IFERROR(SUMIFS(Plans!$S$2:$S$4957,Plans!$A$2:$A$4957,Fixability!$C$3,Plans!$H$2:$H$4957,$A7)/$B7,"") -> 0.0037427515 | L7: =IFERROR(SUMIFS(Plans!$T$2:$T$4957,Plans!$A$2:$A$4957,Fixability!$C$3,Plans!$H$2:$H$4957,$A7)/$B7,"") -> 0.095204546 | M7: =IFERROR(SUMIFS(Plans!$U$2:$U$4957,Plans!$A$2:$A$4957,Fixability!$C$3,Plans!$H$2:$H$4957,$A7)/$B7,"") -> 0.064867963 | N7: =IFERROR(SUMIFS(Plans!$V$2:$V$4957,Plans!$A$2:$A$4957,Fixability!$C$3,Plans!$H$2:$H$4957,$A7)/$B7,"") -> 0.082305317 | O7: =IFERROR(SUMIFS(Plans!$W$2:$W$4957,Plans!$A$2:$A$4957,Fixability!$C$3,Plans!$H$2:$H$4957,$A7)/$B7,"") -> 0.032256085 | P7: =IFERROR(SUMIFS(Plans!$X$2:$X$4957,Plans!$A$2:$A$4957,Fixability!$C$3,Plans!$H$2:$H$4957,$A7)/$B7,"") -> 0.14604292 | Q7: =IFERROR(SUMIFS(Plans!$Y$2:$Y$4957,Plans!$A$2:$A$4957,Fixability!$C$3,Plans!$H$2:$H$4957,$A7)/$B7,"") -> 0.0013342857 | R7: =IFERROR(SUMIFS(Plans!$Z$2:$Z$4957,Plans!$A$2:$A$4957,Fixability!$C$3,Plans!$H$2:$H$4957,$A7)/$B7,"") -> 0.38230175
A8: Platinum | B8: =SUM(C8:G8) -> 398557 | C8: =SUMIFS(Plans!$AA$2:$AA$4957,Plans!$A$2:$A$4957,Fixability!$C$3,Plans!$H$2:$H$4957,$A8) -> 125402 | D8: =SUMIFS(Plans!$AB$2:$AB$4957,Plans!$A$2:$A$4957,Fixability!$C$3,Plans!$H$2:$H$4957,$A8) -> 1116 | E8: =SUMIFS(Plans!$AC$2:$AC$4957,Plans!$A$2:$A$4957,Fixability!$C$3,Plans!$H$2:$H$4957,$A8) -> 21542 | F8: =SUMIFS(Plans!$AD$2:$AD$4957,Plans!$A$2:$A$4957,Fixability!$C$3,Plans!$H$2:$H$4957,$A8) -> 21600 | G8: =SUMIFS(Plans!$AE$2:$AE$4957,Plans!$A$2:$A$4957,Fixability!$C$3,Plans!$H$2:$H$4957,$A8) -> 228897 | H8: =IFERROR((C8+D8)/B8,"") -> 0.31744017 | I8: =IFERROR(SUMIFS(Plans!$Q$2:$Q$4957,Plans!$A$2:$A$4957,Fixability!$C$3,Plans!$H$2:$H$4957,$A8)/$B8,"") -> 0.31464006 | J8: =IFERROR(SUMIFS(Plans!$R$2:$R$4957,Plans!$A$2:$A$4957,Fixability!$C$3,Plans!$H$2:$H$4957,$A8)/$B8,"") -> 0.0020072411 | K8: =IFERROR(SUMIFS(Plans!$S$2:$S$4957,Plans!$A$2:$A$4957,Fixability!$C$3,Plans!$H$2:$H$4957,$A8)/$B8,"") -> 0.00079286024 | L8: =IFERROR(SUMIFS(Plans!$T$2:$T$4957,Plans!$A$2:$A$4957,Fixability!$C$3,Plans!$H$2:$H$4957,$A8)/$B8,"") -> 0.01076634 | M8: =IFERROR(SUMIFS(Plans!$U$2:$U$4957,Plans!$A$2:$A$4957,Fixability!$C$3,Plans!$H$2:$H$4957,$A8)/$B8,"") -> 0.0036080159 | N8: =IFERROR(SUMIFS(Plans!$V$2:$V$4957,Plans!$A$2:$A$4957,Fixability!$C$3,Plans!$H$2:$H$4957,$A8)/$B8,"") -> 0.03967563 | O8: =IFERROR(SUMIFS(Plans!$W$2:$W$4957,Plans!$A$2:$A$4957,Fixability!$C$3,Plans!$H$2:$H$4957,$A8)/$B8,"") -> 0.026074062 | P8: =IFERROR(SUMIFS(Plans!$X$2:$X$4957,Plans!$A$2:$A$4957,Fixability!$C$3,Plans!$H$2:$H$4957,$A8)/$B8,"") -> 0.027188081 | Q8: =IFERROR(SUMIFS(Plans!$Y$2:$Y$4957,Plans!$A$2:$A$4957,Fixability!$C$3,Plans!$H$2:$H$4957,$A8)/$B8,"") -> 0.00093336712 | R8: =IFERROR(SUMIFS(Plans!$Z$2:$Z$4957,Plans!$A$2:$A$4957,Fixability!$C$3,Plans!$H$2:$H$4957,$A8)/$B8,"") -> 0.57431434
A9: Catastrophic | B9: =SUM(C9:G9) -> 60169 | C9: =SUMIFS(Plans!$AA$2:$AA$4957,Plans!$A$2:$A$4957,Fixability!$C$3,Plans!$H$2:$H$4957,$A9) -> 9024 | D9: =SUMIFS(Plans!$AB$2:$AB$4957,Plans!$A$2:$A$4957,Fixability!$C$3,Plans!$H$2:$H$4957,$A9) -> 1116 | E9: =SUMIFS(Plans!$AC$2:$AC$4957,Plans!$A$2:$A$4957,Fixability!$C$3,Plans!$H$2:$H$4957,$A9) -> 27050 | F9: =SUMIFS(Plans!$AD$2:$AD$4957,Plans!$A$2:$A$4957,Fixability!$C$3,Plans!$H$2:$H$4957,$A9) -> 11066 | G9: =SUMIFS(Plans!$AE$2:$AE$4957,Plans!$A$2:$A$4957,Fixability!$C$3,Plans!$H$2:$H$4957,$A9) -> 11913 | H9: =IFERROR((C9+D9)/B9,"") -> 0.16852532 | I9: =IFERROR(SUMIFS(Plans!$Q$2:$Q$4957,Plans!$A$2:$A$4957,Fixability!$C$3,Plans!$H$2:$H$4957,$A9)/$B9,"") -> 0.14997756 | J9: =IFERROR(SUMIFS(Plans!$R$2:$R$4957,Plans!$A$2:$A$4957,Fixability!$C$3,Plans!$H$2:$H$4957,$A9)/$B9,"") -> 0.015755622 | K9: =IFERROR(SUMIFS(Plans!$S$2:$S$4957,Plans!$A$2:$A$4957,Fixability!$C$3,Plans!$H$2:$H$4957,$A9)/$B9,"") -> 0.0027921355 | L9: =IFERROR(SUMIFS(Plans!$T$2:$T$4957,Plans!$A$2:$A$4957,Fixability!$C$3,Plans!$H$2:$H$4957,$A9)/$B9,"") -> 0.056308066 | M9: =IFERROR(SUMIFS(Plans!$U$2:$U$4957,Plans!$A$2:$A$4957,Fixability!$C$3,Plans!$H$2:$H$4957,$A9)/$B9,"") -> 0.26269341 | N9: =IFERROR(SUMIFS(Plans!$V$2:$V$4957,Plans!$A$2:$A$4957,Fixability!$C$3,Plans!$H$2:$H$4957,$A9)/$B9,"") -> 0.13056557 | O9: =IFERROR(SUMIFS(Plans!$W$2:$W$4957,Plans!$A$2:$A$4957,Fixability!$C$3,Plans!$H$2:$H$4957,$A9)/$B9,"") -> 0.052036763 | P9: =IFERROR(SUMIFS(Plans!$X$2:$X$4957,Plans!$A$2:$A$4957,Fixability!$C$3,Plans!$H$2:$H$4957,$A9)/$B9,"") -> 0.13093121 | Q9: =IFERROR(SUMIFS(Plans!$Y$2:$Y$4957,Plans!$A$2:$A$4957,Fixability!$C$3,Plans!$H$2:$H$4957,$A9)/$B9,"") -> 0.00094733168 | R9: =IFERROR(SUMIFS(Plans!$Z$2:$Z$4957,Plans!$A$2:$A$4957,Fixability!$C$3,Plans!$H$2:$H$4957,$A9)/$B9,"") -> 0.19799232
A10: High | B10: =SUM(C10:G10) -> 0 | C10: =SUMIFS(Plans!$AA$2:$AA$4957,Plans!$A$2:$A$4957,Fixability!$C$3,Plans!$H$2:$H$4957,$A10) -> 0 | D10: =SUMIFS(Plans!$AB$2:$AB$4957,Plans!$A$2:$A$4957,Fixability!$C$3,Plans!$H$2:$H$4957,$A10) -> 0 | E10: =SUMIFS(Plans!$AC$2:$AC$4957,Plans!$A$2:$A$4957,Fixability!$C$3,Plans!$H$2:$H$4957,$A10) -> 0 | F10: =SUMIFS(Plans!$AD$2:$AD$4957,Plans!$A$2:$A$4957,Fixability!$C$3,Plans!$H$2:$H$4957,$A10) -> 0 | G10: =SUMIFS(Plans!$AE$2:$AE$4957,Plans!$A$2:$A$4957,Fixability!$C$3,Plans!$H$2:$H$4957,$A10) -> 0 | H10: =IFERROR((C10+D10)/B10,"") | I10: =IFERROR(SUMIFS(Plans!$Q$2:$Q$4957,Plans!$A$2:$A$4957,Fixability!$C$3,Plans!$H$2:$H$4957,$A10)/$B10,"") | J10: =IFERROR(SUMIFS(Plans!$R$2:$R$4957,Plans!$A$2:$A$4957,Fixability!$C$3,Plans!$H$2:$H$4957,$A10)/$B10,"") | K10: =IFERROR(SUMIFS(Plans!$S$2:$S$4957,Plans!$A$2:$A$4957,Fixability!$C$3,Plans!$H$2:$H$4957,$A10)/$B10,"") | L10: =IFERROR(SUMIFS(Plans!$T$2:$T$4957,Plans!$A$2:$A$4957,Fixability!$C$3,Plans!$H$2:$H$4957,$A10)/$B10,"") | M10: =IFERROR(SUMIFS(Plans!$U$2:$U$4957,Plans!$A$2:$A$4957,Fixability!$C$3,Plans!$H$2:$H$4957,$A10)/$B10,"") | N10: =IFERROR(SUMIFS(Plans!$V$2:$V$4957,Plans!$A$2:$A$4957,Fixability!$C$3,Plans!$H$2:$H$4957,$A10)/$B10,"") | O10: =IFERROR(SUMIFS(Plans!$W$2:$W$4957,Plans!$A$2:$A$4957,Fixability!$C$3,Plans!$H$2:$H$4957,$A10)/$B10,"") | P10: =IFERROR(SUMIFS(Plans!$X$2:$X$4957,Plans!$A$2:$A$4957,Fixability!$C$3,Plans!$H$2:$H$4957,$A10)/$B10,"") | Q10: =IFERROR(SUMIFS(Plans!$Y$2:$Y$4957,Plans!$A$2:$A$4957,Fixability!$C$3,Plans!$H$2:$H$4957,$A10)/$B10,"") | R10: =IFERROR(SUMIFS(Plans!$Z$2:$Z$4957,Plans!$A$2:$A$4957,Fixability!$C$3,Plans!$H$2:$H$4957,$A10)/$B10,"")
A11: Low | B11: =SUM(C11:G11) -> 0 | C11: =SUMIFS(Plans!$AA$2:$AA$4957,Plans!$A$2:$A$4957,Fixability!$C$3,Plans!$H$2:$H$4957,$A11) -> 0 | D11: =SUMIFS(Plans!$AB$2:$AB$4957,Plans!$A$2:$A$4957,Fixability!$C$3,Plans!$H$2:$H$4957,$A11) -> 0 | E11: =SUMIFS(Plans!$AC$2:$AC$4957,Plans!$A$2:$A$4957,Fixability!$C$3,Plans!$H$2:$H$4957,$A11) -> 0 | F11: =SUMIFS(Plans!$AD$2:$AD$4957,Plans!$A$2:$A$4957,Fixability!$C$3,Plans!$H$2:$H$4957,$A11) -> 0 | G11: =SUMIFS(Plans!$AE$2:$AE$4957,Plans!$A$2:$A$4957,Fixability!$C$3,Plans!$H$2:$H$4957,$A11) -> 0 | H11: =IFERROR((C11+D11)/B11,"") | I11: =IFERROR(SUMIFS(Plans!$Q$2:$Q$4957,Plans!$A$2:$A$4957,Fixability!$C$3,Plans!$H$2:$H$4957,$A11)/$B11,"") | J11: =IFERROR(SUMIFS(Plans!$R$2:$R$4957,Plans!$A$2:$A$4957,Fixability!$C$3,Plans!$H$2:$H$4957,$A11)/$B11,"") | K11: =IFERROR(SUMIFS(Plans!$S$2:$S$4957,Plans!$A$2:$A$4957,Fixability!$C$3,Plans!$H$2:$H$4957,$A11)/$B11,"") | L11: =IFERROR(SUMIFS(Plans!$T$2:$T$4957,Plans!$A$2:$A$4957,Fixability!$C$3,Plans!$H$2:$H$4957,$A11)/$B11,"") | M11: =IFERROR(SUMIFS(Plans!$U$2:$U$4957,Plans!$A$2:$A$4957,Fixability!$C$3,Plans!$H$2:$H$4957,$A11)/$B11,"") | N11: =IFERROR(SUMIFS(Plans!$V$2:$V$4957,Plans!$A$2:$A$4957,Fixability!$C$3,Plans!$H$2:$H$4957,$A11)/$B11,"") | O11: =IFERROR(SUMIFS(Plans!$W$2:$W$4957,Plans!$A$2:$A$4957,Fixability!$C$3,Plans!$H$2:$H$4957,$A11)/$B11,"") | P11: =IFERROR(SUMIFS(Plans!$X$2:$X$4957,Plans!$A$2:$A$4957,Fixability!$C$3,Plans!$H$2:$H$4957,$A11)/$B11,"") | Q11: =IFERROR(SUMIFS(Plans!$Y$2:$Y$4957,Plans!$A$2:$A$4957,Fixability!$C$3,Plans!$H$2:$H$4957,$A11)/$B11,"") | R11: =IFERROR(SUMIFS(Plans!$Z$2:$Z$4957,Plans!$A$2:$A$4957,Fixability!$C$3,Plans!$H$2:$H$4957,$A11)/$B11,"")
A12: All | B12: =SUM(B5:B11) -> 87173324 | C12: =SUM(C5:C11) -> 19612209 | D12: =SUM(D5:D11) -> 3968921 | E12: =SUM(E5:E11) -> 21601333 | F12: =SUM(F5:F11) -> 13877230 | G12: =SUM(G5:G11) -> 28113631 | H12: =IFERROR((C12+D12)/B12,"") -> 0.27050856 | I12: =IFERROR(SUMIFS(Plans!$Q$2:$Q$4957,Plans!$A$2:$A$4957,Fixability!$C$3)/$B12,"") -> 0.22497948 | J12: =IFERROR(SUMIFS(Plans!$R$2:$R$4957,Plans!$A$2:$A$4957,Fixability!$C$3)/$B12,"") -> 0.041234254 | K12: =IFERROR(SUMIFS(Plans!$S$2:$S$4957,Plans!$A$2:$A$4957,Fixability!$C$3)/$B12,"") -> 0.004294823 | L12: =IFERROR(SUMIFS(Plans!$T$2:$T$4957,Plans!$A$2:$A$4957,Fixability!$C$3)/$B12,"") -> 0.083794556 | M12: =IFERROR(SUMIFS(Plans!$U$2:$U$4957,Plans!$A$2:$A$4957,Fixability!$C$3)/$B12,"") -> 0.065720885 | N12: =IFERROR(SUMIFS(Plans!$V$2:$V$4957,Plans!$A$2:$A$4957,Fixability!$C$3)/$B12,"") -> 0.098282073 | O12: =IFERROR(SUMIFS(Plans!$W$2:$W$4957,Plans!$A$2:$A$4957,Fixability!$C$3)/$B12,"") -> 0.041830538 | P12: =IFERROR(SUMIFS(Plans!$X$2:$X$4957,Plans!$A$2:$A$4957,Fixability!$C$3)/$B12,"") -> 0.11619508 | Q12: =IFERROR(SUMIFS(Plans!$Y$2:$Y$4957,Plans!$A$2:$A$4957,Fixability!$C$3)/$B12,"") -> 0.0011656318 | R12: =IFERROR(SUMIFS(Plans!$Z$2:$Z$4957,Plans!$A$2:$A$4957,Fixability!$C$3)/$B12,"") -> 0.32250268

Sheet Issuers
A1: Market | B1: State | C1: Issuer ID | D1: Issuer Name | E1: New to Exchange? | F1: # Plans | G1: Claims Received OON | H1: Claims Received INN | I1: Claims Received Total | J1: Claims Denied OON | K1: Claims Denied INN | L1: Claims Denied Total | M1: Denial Rate Total | N1: OON Denial Rate | O1: INN Denial Rate | P1: Resubmitted OON | Q1: Resubmitted INN | R1: Internal Appeals Filed | S1: Internal Appeals Overturned | T1: Internal Overturn Rate | U1: External Appeals Filed | V1: External Appeals Overturned | W1: External Overturn Rate | X1: Appeals per 1,000 Denials | Y1: Tier 1 High (plan-level sum) | Z1: Tier 2 Medium-High (plan-level sum) | AA1: Tier 3 Medium (plan-level sum) | AB1: Tier 4 Low (plan-level sum) | AC1: Tier 5 Unknown (plan-level sum) | AD1: % Fixable (High + Med-High) | AE1: Data Notes | AF1: Claims Payment Policy URL
A2: Individual Dental | B2: AK | C2: 74819 | D2: BEST Life and Health Insurance Company | E2: No | F2: =COUNTIFS(Plans!$A$2:$A$4957,A2,Plans!$D$2:$D$4957,C2) -> 4 | G2: 80 | H2: 34 | I2: =IF(COUNT(G2:H2)=0,"",SUM(G2:H2)) -> 114 | J2: 34 | K2: 12 | L2: =IF(COUNT(J2:K2)=0,"",SUM(J2:K2)) -> 46 | M2: =IFERROR(L2/I2,"") -> 0.40350877 | N2: =IFERROR(J2/G2,"") -> 0.425 | O2: =IFERROR(K2/H2,"") -> 0.35294118 | Q2: 0 | T2: =IFERROR(S2/R2,"") | U2: 0 | V2: 0 | W2: =IFERROR(V2/U2,"") | X2: =IFERROR((N(R2)+N(U2))/L2*1000,"") -> 0 | Y2: =SUMIFS(Plans!$AA$2:$AA$4957,Plans!$A$2:$A$4957,A2,Plans!$D$2:$D$4957,C2) -> 0 | Z2: =SUMIFS(Plans!$AB$2:$AB$4957,Plans!$A$2:$A$4957,A2,Plans!$D$2:$D$4957,C2) -> 0 | AA2: =SUMIFS(Plans!$AC$2:$AC$4957,Plans!$A$2:$A$4957,A2,Plans!$D$2:$D$4957,C2) -> 0 | AB2: =SUMIFS(Plans!$AD$2:$AD$4957,Plans!$A$2:$A$4957,A2,Plans!$D$2:$D$4957,C2) -> 0 | AC2: =SUMIFS(Plans!$AE$2:$AE$4957,Plans!$A$2:$A$4957,A2,Plans!$D$2:$D$4957,C2) -> 0 | AD2: =IFERROR((Y2+Z2)/SUM(Y2:AC2),"") | AE2: ** suppressed (small numbers) | AF2: https://www.bestlife.com/AK/index.html
A3: Individual Dental | B3: AK | C3: 21989 | D3: Oregon Dental Service | E3: No | F3: =COUNTIFS(Plans!$A$2:$A$4957,A3,Plans!$D$2:$D$4957,C3) -> 3 | G3: 1241 | H3: 9127 | I3: =IF(COUNT(G3:H3)=0,"",SUM(G3:H3)) -> 10368 | J3: 525 | K3: 1615 | L3: =IF(COUNT(J3:K3)=0,"",SUM(J3:K3)) -> 2140 | M3: =IFERROR(L3/I3,"") -> 0.20640432 | N3: =IFERROR(J3/G3,"") -> 0.42304593 | O3: =IFERROR(K3/H3,"") -> 0.17694752 | P3: 22 | Q3: 176 | T3: =IFERROR(S3/R3,"") | U3: 0 | V3: 0 | W3: =IFERROR(V3/U3,"") | X3: =IFERROR((N(R3)+N(U3))/L3*1000,"") -> 0 | Y3: =SUMIFS(Plans!$AA$2:$AA$4957,Plans!$A$2:$A$4957,A3,Plans!$D$2:$D$4957,C3) -> 434 | Z3: =SUMIFS(Plans!$AB$2:$AB$4957,Plans!$A$2:$A$4957,A3,Plans!$D$2:$D$4957,C3) -> 0 | AA3: =SUMIFS(Plans!$AC$2:$AC$4957,Plans!$A$2:$A$4957,A3,Plans!$D$2:$D$4957,C3) -> 329 | AB3: =SUMIFS(Plans!$AD$2:$AD$4957,Plans!$A$2:$A$4957,A3,Plans!$D$2:$D$4957,C3) -> 1266 | AC3: =SUMIFS(Plans!$AE$2:$AE$4957,Plans!$A$2:$A$4957,A3,Plans!$D$2:$D$4957,C3) -> 111 | AD3: =IFERROR((Y3+Z3)/SUM(Y3:AC3),"") -> 0.20280374 | AE3: ** suppressed (small numbers) | AF3: https://www.deltadentalak.com/member/resources/transparency-in-coverage
A4: Individual Dental | B4: AK | C4: 38344 | D4: Premera Blue Cross Blue Shield of Alaska | E4: No | F4: =COUNTIFS(Plans!$A$2:$A$4957,A4,Plans!$D$2:$D$4957,C4) -> 2 | G4: 41736 | H4: 777414 | I4: =IF(COUNT(G4:H4)=0,"",SUM(G4:H4)) -> 819150 | J4: 21282 | K4: 210082 | L4: =IF(COUNT(J4:K4)=0,"",SUM(J4:K4)) -> 231364 | M4: =IFERROR(L4/I4,"") -> 0.282444 | N4: =IFERROR(J4/G4,"") -> 0.50991949 | O4: =IFERROR(K4/H4,"") -> 0.27023182 | P4: 5613 | Q4: 82360 | R4: 187 | S4: 89 | T4: =IFERROR(S4/R4,"") -> 0.47593583 | W4: =IFERROR(V4/U4,"") | X4: =IFERROR((N(R4)+N(U4))/L4*1000,"") -> 0.8082502 | Y4: =SUMIFS(Plans!$AA$2:$AA$4957,Plans!$A$2:$A$4957,A4,Plans!$D$2:$D$4957,C4) -> 0 | Z4: =SUMIFS(Plans!$AB$2:$AB$4957,Plans!$A$2:$A$4957,A4,Plans!$D$2:$D$4957,C4) -> 0 | AA4: =SUMIFS(Plans!$AC$2:$AC$4957,Plans!$A$2:$A$4957,A4,Plans!$D$2:$D$4957,C4) -> 0 | AB4: =SUMIFS(Plans!$AD$2:$AD$4957,Plans!$A$2:$A$4957,A4,Plans!$D$2:$D$4957,C4) -> 0 | AC4: =SUMIFS(Plans!$AE$2:$AE$4957,Plans!$A$2:$A$4957,A4,Plans!$D$2:$D$4957,C4) -> 0 | AD4: =IFERROR((Y4+Z4)/SUM(Y4:AC4),"") | AE4: ** suppressed (small numbers) | AF4: https://www.premera.com/visitor/transparency-coverage?region=pbcak
A5: Individual Dental | B5: AL | C5: 12538 | D5: BEST Life and Health Insurance Company | E5: No | F5: =COUNTIFS(Plans!$A$2:$A$4957,A5,Plans!$D$2:$D$4957,C5) -> 4 | H5: 37 | I5: =IF(COUNT(G5:H5)=0,"",SUM(G5:H5)) -> 37 | L5: =IF(COUNT(J5:K5)=0,"",SUM(J5:K5)) | M5: =IFERROR(L5/I5,"") | N5: =IFERROR(J5/G5,"") | O5: =IFERROR(K5/H5,"") -> 0 | R5: 0 | S5: 0 | T5: =IFERROR(S5/R5,"") | W5: =IFERROR(V5/U5,"") | X5: =IFERROR((N(R5)+N(U5))/L5*1000,"") | Y5: =SUMIFS(Plans!$AA$2:$AA$4957,Plans!$A$2:$A$4957,A5,Plans!$D$2:$D$4957,C5) -> 0 | Z5: =SUMIFS(Plans!$AB$2:$AB$4957,Plans!$A$2:$A$4957,A5,Plans!$D$2:$D$4957,C5) -> 0 | AA5: =SUMIFS(Plans!$AC$2:$AC$4957,Plans!$A$2:$A$4957,A5,Plans!$D$2:$D$4957,C5) -> 0 | AB5: =SUMIFS(Plans!$AD$2:$AD$4957,Plans!$A$2:$A$4957,A5,Plans!$D$2:$D$4957,C5) -> 0 | AC5: =SUMIFS(Plans!$AE$2:$AE$4957,Plans!$A$2:$A$4957,A5,Plans!$D$2:$D$4957,C5) -> 0 | AD5: =IFERROR((Y5+Z5)/SUM(Y5:AC5),"") | AE5: ** suppressed (small numbers) | AF5: https://www.bestlife.com/AL/index.html
A6: Individual Dental | B6: AL | C6: 46944 | D6: Blue Cross and Blue Shield of Alabama | E6: No | F6: =COUNTIFS(Plans!$A$2:$A$4957,A6,Plans!$D$2:$D$4957,C6) -> 1 | G6: 204199 | H6: 10704172 | I6: =IF(COUNT(G6:H6)=0,"",SUM(G6:H6)) -> 10908371 | J6: 181561 | K6: 2038603 | L6: =IF(COUNT(J6:K6)=0,"",SUM(J6:K6)) -> 2220164 | M6: =IFERROR(L6/I6,"") -> 0.20352846 | N6: =IFERROR(J6/G6,"") -> 0.88913756 | O6: =IFERROR(K6/H6,"") -> 0.19044939 | P6: 40988 | Q6: 869832 | R6: 5200 | S6: 2608 | T6: =IFERROR(S6/R6,"") -> 0.50153846 | U6: 13 | V6: 0 | W6: =IFERROR(V6/U6,"") -> 0 | X6: =IFERROR((N(R6)+N(U6))/L6*1000,"") -> 2.3480247 | Y6: =SUMIFS(Plans!$AA$2:$AA$4957,Plans!$A$2:$A$4957,A6,Plans!$D$2:$D$4957,C6) -> 3353 | Z6: =SUMIFS(Plans!$AB$2:$AB$4957,Plans!$A$2:$A$4957,A6,Plans!$D$2:$D$4957,C6) -> 0 | AA6: =SUMIFS(Plans!$AC$2:$AC$4957,Plans!$A$2:$A$4957,A6,Plans!$D$2:$D$4957,C6) -> 5729 | AB6: =SUMIFS(Plans!$AD$2:$AD$4957,Plans!$A$2:$A$4957,A6,Plans!$D$2:$D$4957,C6) -> 9242 | AC6: =SUMIFS(Plans!$AE$2:$AE$4957,Plans!$A$2:$A$4957,A6,Plans!$D$2:$D$4957,C6) -> 229 | AD6: =IFERROR((Y6+Z6)/SUM(Y6:AC6),"") -> 0.18072549 | AF6: https://www.bcbsal.org/web/public/portal/claims-payment-policy-other-information.html
A7: Individual Dental | B7: AL | C7: 82285 | D7: Delta Dental Insurance Company | E7: No | F7: =COUNTIFS(Plans!$A$2:$A$4957,A7,Plans!$D$2:$D$4957,C7) -> 3 | G7: 1939 | H7: 23217 | I7: =IF(COUNT(G7:H7)=0,"",SUM(G7:H7)) -> 25156 | J7: 797 | K7: 6620 | L7: =IF(COUNT(J7:K7)=0,"",SUM(J7:K7)) -> 7417 | M7: =IFERROR(L7/I7,"") -> 0.2948402 | N7: =IFERROR(J7/G7,"") -> 0.41103662 | O7: =IFERROR(K7/H7,"") -> 0.28513589 | P7: 64 | Q7: 320 | R7: 41 | T7: =IFERROR(S7/R7,"") -> 0 | U7: 0 | V7: 0 | W7: =IFERROR(V7/U7,"") | X7: =IFERROR((N(R7)+N(U7))/L7*1000,"") -> 5.5278414 | Y7: =SUMIFS(Plans!$AA$2:$AA$4957,Plans!$A$2:$A$4957,A7,Plans!$D$2:$D$4957,C7) -> 609 | Z7: =SUMIFS(Plans!$AB$2:$AB$4957,Plans!$A$2:$A$4957,A7,Plans!$D$2:$D$4957,C7) -> 0 | AA7: =SUMIFS(Plans!$AC$2:$AC$4957,Plans!$A$2:$A$4957,A7,Plans!$D$2:$D$4957,C7) -> 924 | AB7: =SUMIFS(Plans!$AD$2:$AD$4957,Plans!$A$2:$A$4957,A7,Plans!$D$2:$D$4957,C7) -> 4464 | AC7: =SUMIFS(Plans!$AE$2:$AE$4957,Plans!$A$2:$A$4957,A7,Plans!$D$2:$D$4957,C7) -> 1412 | AD7: =IFERROR((Y7+Z7)/SUM(Y7:AC7),"") -> 0.082197328 | AE7: ** suppressed (small numbers) | AF7: https://www1.deltadentalins.com/individuals-and-families/healthcare-reform-for-individuals/how-your-marketplace-plan-works.html
A8: Individual Dental | B8: AL | C8: 46363 | D8: Educators Health Plans Life, Accident, and Health, Inc | E8: No | F8: =COUNTIFS(Plans!$A$2:$A$4957,A8,Plans!$D$2:$D$4957,C8) -> 4 | G8: 9391 | H8: 8905 | I8: =IF(COUNT(G8:H8)=0,"",SUM(G8:H8)) -> 18296 | J8: 4146 | K8: 3357 | L8: =IF(COUNT(J8:K8)=0,"",SUM(J8:K8)) -> 7503 | M8: =IFERROR(L8/I8,"") -> 0.41008964 | N8: =IFERROR(J8/G8,"") -> 0.44148653 | O8: =IFERROR(K8/H8,"") -> 0.37697923 | P8: 958 | Q8: 582 | S8: 0 | T8: =IFERROR(S8/R8,"") | U8: 0 | V8: 0 | W8: =IFERROR(V8/U8,"") | X8: =IFERROR((N(R8)+N(U8))/L8*1000,"") -> 0 | Y8: =SUMIFS(Plans!$AA$2:$AA$4957,Plans!$A$2:$A$4957,A8,Plans!$D$2:$D$4957,C8) -> 3105 | Z8: =SUMIFS(Plans!$AB$2:$AB$4957,Plans!$A$2:$A$4957,A8,Plans!$D$2:$D$4957,C8) -> 0 | AA8: =SUMIFS(Plans!$AC$2:$AC$4957,Plans!$A$2:$A$4957,A8,Plans!$D$2:$D$4957,C8) -> 1013 | AB8: =SUMIFS(Plans!$AD$2:$AD$4957,Plans!$A$2:$A$4957,A8,Plans!$D$2:$D$4957,C8) -> 3368 | AC8: =SUMIFS(Plans!$AE$2:$AE$4957,Plans!$A$2:$A$4957,A8,Plans!$D$2:$D$4957,C8) -> 0 | AD8: =IFERROR((Y8+Z8)/SUM(Y8:AC8),"") -> 0.41477425 | AE8: ** suppressed (small numbers) | AF8: https://emihealth.com/Policies/AlabamaDental
A9: Individual Dental | B9: AL | C9: 17540 | D9: Guardian Life Insurance Company of America | E9: No | F9: =COUNTIFS(Plans!$A$2:$A$4957,A9,Plans!$D$2:$D$4957,C9) -> 3 | G9: 1369 | H9: 5947 | I9: =IF(COUNT(G9:H9)=0,"",SUM(G9:H9)) -> 7316 | J9: 647 | K9: 2557 | L9: =IF(COUNT(J9:K9)=0,"",SUM(J9:K9)) -> 3204 | M9: =IFERROR(L9/I9,"") -> 0.43794423 | N9: =IFERROR(J9/G9,"") -> 0.47260774 | O9: =IFERROR(K9/H9,"") -> 0.42996469 | P9: 0 | Q9: 0 | R9: 0 | S9: 0 | T9: =IFERROR(S9/R9,"") | U9: 0 | V9: 0 | W9: =IFERROR(V9/U9,"") | X9: =IFERROR((N(R9)+N(U9))/L9*1000,"") -> 0 | Y9: =SUMIFS(Plans!$AA$2:$AA$4957,Plans!$A$2:$A$4957,A9,Plans!$D$2:$D$4957,C9) -> 0 | Z9: =SUMIFS(Plans!$AB$2:$AB$4957,Plans!$A$2:$A$4957,A9,Plans!$D$2:$D$4957,C9) -> 0 | AA9: =SUMIFS(Plans!$AC$2:$AC$4957,Plans!$A$2:$A$4957,A9,Plans!$D$2:$D$4957,C9) -> 0 | AB9: =SUMIFS(Plans!$AD$2:$AD$4957,Plans!$A$2:$A$4957,A9,Plans!$D$2:$D$4957,C9) -> 0 | AC9: =SUMIFS(Plans!$AE$2:$AE$4957,Plans!$A$2:$A$4957,A9,Plans!$D$2:$D$4957,C9) -> 0 | AD9: =IFERROR((Y9+Z9)/SUM(Y9:AC9),"") | AF9: https://assets.ctfassets.net/jrhizl9l7csx/3AyKUByHZ9NSjeQMcwn8j8/53ce95a9baee7494befb828f7152268a/Exchange_Transparency_in_Coverage_8.11.25.pdf
A10: Individual Dental | B10: AL | C10: 44580 | D10: Humana Insurance Company | E10: No | F10: =COUNTIFS(Plans!$A$2:$A$4957,A10,Plans!$D$2:$D$4957,C10) -> 3 | G10: 2691 | H10: 20563 | I10: =IF(COUNT(G10:H10)=0,"",SUM(G10:H10)) -> 23254 | J10: 753 | K10: 4462 | L10: =IF(COUNT(J10:K10)=0,"",SUM(J10:K10)) -> 5215 | M10: =IFERROR(L10/I10,"") -> 0.22426249 | N10: =IFERROR(J10/G10,"") -> 0.27982163 | O10: =IFERROR(K10/H10,"") -> 0.21699168 | R10: 14 | S10: 0 | T10: =IFERROR(S10/R10,"") -> 0 | U10: 0 | V10: 0 | W10: =IFERROR(V10/U10,"") | X10: =IFERROR((N(R10)+N(U10))/L10*1000,"") -> 2.6845638 | Y10: =SUMIFS(Plans!$AA$2:$AA$4957,Plans!$A$2:$A$4957,A10,Plans!$D$2:$D$4957,C10) -> 0 | Z10: =SUMIFS(Plans!$AB$2:$AB$4957,Plans!$A$2:$A$4957,A10,Plans!$D$2:$D$4957,C10) -> 147 | AA10: =SUMIFS(Plans!$AC$2:$AC$4957,Plans!$A$2:$A$4957,A10,Plans!$D$2:$D$4957,C10) -> 1130 | AB10: =SUMIFS(Plans!$AD$2:$AD$4957,Plans!$A$2:$A$4957,A10,Plans!$D$2:$D$4957,C10) -> 4203 | AC10: =SUMIFS(Plans!$AE$2:$AE$4957,Plans!$A$2:$A$4957,A10,Plans!$D$2:$D$4957,C10) -> 1151 | AD10: =IFERROR((Y10+Z10)/SUM(Y10:AC10),"") -> 0.022168602 | AE10: ** suppressed (small numbers) | AF10: https://www.humana.com/member/plain-language-policy
A11: Individual Dental | B11: AL | C11: 28725 | D11: Renaissance Life & Health Insurance Company of America | E11: No | F11: =COUNTIFS(Plans!$A$2:$A$4957,A11,Plans!$D$2:$D$4957,C11) -> 5 | G11: 2034 | H11: 7651 | I11: =IF(COUNT(G11:H11)=0,"",SUM(G11:H11)) -> 9685 | J11: 792 | K11: 1907 | L11: =IF(COUNT(J11:K11)=0,"",SUM(J11:K11)) -> 2699 | M11: =IFERROR(L11/I11,"") -> 0.27867837 | N11: =IFERROR(J11/G11,"") -> 0.38938053 | O11: =IFERROR(K11/H11,"") -> 0.24924846 | P11: 147 | Q11: 411 | R11: 0 | S11: 0 | T11: =IFERROR(S11/R11,"") | U11: 0 | V11: 0 | W11: =IFERROR(V11/U11,"") | X11: =IFERROR((N(R11)+N(U11))/L11*1000,"") -> 0 | Y11: =SUMIFS(Plans!$AA$2:$AA$4957,Plans!$A$2:$A$4957,A11,Plans!$D$2:$D$4957,C11) -> 236 | Z11: =SUMIFS(Plans!$AB$2:$AB$4957,Plans!$A$2:$A$4957,A11,Plans!$D$2:$D$4957,C11) -> 0 | AA11: =SUMIFS(Plans!$AC$2:$AC$4957,Plans!$A$2:$A$4957,A11,Plans!$D$2:$D$4957,C11) -> 1531 | AB11: =SUMIFS(Plans!$AD$2:$AD$4957,Plans!$A$2:$A$4957,A11,Plans!$D$2:$D$4957,C11) -> 945 | AC11: =SUMIFS(Plans!$AE$2:$AE$4957,Plans!$A$2:$A$4957,A11,Plans!$D$2:$D$4957,C11) -> 1155 | AD11: =IFERROR((Y11+Z11)/SUM(Y11:AC11),"") -> 0.061029222 | AF11: https://renaissancebenefits.com/understanding-your-benefits/affordable-care-act-coverage/
A12: Individual Dental | B12: AL | C12: 60075 | D12: TRUASSURE INSURANCE COMPANY | E12: No | F12: =COUNTIFS(Plans!$A$2:$A$4957,A12,Plans!$D$2:$D$4957,C12) -> 3 | G12: 523 | H12: 1465 | I12: =IF(COUNT(G12:H12)=0,"",SUM(G12:H12)) -> 1988 | J12: 132 | K12: 526 | L12: =IF(COUNT(J12:K12)=0,"",SUM(J12:K12)) -> 658 | M12: =IFERROR(L12/I12,"") -> 0.33098592 | N12: =IFERROR(J12/G12,"") -> 0.25239006 | O12: =IFERROR(K12/H12,"") -> 0.35904437 | Q12: 17 | T12: =IFERROR(S12/R12,"") | U12: 0 | V12: 0 | W12: =IFERROR(V12/U12,"") | X12: =IFERROR((N(R12)+N(U12))/L12*1000,"") -> 0 | Y12: =SUMIFS(Plans!$AA$2:$AA$4957,Plans!$A$2:$A$4957,A12,Plans!$D$2:$D$4957,C12) -> 0 | Z12: =SUMIFS(Plans!$AB$2:$AB$4957,Plans!$A$2:$A$4957,A12,Plans!$D$2:$D$4957,C12) -> 0 | AA12: =SUMIFS(Plans!$AC$2:$AC$4957,Plans!$A$2:$A$4957,A12,Plans!$D$2:$D$4957,C12) -> 99 | AB12: =SUMIFS(Plans!$AD$2:$AD$4957,Plans!$A$2:$A$4957,A12,Plans!$D$2:$D$4957,C12) -> 14 | AC12: =SUMIFS(Plans!$AE$2:$AE$4957,Plans!$A$2:$A$4957,A12,Plans!$D$2:$D$4957,C12) -> 772 | AD12: =IFERROR((Y12+Z12)/SUM(Y12:AC12),"") -> 0 | AE12: ** suppressed (small numbers) | AF12: https://www.truassure.com/aca-plans
A13: Individual Dental | B13: AR | C13: 26904 | D13: BEST Life and Health Insurance Company | E13: Yes | F13: =COUNTIFS(Plans!$A$2:$A$4957,A13,Plans!$D$2:$D$4957,C13) -> 4 | I13: =IF(COUNT(G13:H13)=0,"",SUM(G13:H13)) | L13: =IF(COUNT(J13:K13)=0,"",SUM(J13:K13)) | M13: =IFERROR(L13/I13,"") | N13: =IFERROR(J13/G13,"") | O13: =IFERROR(K13/H13,"") | T13: =IFERROR(S13/R13,"") | W13: =IFERROR(V13/U13,"") | X13: =IFERROR((N(R13)+N(U13))/L13*1000,"") | Y13: =SUMIFS(Plans!$AA$2:$AA$4957,Plans!$A$2:$A$4957,A13,Plans!$D$2:$D$4957,C13) -> 0 | Z13: =SUMIFS(Plans!$AB$2:$AB$4957,Plans!$A$2:$A$4957,A13,Plans!$D$2:$D$4957,C13) -> 0 | AA13: =SUMIFS(Plans!$AC$2:$AC$4957,Plans!$A$2:$A$4957,A13,Plans!$D$2:$D$4957,C13) -> 0 | AB13: =SUMIFS(Plans!$AD$2:$AD$4957,Plans!$A$2:$A$4957,A13,Plans!$D$2:$D$4957,C13) -> 0 | AC13: =SUMIFS(Plans!$AE$2:$AE$4957,Plans!$A$2:$A$4957,A13,Plans!$D$2:$D$4957,C13) -> 0 | AD13: =IFERROR((Y13+Z13)/SUM(Y13:AC13),"") | AF13: https://www.bestlife.com/AR/index.html
A14: Individual Dental | B14: AR | C14: 28348 | D14: Delta Dental Plan of Arkansas, Inc. | E14: No | F14: =COUNTIFS(Plans!$A$2:$A$4957,A14,Plans!$D$2:$D$4957,C14) -> 5 | G14: 426 | H14: 16788 | I14: =IF(COUNT(G14:H14)=0,"",SUM(G14:H14)) -> 17214 | J14: 213 | K14: 2936 | L14: =IF(COUNT(J14:K14)=0,"",SUM(J14:K14)) -> 3149 | M14: =IFERROR(L14/I14,"") -> 0.1829325 | N14: =IFERROR(J14/G14,"") -> 0.5 | O14: =IFERROR(K14/H14,"") -> 0.17488682 | P14: 42 | Q14: 1218 | R14: 0 | S14: 0 | T14: =IFERROR(S14/R14,"") | U14: 0 | V14: 0 | W14: =IFERROR(V14/U14,"") | X14: =IFERROR((N(R14)+N(U14))/L14*1000,"") -> 0 | Y14: =SUMIFS(Plans!$AA$2:$AA$4957,Plans!$A$2:$A$4957,A14,Plans!$D$2:$D$4957,C14) -> 501 | Z14: =SUMIFS(Plans!$AB$2:$AB$4957,Plans!$A$2:$A$4957,A14,Plans!$D$2:$D$4957,C14) -> 0 | AA14: =SUMIFS(Plans!$AC$2:$AC$4957,Plans!$A$2:$A$4957,A14,Plans!$D$2:$D$4957,C14) -> 775 | AB14: =SUMIFS(Plans!$AD$2:$AD$4957,Plans!$A$2:$A$4957,A14,Plans!$D$2:$D$4957,C14) -> 1202 | AC14: =SUMIFS(Plans!$AE$2:$AE$4957,Plans!$A$2:$A$4957,A14,Plans!$D$2:$D$4957,C14) -> 1734 | AD14: =IFERROR((Y14+Z14)/SUM(Y14:AC14),"") -> 0.11894587 | AF14: https://www.deltadentalar.com/understanding-your-aca-coverage
A15: Individual Dental | B15: AR | C15: 75293 | D15: USAble Mutual Insurance Company | E15: No | F15: =COUNTIFS(Plans!$A$2:$A$4957,A15,Plans!$D$2:$D$4957,C15) -> 8 | G15: 19729 | H15: 4295266 | I15: =IF(COUNT(G15:H15)=0,"",SUM(G15:H15)) -> 4314995 | J15: 7106 | K15: 669702 | L15: =IF(COUNT(J15:K15)=0,"",SUM(J15:K15)) -> 676808 | M15: =IFERROR(L15/I15,"") -> 0.15685024 | N15: =IFERROR(J15/G15,"") -> 0.36018045 | O15: =IFERROR(K15/H15,"") -> 0.1559163 | P15: 36 | Q15: 179074 | R15: 7600 | S15: 2400 | T15: =IFERROR(S15/R15,"") -> 0.31578947 | U15: 35 | V15: 13 | W15: =IFERROR(V15/U15,"") -> 0.37142857 | X15: =IFERROR((N(R15)+N(U15))/L15*1000,"") -> 11.280895 | Y15: =SUMIFS(Plans!$AA$2:$AA$4957,Plans!$A$2:$A$4957,A15,Plans!$D$2:$D$4957,C15) -> 369 | Z15: =SUMIFS(Plans!$AB$2:$AB$4957,Plans!$A$2:$A$4957,A15,Plans!$D$2:$D$4957,C15) -> 0 | AA15: =SUMIFS(Plans!$AC$2:$AC$4957,Plans!$A$2:$A$4957,A15,Plans!$D$2:$D$4957,C15) -> 13 | AB15: =SUMIFS(Plans!$AD$2:$AD$4957,Plans!$A$2:$A$4957,A15,Plans!$D$2:$D$4957,C15) -> 2433 | AC15: =SUMIFS(Plans!$AE$2:$AE$4957,Plans!$A$2:$A$4957,A15,Plans!$D$2:$D$4957,C15) -> 581 | AD15: =IFERROR((Y15+Z15)/SUM(Y15:AC15),"") -> 0.10865724 | AF15: https://www.arkansasbluecross.com/members/individual-and-family/member-rights/transparency-in-coverage
A16: Individual Dental | B16: AZ | C16: 30045 | D16: Arizona Dental Insurance Service, Inc. | E16: No | F16: =COUNTIFS(Plans!$A$2:$A$4957,A16,Plans!$D$2:$D$4957,C16) -> 2 | G16: 1765 | H16: 42715 | I16: =IF(COUNT(G16:H16)=0,"",SUM(G16:H16)) -> 44480 | J16: 1009 | K16: 12738 | L16: =IF(COUNT(J16:K16)=0,"",SUM(J16:K16)) -> 13747 | M16: =IFERROR(L16/I16,"") -> 0.30906025 | N16: =IFERROR(J16/G16,"") -> 0.57167139 | O16: =IFERROR(K16/H16,"") -> 0.29820906 | P16: 148 | Q16: 2887 | R16: 14 | T16: =IFERROR(S16/R16,"") -> 0 | V16: 0 | W16: =IFERROR(V16/U16,"") | X16: =IFERROR((N(R16)+N(U16))/L16*1000,"") -> 1.018404 | Y16: =SUMIFS(Plans!$AA$2:$AA$4957,Plans!$A$2:$A$4957,A16,Plans!$D$2:$D$4957,C16) -> 1320 | Z16: =SUMIFS(Plans!$AB$2:$AB$4957,Plans!$A$2:$A$4957,A16,Plans!$D$2:$D$4957,C16) -> 73 | AA16: =SUMIFS(Plans!$AC$2:$AC$4957,Plans!$A$2:$A$4957,A16,Plans!$D$2:$D$4957,C16) -> 2742 | AB16: =SUMIFS(Plans!$AD$2:$AD$4957,Plans!$A$2:$A$4957,A16,Plans!$D$2:$D$4957,C16) -> 9192 | AC16: =SUMIFS(Plans!$AE$2:$AE$4957,Plans!$A$2:$A$4957,A16,Plans!$D$2:$D$4957,C16) -> 4131 | AD16: =IFERROR((Y16+Z16)/SUM(Y16:AC16),"") -> 0.0797915 | AE16: ** suppressed (small numbers) | AF16: https://www.deltadentalaz.com/shop-for-plans/aca-dental-plans/
A17: Individual Dental | B17: AZ | C17: 77352 | D17: BEST Life and Health Insurance Company | E17: No | F17: =COUNTIFS(Plans!$A$2:$A$4957,A17,Plans!$D$2:$D$4957,C17) -> 4 | G17: 18 | H17: 33 | I17: =IF(COUNT(G17:H17)=0,"",SUM(G17:H17)) -> 51 | J17: 12 | L17: =IF(COUNT(J17:K17)=0,"",SUM(J17:K17)) -> 12 | M17: =IFERROR(L17/I17,"") -> 0.23529412 | N17: =IFERROR(J17/G17,"") -> 0.66666667 | O17: =IFERROR(K17/H17,"") -> 0 | R17: 0 | S17: 0 | T17: =IFERROR(S17/R17,"") | U17: 0 | V17: 0 | W17: =IFERROR(V17/U17,"") | X17: =IFERROR((N(R17)+N(U17))/L17*1000,"") -> 0 | Y17: =SUMIFS(Plans!$AA$2:$AA$4957,Plans!$A$2:$A$4957,A17,Plans!$D$2:$D$4957,C17) -> 0 | Z17: =SUMIFS(Plans!$AB$2:$AB$4957,Plans!$A$2:$A$4957,A17,Plans!$D$2:$D$4957,C17) -> 0 | AA17: =SUMIFS(Plans!$AC$2:$AC$4957,Plans!$A$2:$A$4957,A17,Plans!$D$2:$D$4957,C17) -> 0 | AB17: =SUMIFS(Plans!$AD$2:$AD$4957,Plans!$A$2:$A$4957,A17,Plans!$D$2:$D$4957,C17) -> 0 | AC17: =SUMIFS(Plans!$AE$2:$AE$4957,Plans!$A$2:$A$4957,A17,Plans!$D$2:$D$4957,C17) -> 0 | AD17: =IFERROR((Y17+Z17)/SUM(Y17:AC17),"") | AE17: ** suppressed (small numbers) | AF17: https://www.bestlife.com/AZ/index.html
A18: Individual Dental | B18: AZ | C18: 86830 | D18: Cigna Health and Life Insurance Company | E18: No | F18: =COUNTIFS(Plans!$A$2:$A$4957,A18,Plans!$D$2:$D$4957,C18) -> 2 | G18: 1708 | H18: 7142 | I18: =IF(COUNT(G18:H18)=0,"",SUM(G18:H18)) -> 8850 | J18: 575 | K18: 2444 | L18: =IF(COUNT(J18:K18)=0,"",SUM(J18:K18)) -> 3019 | M18: =IFERROR(L18/I18,"") -> 0.34112994 | N18: =IFERROR(J18/G18,"") -> 0.33665105 | O18: =IFERROR(K18/H18,"") -> 0.34220106 | P18: 77 | Q18: 451 | R18: 71 | S18: 13 | T18: =IFERROR(S18/R18,"") -> 0.18309859 | U18: 0 | V18: 0 | W18: =IFERROR(V18/U18,"") | X18: =IFERROR((N(R18)+N(U18))/L18*1000,"") -> 23.517721 | Y18: =SUMIFS(Plans!$AA$2:$AA$4957,Plans!$A$2:$A$4957,A18,Plans!$D$2:$D$4957,C18) -> 107 | Z18: =SUMIFS(Plans!$AB$2:$AB$4957,Plans!$A$2:$A$4957,A18,Plans!$D$2:$D$4957,C18) -> 0 | AA18: =SUMIFS(Plans!$AC$2:$AC$4957,Plans!$A$2:$A$4957,A18,Plans!$D$2:$D$4957,C18) -> 167 | AB18: =SUMIFS(Plans!$AD$2:$AD$4957,Plans!$A$2:$A$4957,A18,Plans!$D$2:$D$4957,C18) -> 2727 | AC18: =SUMIFS(Plans!$AE$2:$AE$4957,Plans!$A$2:$A$4957,A18,Plans!$D$2:$D$4957,C18) -> 0 | AD18: =IFERROR((Y18+Z18)/SUM(Y18:AC18),"") -> 0.035654782 | AF18: https://www.cigna.com/individuals-families/shop-plans/transparency-in-coverage
A19: Individual Dental | B19: AZ | C19: 12303 | D19: DentaQuest National Insurance Company, Inc. | E19: No | F19: =COUNTIFS(Plans!$A$2:$A$4957,A19,Plans!$D$2:$D$4957,C19) -> 3 | G19: 844 | H19: 1119 | I19: =IF(COUNT(G19:H19)=0,"",SUM(G19:H19)) -> 1963 | J19: 580 | K19: 543 | L19: =IF(COUNT(J19:K19)=0,"",SUM(J19:K19)) -> 1123 | M19: =IFERROR(L19/I19,"") -> 0.57208355 | N19: =IFERROR(J19/G19,"") -> 0.68720379 | O19: =IFERROR(K19/H19,"") -> 0.48525469 | P19: 11 | Q19: 0 | S19: 0 | T19: =IFERROR(S19/R19,"") | U19: 0 | V19: 0 | W19: =IFERROR(V19/U19,"") | X19: =IFERROR((N(R19)+N(U19))/L19*1000,"") -> 0 | Y19: =SUMIFS(Plans!$AA$2:$AA$4957,Plans!$A$2:$A$4957,A19,Plans!$D$2:$D$4957,C19) -> 43 | Z19: =SUMIFS(Plans!$AB$2:$AB$4957,Plans!$A$2:$A$4957,A19,Plans!$D$2:$D$4957,C19) -> 52 | AA19: =SUMIFS(Plans!$AC$2:$AC$4957,Plans!$A$2:$A$4957,A19,Plans!$D$2:$D$4957,C19) -> 0 | AB19: =SUMIFS(Plans!$AD$2:$AD$4957,Plans!$A$2:$A$4957,A19,Plans!$D$2:$D$4957,C19) -> 651 | AC19: =SUMIFS(Plans!$AE$2:$AE$4957,Plans!$A$2:$A$4957,A19,Plans!$D$2:$D$4957,C19) -> 377 | AD19: =IFERROR((Y19+Z19)/SUM(Y19:AC19),"") -> 0.084594835 | AE19: ** suppressed (small numbers) | AF19: https://www.dentaquest.com/en/members/marketplace/transparency-in-coverage
A20: Individual Dental | B20: AZ | C20: 53613 | D20: Educators Health Plans Life, Accident, and Health, Inc | E20: No | F20: =COUNTIFS(Plans!$A$2:$A$4957,A20,Plans!$D$2:$D$4957,C20) -> 5 | G20: 8889 | H20: 15597 | I20: =IF(COUNT(G20:H20)=0,"",SUM(G20:H20)) -> 24486 | J20: 3064 | K20: 5850 | L20: =IF(COUNT(J20:K20)=0,"",SUM(J20:K20)) -> 8914 | M20: =IFERROR(L20/I20,"") -> 0.36404476 | N20: =IFERROR(J20/G20,"") -> 0.34469569 | O20: =IFERROR(K20/H20,"") -> 0.37507213 | P20: 677 | Q20: 1022 | T20: =IFERROR(S20/R20,"") | U20: 0 | V20: 0 | W20: =IFERROR(V20/U20,"") | X20: =IFERROR((N(R20)+N(U20))/L20*1000,"") -> 0 | Y20: =SUMIFS(Plans!$AA$2:$AA$4957,Plans!$A$2:$A$4957,A20,Plans!$D$2:$D$4957,C20) -> 2749 | Z20: =SUMIFS(Plans!$AB$2:$AB$4957,Plans!$A$2:$A$4957,A20,Plans!$D$2:$D$4957,C20) -> 35 | AA20: =SUMIFS(Plans!$AC$2:$AC$4957,Plans!$A$2:$A$4957,A20,Plans!$D$2:$D$4957,C20) -> 778 | AB20: =SUMIFS(Plans!$AD$2:$AD$4957,Plans!$A$2:$A$4957,A20,Plans!$D$2:$D$4957,C20) -> 5312 | AC20: =SUMIFS(Plans!$AE$2:$AE$4957,Plans!$A$2:$A$4957,A20,Plans!$D$2:$D$4957,C20) -> 0 | AD20: =IFERROR((Y20+Z20)/SUM(Y20:AC20),"") -> 0.31372549 | AE20: ** suppressed (small numbers) | AF20: https://emihealth.com/Policies/ArizonaDental
A21: Individual Dental | B21: AZ | C21: 17454 | D21: Guardian Life Insurance Company of America | E21: No | F21: =COUNTIFS(Plans!$A$2:$A$4957,A21,Plans!$D$2:$D$4957,C21) -> 4 | G21: 738 | H21: 3561 | I21: =IF(COUNT(G21:H21)=0,"",SUM(G21:H21)) -> 4299 | J21: 319 | K21: 1515 | L21: =IF(COUNT(J21:K21)=0,"",SUM(J21:K21)) -> 1834 | M21: =IFERROR(L21/I21,"") -> 0.42661084 | N21: =IFERROR(J21/G21,"") -> 0.43224932 | O21: =IFERROR(K21/H21,"") -> 0.42544229 | P21: 0 | Q21: 0 | R21: 0 | S21: 0 | T21: =IFERROR(S21/R21,"") | U21: 0 | V21: 0 | W21: =IFERROR(V21/U21,"") | X21: =IFERROR((N(R21)+N(U21))/L21*1000,"") -> 0 | Y21: =SUMIFS(Plans!$AA$2:$AA$4957,Plans!$A$2:$A$4957,A21,Plans!$D$2:$D$4957,C21) -> 0 | Z21: =SUMIFS(Plans!$AB$2:$AB$4957,Plans!$A$2:$A$4957,A21,Plans!$D$2:$D$4957,C21) -> 0 | AA21: =SUMIFS(Plans!$AC$2:$AC$4957,Plans!$A$2:$A$4957,A21,Plans!$D$2:$D$4957,C21) -> 0 | AB21: =SUMIFS(Plans!$AD$2:$AD$4957,Plans!$A$2:$A$4957,A21,Plans!$D$2:$D$4957,C21) -> 0 | AC21: =SUMIFS(Plans!$AE$2:$AE$4957,Plans!$A$2:$A$4957,A21,Plans!$D$2:$D$4957,C21) -> 0 | AD21: =IFERROR((Y21+Z21)/SUM(Y21:AC21),"") | AF21: https://assets.ctfassets.net/jrhizl9l7csx/3AyKUByHZ9NSjeQMcwn8j8/53ce95a9baee7494befb828f7152268a/Exchange_Transparency_in_Coverage_8.11.25.pdf
A22: Individual Dental | B22: AZ | C22: 66105 | D22: Humana Insurance Company | E22: No | F22: =COUNTIFS(Plans!$A$2:$A$4957,A22,Plans!$D$2:$D$4957,C22) -> 2 | G22: 1276 | H22: 15828 | I22: =IF(COUNT(G22:H22)=0,"",SUM(G22:H22)) -> 17104 | J22: 343 | K22: 4259 | L22: =IF(COUNT(J22:K22)=0,"",SUM(J22:K22)) -> 4602 | M22: =IFERROR(L22/I22,"") -> 0.26905987 | N22: =IFERROR(J22/G22,"") -> 0.26880878 | O22: =IFERROR(K22/H22,"") -> 0.26908011 | P22: 0 | Q22: 35 | R22: 14 | T22: =IFERROR(S22/R22,"") -> 0 | U22: 0 | V22: 0 | W22: =IFERROR(V22/U22,"") | X22: =IFERROR((N(R22)+N(U22))/L22*1000,"") -> 3.0421556 | Y22: =SUMIFS(Plans!$AA$2:$AA$4957,Plans!$A$2:$A$4957,A22,Plans!$D$2:$D$4957,C22) -> 0 | Z22: =SUMIFS(Plans!$AB$2:$AB$4957,Plans!$A$2:$A$4957,A22,Plans!$D$2:$D$4957,C22) -> 0 | AA22: =SUMIFS(Plans!$AC$2:$AC$4957,Plans!$A$2:$A$4957,A22,Plans!$D$2:$D$4957,C22) -> 1204 | AB22: =SUMIFS(Plans!$AD$2:$AD$4957,Plans!$A$2:$A$4957,A22,Plans!$D$2:$D$4957,C22) -> 4154 | AC22: =SUMIFS(Plans!$AE$2:$AE$4957,Plans!$A$2:$A$4957,A22,Plans!$D$2:$D$4957,C22) -> 661 | AD22: =IFERROR((Y22+Z22)/SUM(Y22:AC22),"") -> 0 | AE22: ** suppressed (small numbers) | AF22: https://www.humana.com/member/plain-language-policy
A23: Individual Dental | B23: AZ | C23: 34095 | D23: Solstice Healthplans of Arizona, Inc. | E23: No | F23: =COUNTIFS(Plans!$A$2:$A$4957,A23,Plans!$D$2:$D$4957,C23) -> 1 | G23: 1451 | H23: 9053 | I23: =IF(COUNT(G23:H23)=0,"",SUM(G23:H23)) -> 10504 | J23: 1286 | K23: 6742 | L23: =IF(COUNT(J23:K23)=0,"",SUM(J23:K23)) -> 8028 | M23: =IFERROR(L23/I23,"") -> 0.76428027 | N23: =IFERROR(J23/G23,"") -> 0.88628532 | O23: =IFERROR(K23/H23,"") -> 0.74472551 | P23: 0 | Q23: 0 | R23: 15 | T23: =IFERROR(S23/R23,"") -> 0 | U23: 0 | V23: 0 | W23: =IFERROR(V23/U23,"") | X23: =IFERROR((N(R23)+N(U23))/L23*1000,"") -> 1.8684604 | Y23: =SUMIFS(Plans!$AA$2:$AA$4957,Plans!$A$2:$A$4957,A23,Plans!$D$2:$D$4957,C23) -> 0 | Z23: =SUMIFS(Plans!$AB$2:$AB$4957,Plans!$A$2:$A$4957,A23,Plans!$D$2:$D$4957,C23) -> 1155 | AA23: =SUMIFS(Plans!$AC$2:$AC$4957,Plans!$A$2:$A$4957,A23,Plans!$D$2:$D$4957,C23) -> 0 | AB23: =SUMIFS(Plans!$AD$2:$AD$4957,Plans!$A$2:$A$4957,A23,Plans!$D$2:$D$4957,C23) -> 6873 | AC23: =SUMIFS(Plans!$AE$2:$AE$4957,Plans!$A$2:$A$4957,A23,Plans!$D$2:$D$4957,C23) -> 0 | AD23: =IFERROR((Y23+Z23)/SUM(Y23:AC23),"") -> 0.14387145 | AE23: ** suppressed (small numbers) | AF23: https://www.solsticecare.com/claimsFaq.aspx
A24: Individual Dental | B24: AZ | C24: 24106 | D24: TRUASSURE INSURANCE COMPANY | E24: No | F24: =COUNTIFS(Plans!$A$2:$A$4957,A24,Plans!$D$2:$D$4957,C24) -> 3 | G24: 112 | H24: 766 | I24: =IF(COUNT(G24:H24)=0,"",SUM(G24:H24)) -> 878 | J24: 46 | K24: 413 | L24: =IF(COUNT(J24:K24)=0,"",SUM(J24:K24)) -> 459 | M24: =IFERROR(L24/I24,"") -> 0.52277904 | N24: =IFERROR(J24/G24,"") -> 0.41071429 | O24: =IFERROR(K24/H24,"") -> 0.53916449 | T24: =IFERROR(S24/R24,"") | U24: 0 | V24: 0 | W24: =IFERROR(V24/U24,"") | X24: =IFERROR((N(R24)+N(U24))/L24*1000,"") -> 0 | Y24: =SUMIFS(Plans!$AA$2:$AA$4957,Plans!$A$2:$A$4957,A24,Plans!$D$2:$D$4957,C24) -> 0 | Z24: =SUMIFS(Plans!$AB$2:$AB$4957,Plans!$A$2:$A$4957,A24,Plans!$D$2:$D$4957,C24) -> 0 | AA24: =SUMIFS(Plans!$AC$2:$AC$4957,Plans!$A$2:$A$4957,A24,Plans!$D$2:$D$4957,C24) -> 0 | AB24: =SUMIFS(Plans!$AD$2:$AD$4957,Plans!$A$2:$A$4957,A24,Plans!$D$2:$D$4957,C24) -> 0 | AC24: =SUMIFS(Plans!$AE$2:$AE$4957,Plans!$A$2:$A$4957,A24,Plans!$D$2:$D$4957,C24) -> 464 | AD24: =IFERROR((Y24+Z24)/SUM(Y24:AC24),"") -> 0 | AE24: ** suppressed (small numbers) | AF24: https://www.truassure.com/aca-plans
A25: Individual Dental | B25: AZ | C25: 82011 | D25: UnitedHealthcare Insurance Company | E25: No | F25: =COUNTIFS(Plans!$A$2:$A$4957,A25,Plans!$D$2:$D$4957,C25) -> 1 | G25: 1796 | H25: 4031 | I25: =IF(COUNT(G25:H25)=0,"",SUM(G25:H25)) -> 5827 | J25: 1557 | K25: 1001 | L25: =IF(COUNT(J25:K25)=0,"",SUM(J25:K25)) -> 2558 | M25: =IFERROR(L25/I25,"") -> 0.4389909 | N25: =IFERROR(J25/G25,"") -> 0.8669265 | O25: =IFERROR(K25/H25,"") -> 0.24832548 | P25: 0 | Q25: 0 | R25: 15 | T25: =IFERROR(S25/R25,"") -> 0 | U25: 0 | V25: 0 | W25: =IFERROR(V25/U25,"") | X25: =IFERROR((N(R25)+N(U25))/L25*1000,"") -> 5.8639562 | Y25: =SUMIFS(Plans!$AA$2:$AA$4957,Plans!$A$2:$A$4957,A25,Plans!$D$2:$D$4957,C25) -> 0 | Z25: =SUMIFS(Plans!$AB$2:$AB$4957,Plans!$A$2:$A$4957,A25,Plans!$D$2:$D$4957,C25) -> 154 | AA25: =SUMIFS(Plans!$AC$2:$AC$4957,Plans!$A$2:$A$4957,A25,Plans!$D$2:$D$4957,C25) -> 1313 | AB25: =SUMIFS(Plans!$AD$2:$AD$4957,Plans!$A$2:$A$4957,A25,Plans!$D$2:$D$4957,C25) -> 1091 | AC25: =SUMIFS(Plans!$AE$2:$AE$4957,Plans!$A$2:$A$4957,A25,Plans!$D$2:$D$4957,C25) -> 0 | AD25: =IFERROR((Y25+Z25)/SUM(Y25:AC25),"") -> 0.060203284 | AE25: ** suppressed (small numbers) | AF25: https://www.solsticecare.com/claimsFaq.aspx
A26: Individual Dental | B26: DE | C26: 26018 | D26: Delta Dental of Delaware, Inc. | E26: No | F26: =COUNTIFS(Plans!$A$2:$A$4957,A26,Plans!$D$2:$D$4957,C26) -> 2 | G26: 2752 | H26: 11172 | I26: =IF(COUNT(G26:H26)=0,"",SUM(G26:H26)) -> 13924 | J26: 681 | K26: 2242 | L26: =IF(COUNT(J26:K26)=0,"",SUM(J26:K26)) -> 2923 | M26: =IFERROR(L26/I26,"") -> 0.20992531 | N26: =IFERROR(J26/G26,"") -> 0.2474564 | O26: =IFERROR(K26/H26,"") -> 0.20068027 | P26: 117 | Q26: 88 | R26: 19 | T26: =IFERROR(S26/R26,"") -> 0 | U26: 0 | V26: 0 | W26: =IFERROR(V26/U26,"") | X26: =IFERROR((N(R26)+N(U26))/L26*1000,"") -> 6.5001711 | Y26: =SUMIFS(Plans!$AA$2:$AA$4957,Plans!$A$2:$A$4957,A26,Plans!$D$2:$D$4957,C26) -> 166 | Z26: =SUMIFS(Plans!$AB$2:$AB$4957,Plans!$A$2:$A$4957,A26,Plans!$D$2:$D$4957,C26) -> 0 | AA26: =SUMIFS(Plans!$AC$2:$AC$4957,Plans!$A$2:$A$4957,A26,Plans!$D$2:$D$4957,C26) -> 390 | AB26: =SUMIFS(Plans!$AD$2:$AD$4957,Plans!$A$2:$A$4957,A26,Plans!$D$2:$D$4957,C26) -> 748 | AC26: =SUMIFS(Plans!$AE$2:$AE$4957,Plans!$A$2:$A$4957,A26,Plans!$D$2:$D$4957,C26) -> 1615 | AD26: =IFERROR((Y26+Z26)/SUM(Y26:AC26),"") -> 0.056868791 | AE26: ** suppressed (small numbers) | AF26: https://www1.deltadentalins.com/individuals-and-families/healthcare-reform-for-individuals/how-your-marketplace-plan-works.html
A27: Individual Dental | B27: DE | C27: 67775 | D27: Dominion Dental Services, Inc. | E27: No | F27: =COUNTIFS(Plans!$A$2:$A$4957,A27,Plans!$D$2:$D$4957,C27) -> 10 | G27: 1373 | H27: 2876 | I27: =IF(COUNT(G27:H27)=0,"",SUM(G27:H27)) -> 4249 | J27: 346 | K27: 591 | L27: =IF(COUNT(J27:K27)=0,"",SUM(J27:K27)) -> 937 | M27: =IFERROR(L27/I27,"") -> 0.22052248 | N27: =IFERROR(J27/G27,"") -> 0.25200291 | O27: =IFERROR(K27/H27,"") -> 0.20549374 | P27: 14 | Q27: 45 | T27: =IFERROR(S27/R27,"") | U27: 0 | V27: 0 | W27: =IFERROR(V27/U27,"") | X27: =IFERROR((N(R27)+N(U27))/L27*1000,"") -> 0 | Y27: =SUMIFS(Plans!$AA$2:$AA$4957,Plans!$A$2:$A$4957,A27,Plans!$D$2:$D$4957,C27) -> 108 | Z27: =SUMIFS(Plans!$AB$2:$AB$4957,Plans!$A$2:$A$4957,A27,Plans!$D$2:$D$4957,C27) -> 33 | AA27: =SUMIFS(Plans!$AC$2:$AC$4957,Plans!$A$2:$A$4957,A27,Plans!$D$2:$D$4957,C27) -> 0 | AB27: =SUMIFS(Plans!$AD$2:$AD$4957,Plans!$A$2:$A$4957,A27,Plans!$D$2:$D$4957,C27) -> 478 | AC27: =SUMIFS(Plans!$AE$2:$AE$4957,Plans!$A$2:$A$4957,A27,Plans!$D$2:$D$4957,C27) -> 254 | AD27: =IFERROR((Y27+Z27)/SUM(Y27:AC27),"") -> 0.16151203 | AE27: ** suppressed (small numbers) | AF27: https://www.dominionnational.com/wps/wcm/connect/prodnws.dominionnational.com-30097/a166049e-f578-4b90-8fda-60f3bf81a047/PY2026+Transparency+in+Coverage+Policy.pdf?MOD=AJPERES&CVID=pstswnr
A28: Individual Dental | B28: FL | C28: 17121 | D28: BEST Life and Health Insurance Company | E28: No | F28: =COUNTIFS(Plans!$A$2:$A$4957,A28,Plans!$D$2:$D$4957,C28) -> 4 | G28: 21 | H28: 197 | I28: =IF(COUNT(G28:H28)=0,"",SUM(G28:H28)) -> 218 | J28: 13 | K28: 69 | L28: =IF(COUNT(J28:K28)=0,"",SUM(J28:K28)) -> 82 | M28: =IFERROR(L28/I28,"") -> 0.37614679 | N28: =IFERROR(J28/G28,"") -> 0.61904762 | O28: =IFERROR(K28/H28,"") -> 0.35025381 | Q28: 13 | R28: 0 | S28: 0 | T28: =IFERROR(S28/R28,"") | W28: =IFERROR(V28/U28,"") | X28: =IFERROR((N(R28)+N(U28))/L28*1000,"") -> 0 | Y28: =SUMIFS(Plans!$AA$2:$AA$4957,Plans!$A$2:$A$4957,A28,Plans!$D$2:$D$4957,C28) -> 0 | Z28: =SUMIFS(Plans!$AB$2:$AB$4957,Plans!$A$2:$A$4957,A28,Plans!$D$2:$D$4957,C28) -> 0 | AA28: =SUMIFS(Plans!$AC$2:$AC$4957,Plans!$A$2:$A$4957,A28,Plans!$D$2:$D$4957,C28) -> 20 | AB28: =SUMIFS(Plans!$AD$2:$AD$4957,Plans!$A$2:$A$4957,A28,Plans!$D$2:$D$4957,C28) -> 38 | AC28: =SUMIFS(Plans!$AE$2:$AE$4957,Plans!$A$2:$A$4957,A28,Plans!$D$2:$D$4957,C28) -> 0 | AD28: =IFERROR((Y28+Z28)/SUM(Y28:AC28),"") -> 0 | AE28: ** suppressed (small numbers) | AF28: https://www.bestlife.com/FL/index.html
A29: Individual Dental | B29: FL | C29: 48121 | D29: Cigna Health and Life Insurance Company | E29: No | F29: =COUNTIFS(Plans!$A$2:$A$4957,A29,Plans!$D$2:$D$4957,C29) -> 2 | G29: 157117 | H29: 4620013 | I29: =IF(COUNT(G29:H29)=0,"",SUM(G29:H29)) -> 4777130 | J29: 134858 | K29: 926080 | L29: =IF(COUNT(J29:K29)=0,"",SUM(J29:K29)) -> 1060938 | M29: =IFERROR(L29/I29,"") -> 0.2220869 | N29: =IFERROR(J29/G29,"") -> 0.85832851 | O29: =IFERROR(K29/H29,"") -> 0.20044965 | P29: 5594 | Q29: 161971 | R29: 1210 | S29: 389 | T29: =IFERROR(S29/R29,"") -> 0.3214876 | U29: 15 | W29: =IFERROR(V29/U29,"") -> 0 | X29: =IFERROR((N(R29)+N(U29))/L29*1000,"") -> 1.1546386 | Y29: =SUMIFS(Plans!$AA$2:$AA$4957,Plans!$A$2:$A$4957,A29,Plans!$D$2:$D$4957,C29) -> 494 | Z29: =SUMIFS(Plans!$AB$2:$AB$4957,Plans!$A$2:$A$4957,A29,Plans!$D$2:$D$4957,C29) -> 0 | AA29: =SUMIFS(Plans!$AC$2:$AC$4957,Plans!$A$2:$A$4957,A29,Plans!$D$2:$D$4957,C29) -> 611 | AB29: =SUMIFS(Plans!$AD$2:$AD$4957,Plans!$A$2:$A$4957,A29,Plans!$D$2:$D$4957,C29) -> 11892 | AC29: =SUMIFS(Plans!$AE$2:$AE$4957,Plans!$A$2:$A$4957,A29,Plans!$D$2:$D$4957,C29) -> 70 | AD29: =IFERROR((Y29+Z29)/SUM(Y29:AC29),"") -> 0.037805158 | AE29: ** suppressed (small numbers) | AF29: https://www.cigna.com/individuals-families/shop-plans/transparency-in-coverage
A30: Individual Dental | B30: FL | C30: 97725 | D30: Delta Dental Insurance Company | E30: No | F30: =COUNTIFS(Plans!$A$2:$A$4957,A30,Plans!$D$2:$D$4957,C30) -> 5 | G30: 13805 | H30: 137313 | I30: =IF(COUNT(G30:H30)=0,"",SUM(G30:H30)) -> 151118 | J30: 5671 | K30: 47090 | L30: =IF(COUNT(J30:K30)=0,"",SUM(J30:K30)) -> 52761 | M30: =IFERROR(L30/I30,"") -> 0.34913776 | N30: =IFERROR(J30/G30,"") -> 0.41079319 | O30: =IFERROR(K30/H30,"") -> 0.34293912 | P30: 228 | Q30: 1953 | R30: 1203 | S30: 16518 | T30: =IFERROR(S30/R30,"") -> 13.730673 | U30: 5650 | V30: 0 | W30: =IFERROR(V30/U30,"") -> 0 | X30: =IFERROR((N(R30)+N(U30))/L30*1000,"") -> 129.88761 | Y30: =SUMIFS(Plans!$AA$2:$AA$4957,Plans!$A$2:$A$4957,A30,Plans!$D$2:$D$4957,C30) -> 1423 | Z30: =SUMIFS(Plans!$AB$2:$AB$4957,Plans!$A$2:$A$4957,A30,Plans!$D$2:$D$4957,C30) -> 0 | AA30: =SUMIFS(Plans!$AC$2:$AC$4957,Plans!$A$2:$A$4957,A30,Plans!$D$2:$D$4957,C30) -> 9360 | AB30: =SUMIFS(Plans!$AD$2:$AD$4957,Plans!$A$2:$A$4957,A30,Plans!$D$2:$D$4957,C30) -> 24853 | AC30: =SUMIFS(Plans!$AE$2:$AE$4957,Plans!$A$2:$A$4957,A30,Plans!$D$2:$D$4957,C30) -> 17123 | AD30: =IFERROR((Y30+Z30)/SUM(Y30:AC30),"") -> 0.026971702 | AF30: https://www1.deltadentalins.com/individuals-and-families/healthcare-reform-for-individuals/how-your-marketplace-plan-works.html
A31: Individual Dental | B31: FL | C31: 59667 | D31: DentaQuest of Florida, Inc. | E31: No | F31: =COUNTIFS(Plans!$A$2:$A$4957,A31,Plans!$D$2:$D$4957,C31) -> 3 | G31: 137 | H31: 4459 | I31: =IF(COUNT(G31:H31)=0,"",SUM(G31:H31)) -> 4596 | J31: 118 | K31: 2787 | L31: =IF(COUNT(J31:K31)=0,"",SUM(J31:K31)) -> 2905 | M31: =IFERROR(L31/I31,"") -> 0.63207137 | N31: =IFERROR(J31/G31,"") -> 0.86131387 | O31: =IFERROR(K31/H31,"") -> 0.62502803 | P31: 0 | S31: 0 | T31: =IFERROR(S31/R31,"") | U31: 0 | V31: 0 | W31: =IFERROR(V31/U31,"") | X31: =IFERROR((N(R31)+N(U31))/L31*1000,"") -> 0 | Y31: =SUMIFS(Plans!$AA$2:$AA$4957,Plans!$A$2:$A$4957,A31,Plans!$D$2:$D$4957,C31) -> 12 | Z31: =SUMIFS(Plans!$AB$2:$AB$4957,Plans!$A$2:$A$4957,A31,Plans!$D$2:$D$4957,C31) -> 0 | AA31: =SUMIFS(Plans!$AC$2:$AC$4957,Plans!$A$2:$A$4957,A31,Plans!$D$2:$D$4957,C31) -> 343 | AB31: =SUMIFS(Plans!$AD$2:$AD$4957,Plans!$A$2:$A$4957,A31,Plans!$D$2:$D$4957,C31) -> 2003 | AC31: =SUMIFS(Plans!$AE$2:$AE$4957,Plans!$A$2:$A$4957,A31,Plans!$D$2:$D$4957,C31) -> 529 | AD31: =IFERROR((Y31+Z31)/SUM(Y31:AC31),"") -> 0.0041565639 | AE31: ** suppressed (small numbers) | AF31: https://www.dentaquest.com/en/members/marketplace/transparency-in-coverage
A32: Individual Dental | B32: FL | C32: 74243 | D32: Dominion Dental Services, Inc. | E32: No | F32: =COUNTIFS(Plans!$A$2:$A$4957,A32,Plans!$D$2:$D$4957,C32) -> 6 | G32: 1672 | H32: 8849 | I32: =IF(COUNT(G32:H32)=0,"",SUM(G32:H32)) -> 10521 | J32: 698 | K32: 2713 | L32: =IF(COUNT(J32:K32)=0,"",SUM(J32:K32)) -> 3411 | M32: =IFERROR(L32/I32,"") -> 0.32420873 | N32: =IFERROR(J32/G32,"") -> 0.41746411 | O32: =IFERROR(K32/H32,"") -> 0.30658832 | P32: 76 | Q32: 892 | T32: =IFERROR(S32/R32,"") | U32: 0 | V32: 0 | W32: =IFERROR(V32/U32,"") | X32: =IFERROR((N(R32)+N(U32))/L32*1000,"") -> 0 | Y32: =SUMIFS(Plans!$AA$2:$AA$4957,Plans!$A$2:$A$4957,A32,Plans!$D$2:$D$4957,C32) -> 515 | Z32: =SUMIFS(Plans!$AB$2:$AB$4957,Plans!$A$2:$A$4957,A32,Plans!$D$2:$D$4957,C32) -> 175 | AA32: =SUMIFS(Plans!$AC$2:$AC$4957,Plans!$A$2:$A$4957,A32,Plans!$D$2:$D$4957,C32) -> 34 | AB32: =SUMIFS(Plans!$AD$2:$AD$4957,Plans!$A$2:$A$4957,A32,Plans!$D$2:$D$4957,C32) -> 2027 | AC32: =SUMIFS(Plans!$AE$2:$AE$4957,Plans!$A$2:$A$4957,A32,Plans!$D$2:$D$4957,C32) -> 621 | AD32: =IFERROR((Y32+Z32)/SUM(Y32:AC32),"") -> 0.20462633 | AE32: ** suppressed (small numbers) | AF32: https://www.dominionnational.com/wps/wcm/connect/prodnws.dominionnational.com-30097/a166049e-f578-4b90-8fda-60f3bf81a047/PY2026+Transparency+in+Coverage+Policy.pdf?MOD=AJPERES&CVID=pstswnr
A33: Individual Dental | B33: FL | C33: 98869 | D33: Educators Health Plans Life, Accident, and Health, | E33: No | F33: =COUNTIFS(Plans!$A$2:$A$4957,A33,Plans!$D$2:$D$4957,C33) -> 5 | G33: 17627 | H33: 32850 | I33: =IF(COUNT(G33:H33)=0,"",SUM(G33:H33)) -> 50477 | J33: 7965 | K33: 13439 | L33: =IF(COUNT(J33:K33)=0,"",SUM(J33:K33)) -> 21404 | M33: =IFERROR(L33/I33,"") -> 0.42403471 | N33: =IFERROR(J33/G33,"") -> 0.45186362 | O33: =IFERROR(K33/H33,"") -> 0.40910198 | P33: 1694 | Q33: 3170 | T33: =IFERROR(S33/R33,"") | U33: 0 | V33: 0 | W33: =IFERROR(V33/U33,"") | X33: =IFERROR((N(R33)+N(U33))/L33*1000,"") -> 0 | Y33: =SUMIFS(Plans!$AA$2:$AA$4957,Plans!$A$2:$A$4957,A33,Plans!$D$2:$D$4957,C33) -> 9173 | Z33: =SUMIFS(Plans!$AB$2:$AB$4957,Plans!$A$2:$A$4957,A33,Plans!$D$2:$D$4957,C33) -> 92 | AA33: =SUMIFS(Plans!$AC$2:$AC$4957,Plans!$A$2:$A$4957,A33,Plans!$D$2:$D$4957,C33) -> 2313 | AB33: =SUMIFS(Plans!$AD$2:$AD$4957,Plans!$A$2:$A$4957,A33,Plans!$D$2:$D$4957,C33) -> 9737 | AC33: =SUMIFS(Plans!$AE$2:$AE$4957,Plans!$A$2:$A$4957,A33,Plans!$D$2:$D$4957,C33) -> 0 | AD33: =IFERROR((Y33+Z33)/SUM(Y33:AC33),"") -> 0.43467042 | AE33: ** suppressed (small numbers) | AF33: https://emihealth.com/Policies/FloridaDental
A34: Individual Dental | B34: FL | C34: 30115 | D34: Florida Combined Life Insurance Company | E34: No | F34: =COUNTIFS(Plans!$A$2:$A$4957,A34,Plans!$D$2:$D$4957,C34) -> 4 | G34: 10077 | H34: 59662 | I34: =IF(COUNT(G34:H34)=0,"",SUM(G34:H34)) -> 69739 | J34: 3580 | K34: 20412 | L34: =IF(COUNT(J34:K34)=0,"",SUM(J34:K34)) -> 23992 | M34: =IFERROR(L34/I34,"") -> 0.34402558 | N34: =IFERROR(J34/G34,"") -> 0.35526446 | O34: =IFERROR(K34/H34,"") -> 0.34212732 | P34: 0 | Q34: 0 | R34: 0 | S34: 0 | T34: =IFERROR(S34/R34,"") | U34: 0 | V34: 0 | W34: =IFERROR(V34/U34,"") | X34: =IFERROR((N(R34)+N(U34))/L34*1000,"") -> 0 | Y34: =SUMIFS(Plans!$AA$2:$AA$4957,Plans!$A$2:$A$4957,A34,Plans!$D$2:$D$4957,C34) -> 1368 | Z34: =SUMIFS(Plans!$AB$2:$AB$4957,Plans!$A$2:$A$4957,A34,Plans!$D$2:$D$4957,C34) -> 0 | AA34: =SUMIFS(Plans!$AC$2:$AC$4957,Plans!$A$2:$A$4957,A34,Plans!$D$2:$D$4957,C34) -> 41 | AB34: =SUMIFS(Plans!$AD$2:$AD$4957,Plans!$A$2:$A$4957,A34,Plans!$D$2:$D$4957,C34) -> 17789 | AC34: =SUMIFS(Plans!$AE$2:$AE$4957,Plans!$A$2:$A$4957,A34,Plans!$D$2:$D$4957,C34) -> 4766 | AD34: =IFERROR((Y34+Z34)/SUM(Y34:AC34),"") -> 0.057085628 | AF34: https://floridabluedental.com/members/tools-and-resources/transparency-in-coverage
A35: Individual Dental | B35: FL | C35: 15833 | D35: Guardian Life Insurance Company of America | E35: No | F35: =COUNTIFS(Plans!$A$2:$A$4957,A35,Plans!$D$2:$D$4957,C35) -> 5 | G35: 13229 | H35: 127332 | I35: =IF(COUNT(G35:H35)=0,"",SUM(G35:H35)) -> 140561 | J35: 10812 | K35: 91259 | L35: =IF(COUNT(J35:K35)=0,"",SUM(J35:K35)) -> 102071 | M35: =IFERROR(L35/I35,"") -> 0.72616871 | N35: =IFERROR(J35/G35,"") -> 0.81729534 | O35: =IFERROR(K35/H35,"") -> 0.71670122 | P35: 0 | Q35: 0 | R35: 0 | S35: 0 | T35: =IFERROR(S35/R35,"") | U35: 0 | V35: 0 | W35: =IFERROR(V35/U35,"") | X35: =IFERROR((N(R35)+N(U35))/L35*1000,"") -> 0 | Y35: =SUMIFS(Plans!$AA$2:$AA$4957,Plans!$A$2:$A$4957,A35,Plans!$D$2:$D$4957,C35) -> 0 | Z35: =SUMIFS(Plans!$AB$2:$AB$4957,Plans!$A$2:$A$4957,A35,Plans!$D$2:$D$4957,C35) -> 0 | AA35: =SUMIFS(Plans!$AC$2:$AC$4957,Plans!$A$2:$A$4957,A35,Plans!$D$2:$D$4957,C35) -> 0 | AB35: =SUMIFS(Plans!$AD$2:$AD$4957,Plans!$A$2:$A$4957,A35,Plans!$D$2:$D$4957,C35) -> 0 | AC35: =SUMIFS(Plans!$AE$2:$AE$4957,Plans!$A$2:$A$4957,A35,Plans!$D$2:$D$4957,C35) -> 0 | AD35: =IFERROR((Y35+Z35)/SUM(Y35:AC35),"") | AF35: https://assets.ctfassets.net/jrhizl9l7csx/3AyKUByHZ9NSjeQMcwn8j8/53ce95a9baee7494befb828f7152268a/Exchange_Transparency_in_Coverage_8.11.25.pdf
A36: Individual Dental | B36: FL | C36: 15980 | D36: Humana Insurance Company | E36: No | F36: =COUNTIFS(Plans!$A$2:$A$4957,A36,Plans!$D$2:$D$4957,C36) -> 3 | G36: 5057 | H36: 52493 | I36: =IF(COUNT(G36:H36)=0,"",SUM(G36:H36)) -> 57550 | J36: 1596 | K36: 15282 | L36: =IF(COUNT(J36:K36)=0,"",SUM(J36:K36)) -> 16878 | M36: =IFERROR(L36/I36,"") -> 0.29327541 | N36: =IFERROR(J36/G36,"") -> 0.31560214 | O36: =IFERROR(K36/H36,"") -> 0.29112453 | P36: 16 | Q36: 91 | R36: 23 | T36: =IFERROR(S36/R36,"") -> 0 | U36: 0 | V36: 0 | W36: =IFERROR(V36/U36,"") | X36: =IFERROR((N(R36)+N(U36))/L36*1000,"") -> 1.3627207 | Y36: =SUMIFS(Plans!$AA$2:$AA$4957,Plans!$A$2:$A$4957,A36,Plans!$D$2:$D$4957,C36) -> 0 | Z36: =SUMIFS(Plans!$AB$2:$AB$4957,Plans!$A$2:$A$4957,A36,Plans!$D$2:$D$4957,C36) -> 214 | AA36: =SUMIFS(Plans!$AC$2:$AC$4957,Plans!$A$2:$A$4957,A36,Plans!$D$2:$D$4957,C36) -> 4828 | AB36: =SUMIFS(Plans!$AD$2:$AD$4957,Plans!$A$2:$A$4957,A36,Plans!$D$2:$D$4957,C36) -> 14523 | AC36: =SUMIFS(Plans!$AE$2:$AE$4957,Plans!$A$2:$A$4957,A36,Plans!$D$2:$D$4957,C36) -> 2839 | AD36: =IFERROR((Y36+Z36)/SUM(Y36:AC36),"") -> 0.0095518657 | AE36: ** suppressed (small numbers) | AF36: https://www.humana.com/member/plain-language-policy
A37: Individual Dental | B37: FL | C37: 48129 | D37: Renaissance Life & Health Insurance Company of America | E37: No | F37: =COUNTIFS(Plans!$A$2:$A$4957,A37,Plans!$D$2:$D$4957,C37) -> 5 | G37: 2874 | H37: 10740 | I37: =IF(COUNT(G37:H37)=0,"",SUM(G37:H37)) -> 13614 | J37: 1274 | K37: 3270 | L37: =IF(COUNT(J37:K37)=0,"",SUM(J37:K37)) -> 4544 | M37: =IFERROR(L37/I37,"") -> 0.33377406 | N37: =IFERROR(J37/G37,"") -> 0.44328462 | O37: =IFERROR(K37/H37,"") -> 0.30446927 | P37: 262 | Q37: 762 | R37: 0 | S37: 0 | T37: =IFERROR(S37/R37,"") | W37: =IFERROR(V37/U37,"") | X37: =IFERROR((N(R37)+N(U37))/L37*1000,"") -> 0 | Y37: =SUMIFS(Plans!$AA$2:$AA$4957,Plans!$A$2:$A$4957,A37,Plans!$D$2:$D$4957,C37) -> 405 | Z37: =SUMIFS(Plans!$AB$2:$AB$4957,Plans!$A$2:$A$4957,A37,Plans!$D$2:$D$4957,C37) -> 0 | AA37: =SUMIFS(Plans!$AC$2:$AC$4957,Plans!$A$2:$A$4957,A37,Plans!$D$2:$D$4957,C37) -> 2223 | AB37: =SUMIFS(Plans!$AD$2:$AD$4957,Plans!$A$2:$A$4957,A37,Plans!$D$2:$D$4957,C37) -> 1711 | AC37: =SUMIFS(Plans!$AE$2:$AE$4957,Plans!$A$2:$A$4957,A37,Plans!$D$2:$D$4957,C37) -> 1843 | AD37: =IFERROR((Y37+Z37)/SUM(Y37:AC37),"") -> 0.065512779 | AE37: ** suppressed (small numbers) | AF37: https://renaissancebenefits.com/understanding-your-benefits/affordable-care-act-coverage/
A38: Individual Dental | B38: FL | C38: 43274 | D38: Solstice Benefits, Inc. | E38: No | F38: =COUNTIFS(Plans!$A$2:$A$4957,A38,Plans!$D$2:$D$4957,C38) -> 3 | G38: 3949 | H38: 19794 | I38: =IF(COUNT(G38:H38)=0,"",SUM(G38:H38)) -> 23743 | J38: 3434 | K38: 13482 | L38: =IF(COUNT(J38:K38)=0,"",SUM(J38:K38)) -> 16916 | M38: =IFERROR(L38/I38,"") -> 0.71246262 | N38: =IFERROR(J38/G38,"") -> 0.86958724 | O38: =IFERROR(K38/H38,"") -> 0.68111549 | P38: 0 | Q38: 0 | R38: 100 | S38: 44 | T38: =IFERROR(S38/R38,"") -> 0.44 | U38: 0 | V38: 0 | W38: =IFERROR(V38/U38,"") | X38: =IFERROR((N(R38)+N(U38))/L38*1000,"") -> 5.911563 | Y38: =SUMIFS(Plans!$AA$2:$AA$4957,Plans!$A$2:$A$4957,A38,Plans!$D$2:$D$4957,C38) -> 0 | Z38: =SUMIFS(Plans!$AB$2:$AB$4957,Plans!$A$2:$A$4957,A38,Plans!$D$2:$D$4957,C38) -> 1131 | AA38: =SUMIFS(Plans!$AC$2:$AC$4957,Plans!$A$2:$A$4957,A38,Plans!$D$2:$D$4957,C38) -> 252 | AB38: =SUMIFS(Plans!$AD$2:$AD$4957,Plans!$A$2:$A$4957,A38,Plans!$D$2:$D$4957,C38) -> 15525 | AC38: =SUMIFS(Plans!$AE$2:$AE$4957,Plans!$A$2:$A$4957,A38,Plans!$D$2:$D$4957,C38) -> 0 | AD38: =IFERROR((Y38+Z38)/SUM(Y38:AC38),"") -> 0.066891412 | AF38: https://www.solsticecare.com/claimsFaq.aspx
A39: Individual Dental | B39: HI | C39: 10046 | D39: BEST Life and Health Insurance Company | E39: No | F39: =COUNTIFS(Plans!$A$2:$A$4957,A39,Plans!$D$2:$D$4957,C39) -> 4 | H39: 13 | I39: =IF(COUNT(G39:H39)=0,"",SUM(G39:H39)) -> 13 | L39: =IF(COUNT(J39:K39)=0,"",SUM(J39:K39)) | M39: =IFERROR(L39/I39,"") | N39: =IFERROR(J39/G39,"") | O39: =IFERROR(K39/H39,"") -> 0 | P39: 0 | Q39: 0 | T39: =IFERROR(S39/R39,"") | U39: 0 | V39: 0 | W39: =IFERROR(V39/U39,"") | X39: =IFERROR((N(R39)+N(U39))/L39*1000,"") | Y39: =SUMIFS(Plans!$AA$2:$AA$4957,Plans!$A$2:$A$4957,A39,Plans!$D$2:$D$4957,C39) -> 0 | Z39: =SUMIFS(Plans!$AB$2:$AB$4957,Plans!$A$2:$A$4957,A39,Plans!$D$2:$D$4957,C39) -> 0 | AA39: =SUMIFS(Plans!$AC$2:$AC$4957,Plans!$A$2:$A$4957,A39,Plans!$D$2:$D$4957,C39) -> 0 | AB39: =SUMIFS(Plans!$AD$2:$AD$4957,Plans!$A$2:$A$4957,A39,Plans!$D$2:$D$4957,C39) -> 0 | AC39: =SUMIFS(Plans!$AE$2:$AE$4957,Plans!$A$2:$A$4957,A39,Plans!$D$2:$D$4957,C39) -> 0 | AD39: =IFERROR((Y39+Z39)/SUM(Y39:AC39),"") | AE39: ** suppressed (small numbers) | AF39: https://www.bestlife.com/HI/index.html
A40: Individual Dental | B40: HI | C40: 27409 | D40: Guardian Life Insurance Company of America | E40: Yes | F40: =COUNTIFS(Plans!$A$2:$A$4957,A40,Plans!$D$2:$D$4957,C40) -> 3 | I40: =IF(COUNT(G40:H40)=0,"",SUM(G40:H40)) | L40: =IF(COUNT(J40:K40)=0,"",SUM(J40:K40)) | M40: =IFERROR(L40/I40,"") | N40: =IFERROR(J40/G40,"") | O40: =IFERROR(K40/H40,"") | T40: =IFERROR(S40/R40,"") | W40: =IFERROR(V40/U40,"") | X40: =IFERROR((N(R40)+N(U40))/L40*1000,"") | Y40: =SUMIFS(Plans!$AA$2:$AA$4957,Plans!$A$2:$A$4957,A40,Plans!$D$2:$D$4957,C40) -> 0 | Z40: =SUMIFS(Plans!$AB$2:$AB$4957,Plans!$A$2:$A$4957,A40,Plans!$D$2:$D$4957,C40) -> 0 | AA40: =SUMIFS(Plans!$AC$2:$AC$4957,Plans!$A$2:$A$4957,A40,Plans!$D$2:$D$4957,C40) -> 0 | AB40: =SUMIFS(Plans!$AD$2:$AD$4957,Plans!$A$2:$A$4957,A40,Plans!$D$2:$D$4957,C40) -> 0 | AC40: =SUMIFS(Plans!$AE$2:$AE$4957,Plans!$A$2:$A$4957,A40,Plans!$D$2:$D$4957,C40) -> 0 | AD40: =IFERROR((Y40+Z40)/SUM(Y40:AC40),"") | AF40: https://assets.ctfassets.net/jrhizl9l7csx/3AyKUByHZ9NSjeQMcwn8j8/53ce95a9baee7494befb828f7152268a/Exchange_Transparency_in_Coverage_8.11.25.pdf
A41: Individual Dental | B41: HI | C41: 46082 | D41: Hawaii Dental Service | E41: No | F41: =COUNTIFS(Plans!$A$2:$A$4957,A41,Plans!$D$2:$D$4957,C41) -> 3 | G41: 450 | H41: 10373 | I41: =IF(COUNT(G41:H41)=0,"",SUM(G41:H41)) -> 10823 | J41: 159 | K41: 695 | L41: =IF(COUNT(J41:K41)=0,"",SUM(J41:K41)) -> 854 | M41: =IFERROR(L41/I41,"") -> 0.078906033 | N41: =IFERROR(J41/G41,"") -> 0.35333333 | O41: =IFERROR(K41/H41,"") -> 0.067000868 | Q41: 93 | R41: 98 | S41: 57 | T41: =IFERROR(S41/R41,"") -> 0.58163265 | U41: 0 | V41: 0 | W41: =IFERROR(V41/U41,"") | X41: =IFERROR((N(R41)+N(U41))/L41*1000,"") -> 114.7541 | Y41: =SUMIFS(Plans!$AA$2:$AA$4957,Plans!$A$2:$A$4957,A41,Plans!$D$2:$D$4957,C41) -> 0 | Z41: =SUMIFS(Plans!$AB$2:$AB$4957,Plans!$A$2:$A$4957,A41,Plans!$D$2:$D$4957,C41) -> 0 | AA41: =SUMIFS(Plans!$AC$2:$AC$4957,Plans!$A$2:$A$4957,A41,Plans!$D$2:$D$4957,C41) -> 58 | AB41: =SUMIFS(Plans!$AD$2:$AD$4957,Plans!$A$2:$A$4957,A41,Plans!$D$2:$D$4957,C41) -> 520 | AC41: =SUMIFS(Plans!$AE$2:$AE$4957,Plans!$A$2:$A$4957,A41,Plans!$D$2:$D$4957,C41) -> 269 | AD41: =IFERROR((Y41+Z41)/SUM(Y41:AC41),"") -> 0 | AE41: ** suppressed (small numbers) | AF41: https://www.hawaiidentalservice.com/members/marketplace
A42: Individual Dental | B42: HI | C42: 18350 | D42: Hawaii Medical Service Association | E42: No | F42: =COUNTIFS(Plans!$A$2:$A$4957,A42,Plans!$D$2:$D$4957,C42) -> 5 | G42: 3861 | H42: 723658 | I42: =IF(COUNT(G42:H42)=0,"",SUM(G42:H42)) -> 727519 | J42: 883 | K42: 198069 | L42: =IF(COUNT(J42:K42)=0,"",SUM(J42:K42)) -> 198952 | M42: =IFERROR(L42/I42,"") -> 0.2734664 | N42: =IFERROR(J42/G42,"") -> 0.22869723 | O42: =IFERROR(K42/H42,"") -> 0.27370526 | P42: 16 | Q42: 15825 | R42: 104 | S42: 52 | T42: =IFERROR(S42/R42,"") -> 0.5 | U42: 0 | V42: 0 | W42: =IFERROR(V42/U42,"") | X42: =IFERROR((N(R42)+N(U42))/L42*1000,"") -> 0.52273915 | Y42: =SUMIFS(Plans!$AA$2:$AA$4957,Plans!$A$2:$A$4957,A42,Plans!$D$2:$D$4957,C42) -> 355 | Z42: =SUMIFS(Plans!$AB$2:$AB$4957,Plans!$A$2:$A$4957,A42,Plans!$D$2:$D$4957,C42) -> 0 | AA42: =SUMIFS(Plans!$AC$2:$AC$4957,Plans!$A$2:$A$4957,A42,Plans!$D$2:$D$4957,C42) -> 186 | AB42: =SUMIFS(Plans!$AD$2:$AD$4957,Plans!$A$2:$A$4957,A42,Plans!$D$2:$D$4957,C42) -> 9201 | AC42: =SUMIFS(Plans!$AE$2:$AE$4957,Plans!$A$2:$A$4957,A42,Plans!$D$2:$D$4957,C42) -> 453 | AD42: =IFERROR((Y42+Z42)/SUM(Y42:AC42),"") -> 0.034820991 | AF42: https://hmsa.com/aca-transparency
A43: Individual Dental | B43: HI | C43: 31358 | D43: Humana Insurance Company | E43: Yes | F43: =COUNTIFS(Plans!$A$2:$A$4957,A43,Plans!$D$2:$D$4957,C43) -> 2 | I43: =IF(COUNT(G43:H43)=0,"",SUM(G43:H43)) | L43: =IF(COUNT(J43:K43)=0,"",SUM(J43:K43)) | M43: =IFERROR(L43/I43,"") | N43: =IFERROR(J43/G43,"") | O43: =IFERROR(K43/H43,"") | T43: =IFERROR(S43/R43,"") | W43: =IFERROR(V43/U43,"") | X43: =IFERROR((N(R43)+N(U43))/L43*1000,"") | Y43: =SUMIFS(Plans!$AA$2:$AA$4957,Plans!$A$2:$A$4957,A43,Plans!$D$2:$D$4957,C43) -> 0 | Z43: =SUMIFS(Plans!$AB$2:$AB$4957,Plans!$A$2:$A$4957,A43,Plans!$D$2:$D$4957,C43) -> 0 | AA43: =SUMIFS(Plans!$AC$2:$AC$4957,Plans!$A$2:$A$4957,A43,Plans!$D$2:$D$4957,C43) -> 0 | AB43: =SUMIFS(Plans!$AD$2:$AD$4957,Plans!$A$2:$A$4957,A43,Plans!$D$2:$D$4957,C43) -> 0 | AC43: =SUMIFS(Plans!$AE$2:$AE$4957,Plans!$A$2:$A$4957,A43,Plans!$D$2:$D$4957,C43) -> 0 | AD43: =IFERROR((Y43+Z43)/SUM(Y43:AC43),"") | AF43: https://www.humana.com/member/plain-language-policy
A44: Individual Dental | B44: IA | C44: 71051 | D44: BEST Life and Health Insurance Company | E44: No | F44: =COUNTIFS(Plans!$A$2:$A$4957,A44,Plans!$D$2:$D$4957,C44) -> 4 | G44: 264 | H44: 220 | I44: =IF(COUNT(G44:H44)=0,"",SUM(G44:H44)) -> 484 | J44: 102 | K44: 70 | L44: =IF(COUNT(J44:K44)=0,"",SUM(J44:K44)) -> 172 | M44: =IFERROR(L44/I44,"") -> 0.3553719 | N44: =IFERROR(J44/G44,"") -> 0.38636364 | O44: =IFERROR(K44/H44,"") -> 0.31818182 | R44: 0 | S44: 0 | T44: =IFERROR(S44/R44,"") | W44: =IFERROR(V44/U44,"") | X44: =IFERROR((N(R44)+N(U44))/L44*1000,"") -> 0 | Y44: =SUMIFS(Plans!$AA$2:$AA$4957,Plans!$A$2:$A$4957,A44,Plans!$D$2:$D$4957,C44) -> 0 | Z44: =SUMIFS(Plans!$AB$2:$AB$4957,Plans!$A$2:$A$4957,A44,Plans!$D$2:$D$4957,C44) -> 0 | AA44: =SUMIFS(Plans!$AC$2:$AC$4957,Plans!$A$2:$A$4957,A44,Plans!$D$2:$D$4957,C44) -> 37 | AB44: =SUMIFS(Plans!$AD$2:$AD$4957,Plans!$A$2:$A$4957,A44,Plans!$D$2:$D$4957,C44) -> 109 | AC44: =SUMIFS(Plans!$AE$2:$AE$4957,Plans!$A$2:$A$4957,A44,Plans!$D$2:$D$4957,C44) -> 0 | AD44: =IFERROR((Y44+Z44)/SUM(Y44:AC44),"") -> 0 | AE44: ** suppressed (small numbers) | AF44: https://www.bestlife.com/IA/index.html
A45: Individual Dental | B45: IA | C45: 63366 | D45: Delta Dental of Iowa | E45: No | F45: =COUNTIFS(Plans!$A$2:$A$4957,A45,Plans!$D$2:$D$4957,C45) -> 3 | G45: 352 | H45: 33950 | I45: =IF(COUNT(G45:H45)=0,"",SUM(G45:H45)) -> 34302 | J45: 234 | K45: 6160 | L45: =IF(COUNT(J45:K45)=0,"",SUM(J45:K45)) -> 6394 | M45: =IFERROR(L45/I45,"") -> 0.18640313 | N45: =IFERROR(J45/G45,"") -> 0.66477273 | O45: =IFERROR(K45/H45,"") -> 0.1814433 | P45: 0 | Q45: 85 | S45: 0 | T45: =IFERROR(S45/R45,"") | U45: 0 | V45: 0 | W45: =IFERROR(V45/U45,"") | X45: =IFERROR((N(R45)+N(U45))/L45*1000,"") -> 0 | Y45: =SUMIFS(Plans!$AA$2:$AA$4957,Plans!$A$2:$A$4957,A45,Plans!$D$2:$D$4957,C45) -> 595 | Z45: =SUMIFS(Plans!$AB$2:$AB$4957,Plans!$A$2:$A$4957,A45,Plans!$D$2:$D$4957,C45) -> 0 | AA45: =SUMIFS(Plans!$AC$2:$AC$4957,Plans!$A$2:$A$4957,A45,Plans!$D$2:$D$4957,C45) -> 230 | AB45: =SUMIFS(Plans!$AD$2:$AD$4957,Plans!$A$2:$A$4957,A45,Plans!$D$2:$D$4957,C45) -> 5569 | AC45: =SUMIFS(Plans!$AE$2:$AE$4957,Plans!$A$2:$A$4957,A45,Plans!$D$2:$D$4957,C45) -> 1900 | AD45: =IFERROR((Y45+Z45)/SUM(Y45:AC45),"") -> 0.071738606 | AE45: ** suppressed (small numbers) | AF45: https://www.deltadentalia.com/aca/aptc/
A46: Individual Dental | B46: IA | C46: 50730 | D46: Guardian Life Insurance Company of America | E46: No | F46: =COUNTIFS(Plans!$A$2:$A$4957,A46,Plans!$D$2:$D$4957,C46) -> 4 | G46: 1078 | H46: 1730 | I46: =IF(COUNT(G46:H46)=0,"",SUM(G46:H46)) -> 2808 | J46: 677 | K46: 668 | L46: =IF(COUNT(J46:K46)=0,"",SUM(J46:K46)) -> 1345 | M46: =IFERROR(L46/I46,"") -> 0.4789886 | N46: =IFERROR(J46/G46,"") -> 0.62801484 | O46: =IFERROR(K46/H46,"") -> 0.38612717 | P46: 0 | Q46: 0 | R46: 0 | S46: 0 | T46: =IFERROR(S46/R46,"") | U46: 0 | V46: 0 | W46: =IFERROR(V46/U46,"") | X46: =IFERROR((N(R46)+N(U46))/L46*1000,"") -> 0 | Y46: =SUMIFS(Plans!$AA$2:$AA$4957,Plans!$A$2:$A$4957,A46,Plans!$D$2:$D$4957,C46) -> 0 | Z46: =SUMIFS(Plans!$AB$2:$AB$4957,Plans!$A$2:$A$4957,A46,Plans!$D$2:$D$4957,C46) -> 0 | AA46: =SUMIFS(Plans!$AC$2:$AC$4957,Plans!$A$2:$A$4957,A46,Plans!$D$2:$D$4957,C46) -> 0 | AB46: =SUMIFS(Plans!$AD$2:$AD$4957,Plans!$A$2:$A$4957,A46,Plans!$D$2:$D$4957,C46) -> 0 | AC46: =SUMIFS(Plans!$AE$2:$AE$4957,Plans!$A$2:$A$4957,A46,Plans!$D$2:$D$4957,C46) -> 0 | AD46: =IFERROR((Y46+Z46)/SUM(Y46:AC46),"") | AF46: https://assets.ctfassets.net/jrhizl9l7csx/3AyKUByHZ9NSjeQMcwn8j8/53ce95a9baee7494befb828f7152268a/Exchange_Transparency_in_Coverage_8.11.25.pdf
A47: Individual Dental | B47: IN | C47: 17575 | D47: Anthem Ins Companies Inc(Anthem BCBS) | E47: No | F47: =COUNTIFS(Plans!$A$2:$A$4957,A47,Plans!$D$2:$D$4957,C47) -> 4 | G47: 1001953 | H47: 2552004 | I47: =IF(COUNT(G47:H47)=0,"",SUM(G47:H47)) -> 3553957 | J47: 540076 | K47: 267110 | L47: =IF(COUNT(J47:K47)=0,"",SUM(J47:K47)) -> 807186 | M47: =IFERROR(L47/I47,"") -> 0.22712318 | N47: =IFERROR(J47/G47,"") -> 0.53902329 | O47: =IFERROR(K47/H47,"") -> 0.10466676 | P47: 112585 | Q47: 128899 | R47: 1174 | S47: 359 | T47: =IFERROR(S47/R47,"") -> 0.30579216 | V47: 0 | W47: =IFERROR(V47/U47,"") | X47: =IFERROR((N(R47)+N(U47))/L47*1000,"") -> 1.4544355 | Y47: =SUMIFS(Plans!$AA$2:$AA$4957,Plans!$A$2:$A$4957,A47,Plans!$D$2:$D$4957,C47) -> 0 | Z47: =SUMIFS(Plans!$AB$2:$AB$4957,Plans!$A$2:$A$4957,A47,Plans!$D$2:$D$4957,C47) -> 0 | AA47: =SUMIFS(Plans!$AC$2:$AC$4957,Plans!$A$2:$A$4957,A47,Plans!$D$2:$D$4957,C47) -> 0 | AB47: =SUMIFS(Plans!$AD$2:$AD$4957,Plans!$A$2:$A$4957,A47,Plans!$D$2:$D$4957,C47) -> 1108 | AC47: =SUMIFS(Plans!$AE$2:$AE$4957,Plans!$A$2:$A$4957,A47,Plans!$D$2:$D$4957,C47) -> 751 | AD47: =IFERROR((Y47+Z47)/SUM(Y47:AC47),"") -> 0 | AE47: ** suppressed (small numbers) | AF47: https://www.anthem.com/ms/claims/home.html
A48: Individual Dental | B48: IN | C48: 83557 | D48: BEST Life and Health Insurance Company | E48: No | F48: =COUNTIFS(Plans!$A$2:$A$4957,A48,Plans!$D$2:$D$4957,C48) -> 4 | I48: =IF(COUNT(G48:H48)=0,"",SUM(G48:H48)) | L48: =IF(COUNT(J48:K48)=0,"",SUM(J48:K48)) | M48: =IFERROR(L48/I48,"") | N48: =IFERROR(J48/G48,"") | O48: =IFERROR(K48/H48,"") | T48: =IFERROR(S48/R48,"") | W48: =IFERROR(V48/U48,"") | X48: =IFERROR((N(R48)+N(U48))/L48*1000,"") | Y48: =SUMIFS(Plans!$AA$2:$AA$4957,Plans!$A$2:$A$4957,A48,Plans!$D$2:$D$4957,C48) -> 0 | Z48: =SUMIFS(Plans!$AB$2:$AB$4957,Plans!$A$2:$A$4957,A48,Plans!$D$2:$D$4957,C48) -> 0 | AA48: =SUMIFS(Plans!$AC$2:$AC$4957,Plans!$A$2:$A$4957,A48,Plans!$D$2:$D$4957,C48) -> 0 | AB48: =SUMIFS(Plans!$AD$2:$AD$4957,Plans!$A$2:$A$4957,A48,Plans!$D$2:$D$4957,C48) -> 0 | AC48: =SUMIFS(Plans!$AE$2:$AE$4957,Plans!$A$2:$A$4957,A48,Plans!$D$2:$D$4957,C48) -> 0 | AD48: =IFERROR((Y48+Z48)/SUM(Y48:AC48),"") | AE48: ** suppressed (small numbers) | AF48: https://www.bestlife.com/IN/index.html
A49: Individual Dental | B49: IN | C49: 28856 | D49: Delta Dental Plan of Indiana, Inc. | E49: No | F49: =COUNTIFS(Plans!$A$2:$A$4957,A49,Plans!$D$2:$D$4957,C49) -> 5 | G49: 1517 | H49: 21395 | I49: =IF(COUNT(G49:H49)=0,"",SUM(G49:H49)) -> 22912 | J49: 470 | K49: 4879 | L49: =IF(COUNT(J49:K49)=0,"",SUM(J49:K49)) -> 5349 | M49: =IFERROR(L49/I49,"") -> 0.23345845 | N49: =IFERROR(J49/G49,"") -> 0.30982202 | O49: =IFERROR(K49/H49,"") -> 0.22804394 | P49: 80 | Q49: 1447 | R49: 0 | S49: 0 | T49: =IFERROR(S49/R49,"") | U49: 0 | V49: 0 | W49: =IFERROR(V49/U49,"") | X49: =IFERROR((N(R49)+N(U49))/L49*1000,"") -> 0 | Y49: =SUMIFS(Plans!$AA$2:$AA$4957,Plans!$A$2:$A$4957,A49,Plans!$D$2:$D$4957,C49) -> 665 | Z49: =SUMIFS(Plans!$AB$2:$AB$4957,Plans!$A$2:$A$4957,A49,Plans!$D$2:$D$4957,C49) -> 0 | AA49: =SUMIFS(Plans!$AC$2:$AC$4957,Plans!$A$2:$A$4957,A49,Plans!$D$2:$D$4957,C49) -> 1294 | AB49: =SUMIFS(Plans!$AD$2:$AD$4957,Plans!$A$2:$A$4957,A49,Plans!$D$2:$D$4957,C49) -> 2486 | AC49: =SUMIFS(Plans!$AE$2:$AE$4957,Plans!$A$2:$A$4957,A49,Plans!$D$2:$D$4957,C49) -> 3278 | AD49: =IFERROR((Y49+Z49)/SUM(Y49:AC49),"") -> 0.086106435 | AF49: https://www.deltadentalin.com/Member/Using-Your-Benefits/Affordable-Care-Act
A50: Individual Dental | B50: IN | C50: 43433 | D50: DentaQuest USA Insurance Company, Inc. | E50: No | F50: =COUNTIFS(Plans!$A$2:$A$4957,A50,Plans!$D$2:$D$4957,C50) -> 4 | G50: 307 | H50: 1771 | I50: =IF(COUNT(G50:H50)=0,"",SUM(G50:H50)) -> 2078 | J50: 297 | K50: 526 | L50: =IF(COUNT(J50:K50)=0,"",SUM(J50:K50)) -> 823 | M50: =IFERROR(L50/I50,"") -> 0.3960539 | N50: =IFERROR(J50/G50,"") -> 0.96742671 | O50: =IFERROR(K50/H50,"") -> 0.29700734 | Q50: 63 | R50: 26 | T50: =IFERROR(S50/R50,"") -> 0 | U50: 0 | V50: 0 | W50: =IFERROR(V50/U50,"") | X50: =IFERROR((N(R50)+N(U50))/L50*1000,"") -> 31.591738 | Y50: =SUMIFS(Plans!$AA$2:$AA$4957,Plans!$A$2:$A$4957,A50,Plans!$D$2:$D$4957,C50) -> 15 | Z50: =SUMIFS(Plans!$AB$2:$AB$4957,Plans!$A$2:$A$4957,A50,Plans!$D$2:$D$4957,C50) -> 0 | AA50: =SUMIFS(Plans!$AC$2:$AC$4957,Plans!$A$2:$A$4957,A50,Plans!$D$2:$D$4957,C50) -> 113 | AB50: =SUMIFS(Plans!$AD$2:$AD$4957,Plans!$A$2:$A$4957,A50,Plans!$D$2:$D$4957,C50) -> 250 | AC50: =SUMIFS(Plans!$AE$2:$AE$4957,Plans!$A$2:$A$4957,A50,Plans!$D$2:$D$4957,C50) -> 413 | AD50: =IFERROR((Y50+Z50)/SUM(Y50:AC50),"") -> 0.018963338 | AE50: ** suppressed (small numbers) | AF50: https://www.dentaquest.com/en/members/marketplace/transparency-in-coverage
A51: Individual Dental | B51: IN | C51: 16845 | D51: Dominion Dental Services, Inc. | E51: No | F51: =COUNTIFS(Plans!$A$2:$A$4957,A51,Plans!$D$2:$D$4957,C51) -> 6 | G51: 842 | H51: 1666 | I51: =IF(COUNT(G51:H51)=0,"",SUM(G51:H51)) -> 2508 | J51: 310 | K51: 439 | L51: =IF(COUNT(J51:K51)=0,"",SUM(J51:K51)) -> 749 | M51: =IFERROR(L51/I51,"") -> 0.29864434 | N51: =IFERROR(J51/G51,"") -> 0.36817102 | O51: =IFERROR(K51/H51,"") -> 0.2635054 | P51: 0 | Q51: 101 | R51: 0 | S51: 0 | T51: =IFERROR(S51/R51,"") | U51: 0 | V51: 0 | W51: =IFERROR(V51/U51,"") | X51: =IFERROR((N(R51)+N(U51))/L51*1000,"") -> 0 | Y51: =SUMIFS(Plans!$AA$2:$AA$4957,Plans!$A$2:$A$4957,A51,Plans!$D$2:$D$4957,C51) -> 128 | Z51: =SUMIFS(Plans!$AB$2:$AB$4957,Plans!$A$2:$A$4957,A51,Plans!$D$2:$D$4957,C51) -> 18 | AA51: =SUMIFS(Plans!$AC$2:$AC$4957,Plans!$A$2:$A$4957,A51,Plans!$D$2:$D$4957,C51) -> 13 | AB51: =SUMIFS(Plans!$AD$2:$AD$4957,Plans!$A$2:$A$4957,A51,Plans!$D$2:$D$4957,C51) -> 448 | AC51: =SUMIFS(Plans!$AE$2:$AE$4957,Plans!$A$2:$A$4957,A51,Plans!$D$2:$D$4957,C51) -> 106 | AD51: =IFERROR((Y51+Z51)/SUM(Y51:AC51),"") -> 0.20476858 | AF51: https://www.dominionnational.com/wps/wcm/connect/prodnws.dominionnational.com-30097/a166049e-f578-4b90-8fda-60f3bf81a047/PY2026+Transparency+in+Coverage+Policy.pdf?MOD=AJPERES&CVID=pstswnr
A52: Individual Dental | B52: IN | C52: 59560 | D52: Guardian Life Insurance Company of America | E52: No | F52: =COUNTIFS(Plans!$A$2:$A$4957,A52,Plans!$D$2:$D$4957,C52) -> 4 | G52: 845 | H52: 2096 | I52: =IF(COUNT(G52:H52)=0,"",SUM(G52:H52)) -> 2941 | J52: 561 | K52: 844 | L52: =IF(COUNT(J52:K52)=0,"",SUM(J52:K52)) -> 1405 | M52: =IFERROR(L52/I52,"") -> 0.47772866 | N52: =IFERROR(J52/G52,"") -> 0.66390533 | O52: =IFERROR(K52/H52,"") -> 0.40267176 | P52: 0 | Q52: 0 | R52: 0 | S52: 0 | T52: =IFERROR(S52/R52,"") | U52: 0 | V52: 0 | W52: =IFERROR(V52/U52,"") | X52: =IFERROR((N(R52)+N(U52))/L52*1000,"") -> 0 | Y52: =SUMIFS(Plans!$AA$2:$AA$4957,Plans!$A$2:$A$4957,A52,Plans!$D$2:$D$4957,C52) -> 0 | Z52: =SUMIFS(Plans!$AB$2:$AB$4957,Plans!$A$2:$A$4957,A52,Plans!$D$2:$D$4957,C52) -> 0 | AA52: =SUMIFS(Plans!$AC$2:$AC$4957,Plans!$A$2:$A$4957,A52,Plans!$D$2:$D$4957,C52) -> 0 | AB52: =SUMIFS(Plans!$AD$2:$AD$4957,Plans!$A$2:$A$4957,A52,Plans!$D$2:$D$4957,C52) -> 0 | AC52: =SUMIFS(Plans!$AE$2:$AE$4957,Plans!$A$2:$A$4957,A52,Plans!$D$2:$D$4957,C52) -> 0 | AD52: =IFERROR((Y52+Z52)/SUM(Y52:AC52),"") | AF52: https://assets.ctfassets.net/jrhizl9l7csx/3AyKUByHZ9NSjeQMcwn8j8/53ce95a9baee7494befb828f7152268a/Exchange_Transparency_in_Coverage_8.11.25.pdf
A53: Individual Dental | B53: IN | C53: 33086 | D53: Health Resources, Inc. | E53: No | F53: =COUNTIFS(Plans!$A$2:$A$4957,A53,Plans!$D$2:$D$4957,C53) -> 3 | G53: 70 | H53: 2156 | I53: =IF(COUNT(G53:H53)=0,"",SUM(G53:H53)) -> 2226 | J53: 66 | K53: 782 | L53: =IF(COUNT(J53:K53)=0,"",SUM(J53:K53)) -> 848 | M53: =IFERROR(L53/I53,"") -> 0.38095238 | N53: =IFERROR(J53/G53,"") -> 0.94285714 | O53: =IFERROR(K53/H53,"") -> 0.36270872 | Q53: 81 | T53: =IFERROR(S53/R53,"") | U53: 0 | V53: 0 | W53: =IFERROR(V53/U53,"") | X53: =IFERROR((N(R53)+N(U53))/L53*1000,"") -> 0 | Y53: =SUMIFS(Plans!$AA$2:$AA$4957,Plans!$A$2:$A$4957,A53,Plans!$D$2:$D$4957,C53) -> 0 | Z53: =SUMIFS(Plans!$AB$2:$AB$4957,Plans!$A$2:$A$4957,A53,Plans!$D$2:$D$4957,C53) -> 0 | AA53: =SUMIFS(Plans!$AC$2:$AC$4957,Plans!$A$2:$A$4957,A53,Plans!$D$2:$D$4957,C53) -> 124 | AB53: =SUMIFS(Plans!$AD$2:$AD$4957,Plans!$A$2:$A$4957,A53,Plans!$D$2:$D$4957,C53) -> 479 | AC53: =SUMIFS(Plans!$AE$2:$AE$4957,Plans!$A$2:$A$4957,A53,Plans!$D$2:$D$4957,C53) -> 236 | AD53: =IFERROR((Y53+Z53)/SUM(Y53:AC53),"") -> 0 | AE53: ** suppressed (small numbers) | AF53: https://www.insuringsmiles.com/find-a-plan/marketplace-dental/dental-transparency
A54: Individual Dental | B54: IN | C54: 99791 | D54: Humana Insurance Company | E54: No | F54: =COUNTIFS(Plans!$A$2:$A$4957,A54,Plans!$D$2:$D$4957,C54) -> 2 | G54: 471 | H54: 1397 | I54: =IF(COUNT(G54:H54)=0,"",SUM(G54:H54)) -> 1868 | J54: 162 | K54: 289 | L54: =IF(COUNT(J54:K54)=0,"",SUM(J54:K54)) -> 451 | M54: =IFERROR(L54/I54,"") -> 0.24143469 | N54: =IFERROR(J54/G54,"") -> 0.34394904 | O54: =IFERROR(K54/H54,"") -> 0.20687187 | P54: 0 | Q54: 12 | R54: 0 | S54: 0 | T54: =IFERROR(S54/R54,"") | U54: 0 | V54: 0 | W54: =IFERROR(V54/U54,"") | X54: =IFERROR((N(R54)+N(U54))/L54*1000,"") -> 0 | Y54: =SUMIFS(Plans!$AA$2:$AA$4957,Plans!$A$2:$A$4957,A54,Plans!$D$2:$D$4957,C54) -> 0 | Z54: =SUMIFS(Plans!$AB$2:$AB$4957,Plans!$A$2:$A$4957,A54,Plans!$D$2:$D$4957,C54) -> 0 | AA54: =SUMIFS(Plans!$AC$2:$AC$4957,Plans!$A$2:$A$4957,A54,Plans!$D$2:$D$4957,C54) -> 51 | AB54: =SUMIFS(Plans!$AD$2:$AD$4957,Plans!$A$2:$A$4957,A54,Plans!$D$2:$D$4957,C54) -> 271 | AC54: =SUMIFS(Plans!$AE$2:$AE$4957,Plans!$A$2:$A$4957,A54,Plans!$D$2:$D$4957,C54) -> 184 | AD54: =IFERROR((Y54+Z54)/SUM(Y54:AC54),"") -> 0 | AF54: https://www.humana.com/member/plain-language-policy
A55: Individual Dental | B55: IN | C55: 87417 | D55: TRUASSURE INSURANCE COMPANY | E55: No | F55: =COUNTIFS(Plans!$A$2:$A$4957,A55,Plans!$D$2:$D$4957,C55) -> 3 | G55: 337 | H55: 821 | I55: =IF(COUNT(G55:H55)=0,"",SUM(G55:H55)) -> 1158 | J55: 77 | K55: 193 | L55: =IF(COUNT(J55:K55)=0,"",SUM(J55:K55)) -> 270 | M55: =IFERROR(L55/I55,"") -> 0.23316062 | N55: =IFERROR(J55/G55,"") -> 0.22848665 | O55: =IFERROR(K55/H55,"") -> 0.23507917 | P55: 11 | Q55: 16 | R55: 0 | S55: 0 | T55: =IFERROR(S55/R55,"") | U55: 0 | V55: 0 | W55: =IFERROR(V55/U55,"") | X55: =IFERROR((N(R55)+N(U55))/L55*1000,"") -> 0 | Y55: =SUMIFS(Plans!$AA$2:$AA$4957,Plans!$A$2:$A$4957,A55,Plans!$D$2:$D$4957,C55) -> 0 | Z55: =SUMIFS(Plans!$AB$2:$AB$4957,Plans!$A$2:$A$4957,A55,Plans!$D$2:$D$4957,C55) -> 0 | AA55: =SUMIFS(Plans!$AC$2:$AC$4957,Plans!$A$2:$A$4957,A55,Plans!$D$2:$D$4957,C55) -> 103 | AB55: =SUMIFS(Plans!$AD$2:$AD$4957,Plans!$A$2:$A$4957,A55,Plans!$D$2:$D$4957,C55) -> 0 | AC55: =SUMIFS(Plans!$AE$2:$AE$4957,Plans!$A$2:$A$4957,A55,Plans!$D$2:$D$4957,C55) -> 247 | AD55: =IFERROR((Y55+Z55)/SUM(Y55:AC55),"") -> 0 | AF55: https://www.truassure.com/aca-plans
A56: Individual Dental | B56: KS | C56: 63790 | D56: BEST Life and Health Insurance Company | E56: No | F56: =COUNTIFS(Plans!$A$2:$A$4957,A56,Plans!$D$2:$D$4957,C56) -> 4 | G56: 96 | H56: 391 | I56: =IF(COUNT(G56:H56)=0,"",SUM(G56:H56)) -> 487 | J56: 34 | K56: 120 | L56: =IF(COUNT(J56:K56)=0,"",SUM(J56:K56)) -> 154 | M56: =IFERROR(L56/I56,"") -> 0.31622177 | N56: =IFERROR(J56/G56,"") -> 0.35416667 | O56: =IFERROR(K56/H56,"") -> 0.30690537 | Q56: 24 | R56: 0 | S56: 0 | T56: =IFERROR(S56/R56,"") | W56: =IFERROR(V56/U56,"") | X56: =IFERROR((N(R56)+N(U56))/L56*1000,"") -> 0 | Y56: =SUMIFS(Plans!$AA$2:$AA$4957,Plans!$A$2:$A$4957,A56,Plans!$D$2:$D$4957,C56) -> 0 | Z56: =SUMIFS(Plans!$AB$2:$AB$4957,Plans!$A$2:$A$4957,A56,Plans!$D$2:$D$4957,C56) -> 0 | AA56: =SUMIFS(Plans!$AC$2:$AC$4957,Plans!$A$2:$A$4957,A56,Plans!$D$2:$D$4957,C56) -> 0 | AB56: =SUMIFS(Plans!$AD$2:$AD$4957,Plans!$A$2:$A$4957,A56,Plans!$D$2:$D$4957,C56) -> 88 | AC56: =SUMIFS(Plans!$AE$2:$AE$4957,Plans!$A$2:$A$4957,A56,Plans!$D$2:$D$4957,C56) -> 13 | AD56: =IFERROR((Y56+Z56)/SUM(Y56:AC56),"") -> 0 | AE56: ** suppressed (small numbers) | AF56: https://www.bestlife.com/ks/index.html
A57: Individual Dental | B57: KS | C57: 11339 | D57: Dentegra Insurance Company | E57: No | F57: =COUNTIFS(Plans!$A$2:$A$4957,A57,Plans!$D$2:$D$4957,C57) -> 2 | G57: 2771 | H57: 5000 | I57: =IF(COUNT(G57:H57)=0,"",SUM(G57:H57)) -> 7771 | J57: 1150 | K57: 2066 | L57: =IF(COUNT(J57:K57)=0,"",SUM(J57:K57)) -> 3216 | M57: =IFERROR(L57/I57,"") -> 0.41384635 | N57: =IFERROR(J57/G57,"") -> 0.41501263 | O57: =IFERROR(K57/H57,"") -> 0.4132 | P57: 106 | S57: 0 | T57: =IFERROR(S57/R57,"") | U57: 0 | V57: 0 | W57: =IFERROR(V57/U57,"") | X57: =IFERROR((N(R57)+N(U57))/L57*1000,"") -> 0 | Y57: =SUMIFS(Plans!$AA$2:$AA$4957,Plans!$A$2:$A$4957,A57,Plans!$D$2:$D$4957,C57) -> 198 | Z57: =SUMIFS(Plans!$AB$2:$AB$4957,Plans!$A$2:$A$4957,A57,Plans!$D$2:$D$4957,C57) -> 0 | AA57: =SUMIFS(Plans!$AC$2:$AC$4957,Plans!$A$2:$A$4957,A57,Plans!$D$2:$D$4957,C57) -> 126 | AB57: =SUMIFS(Plans!$AD$2:$AD$4957,Plans!$A$2:$A$4957,A57,Plans!$D$2:$D$4957,C57) -> 1038 | AC57: =SUMIFS(Plans!$AE$2:$AE$4957,Plans!$A$2:$A$4957,A57,Plans!$D$2:$D$4957,C57) -> 1843 | AD57: =IFERROR((Y57+Z57)/SUM(Y57:AC57),"") -> 0.061778471 | AE57: ** suppressed (small numbers) | AF57: https://www.dentegra.com/for-members/use-your-plan/know-your-health-care-exchange-plan.html
A58: Individual Dental | B58: KS | C58: 61779 | D58: Guardian Life Insurance Company of America | E58: No | F58: =COUNTIFS(Plans!$A$2:$A$4957,A58,Plans!$D$2:$D$4957,C58) -> 4 | G58: 691 | H58: 9657 | I58: =IF(COUNT(G58:H58)=0,"",SUM(G58:H58)) -> 10348 | J58: 1127 | K58: 3893 | L58: =IF(COUNT(J58:K58)=0,"",SUM(J58:K58)) -> 5020 | M58: =IFERROR(L58/I58,"") -> 0.4851179 | N58: =IFERROR(J58/G58,"") -> 1.6309696 | O58: =IFERROR(K58/H58,"") -> 0.40312727 | P58: 0 | Q58: 0 | R58: 0 | S58: 0 | T58: =IFERROR(S58/R58,"") | U58: 0 | V58: 0 | W58: =IFERROR(V58/U58,"") | X58: =IFERROR((N(R58)+N(U58))/L58*1000,"") -> 0 | Y58: =SUMIFS(Plans!$AA$2:$AA$4957,Plans!$A$2:$A$4957,A58,Plans!$D$2:$D$4957,C58) -> 0 | Z58: =SUMIFS(Plans!$AB$2:$AB$4957,Plans!$A$2:$A$4957,A58,Plans!$D$2:$D$4957,C58) -> 0 | AA58: =SUMIFS(Plans!$AC$2:$AC$4957,Plans!$A$2:$A$4957,A58,Plans!$D$2:$D$4957,C58) -> 0 | AB58: =SUMIFS(Plans!$AD$2:$AD$4957,Plans!$A$2:$A$4957,A58,Plans!$D$2:$D$4957,C58) -> 0 | AC58: =SUMIFS(Plans!$AE$2:$AE$4957,Plans!$A$2:$A$4957,A58,Plans!$D$2:$D$4957,C58) -> 0 | AD58: =IFERROR((Y58+Z58)/SUM(Y58:AC58),"") | AF58: https://assets.ctfassets.net/jrhizl9l7csx/3AyKUByHZ9NSjeQMcwn8j8/53ce95a9baee7494befb828f7152268a/Exchange_Transparency_in_Coverage_8.11.25.pdf
A59: Individual Dental | B59: KS | C59: 95038 | D59: Renaissance Life & Health Insurance Company of America | E59: No | F59: =COUNTIFS(Plans!$A$2:$A$4957,A59,Plans!$D$2:$D$4957,C59) -> 3 | G59: 4065 | H59: 9837 | I59: =IF(COUNT(G59:H59)=0,"",SUM(G59:H59)) -> 13902 | J59: 1382 | K59: 2608 | L59: =IF(COUNT(J59:K59)=0,"",SUM(J59:K59)) -> 3990 | M59: =IFERROR(L59/I59,"") -> 0.28700906 | N59: =IFERROR(J59/G59,"") -> 0.3399754 | O59: =IFERROR(K59/H59,"") -> 0.26512148 | P59: 318 | Q59: 648 | R59: 0 | S59: 0 | T59: =IFERROR(S59/R59,"") | U59: 0 | V59: 0 | W59: =IFERROR(V59/U59,"") | X59: =IFERROR((N(R59)+N(U59))/L59*1000,"") -> 0 | Y59: =SUMIFS(Plans!$AA$2:$AA$4957,Plans!$A$2:$A$4957,A59,Plans!$D$2:$D$4957,C59) -> 376 | Z59: =SUMIFS(Plans!$AB$2:$AB$4957,Plans!$A$2:$A$4957,A59,Plans!$D$2:$D$4957,C59) -> 0 | AA59: =SUMIFS(Plans!$AC$2:$AC$4957,Plans!$A$2:$A$4957,A59,Plans!$D$2:$D$4957,C59) -> 2193 | AB59: =SUMIFS(Plans!$AD$2:$AD$4957,Plans!$A$2:$A$4957,A59,Plans!$D$2:$D$4957,C59) -> 1426 | AC59: =SUMIFS(Plans!$AE$2:$AE$4957,Plans!$A$2:$A$4957,A59,Plans!$D$2:$D$4957,C59) -> 1435 | AD59: =IFERROR((Y59+Z59)/SUM(Y59:AC59),"") -> 0.069244936 | AF59: https://renaissancebenefits.com/understanding-your-benefits/affordable-care-act-coverage/
A60: Individual Dental | B60: KS | C60: 25268 | D60: TRUASSURE INSURANCE COMPANY | E60: No | F60: =COUNTIFS(Plans!$A$2:$A$4957,A60,Plans!$D$2:$D$4957,C60) -> 3 | G60: 785 | H60: 1819 | I60: =IF(COUNT(G60:H60)=0,"",SUM(G60:H60)) -> 2604 | J60: 256 | K60: 782 | L60: =IF(COUNT(J60:K60)=0,"",SUM(J60:K60)) -> 1038 | M60: =IFERROR(L60/I60,"") -> 0.39861751 | N60: =IFERROR(J60/G60,"") -> 0.32611465 | O60: =IFERROR(K60/H60,"") -> 0.42990654 | P60: 15 | Q60: 24 | R60: 0 | S60: 0 | T60: =IFERROR(S60/R60,"") | U60: 0 | V60: 0 | W60: =IFERROR(V60/U60,"") | X60: =IFERROR((N(R60)+N(U60))/L60*1000,"") -> 0 | Y60: =SUMIFS(Plans!$AA$2:$AA$4957,Plans!$A$2:$A$4957,A60,Plans!$D$2:$D$4957,C60) -> 0 | Z60: =SUMIFS(Plans!$AB$2:$AB$4957,Plans!$A$2:$A$4957,A60,Plans!$D$2:$D$4957,C60) -> 0 | AA60: =SUMIFS(Plans!$AC$2:$AC$4957,Plans!$A$2:$A$4957,A60,Plans!$D$2:$D$4957,C60) -> 0 | AB60: =SUMIFS(Plans!$AD$2:$AD$4957,Plans!$A$2:$A$4957,A60,Plans!$D$2:$D$4957,C60) -> 0 | AC60: =SUMIFS(Plans!$AE$2:$AE$4957,Plans!$A$2:$A$4957,A60,Plans!$D$2:$D$4957,C60) -> 1037 | AD60: =IFERROR((Y60+Z60)/SUM(Y60:AC60),"") -> 0 | AF60: https://www.truassure.com/aca-plans
A61: Individual Dental | B61: LA | C61: 78461 | D61: BEST Life and Health Insurance Company | E61: No | F61: =COUNTIFS(Plans!$A$2:$A$4957,A61,Plans!$D$2:$D$4957,C61) -> 4 | I61: =IF(COUNT(G61:H61)=0,"",SUM(G61:H61)) | L61: =IF(COUNT(J61:K61)=0,"",SUM(J61:K61)) | M61: =IFERROR(L61/I61,"") | N61: =IFERROR(J61/G61,"") | O61: =IFERROR(K61/H61,"") | T61: =IFERROR(S61/R61,"") | W61: =IFERROR(V61/U61,"") | X61: =IFERROR((N(R61)+N(U61))/L61*1000,"") | Y61: =SUMIFS(Plans!$AA$2:$AA$4957,Plans!$A$2:$A$4957,A61,Plans!$D$2:$D$4957,C61) -> 0 | Z61: =SUMIFS(Plans!$AB$2:$AB$4957,Plans!$A$2:$A$4957,A61,Plans!$D$2:$D$4957,C61) -> 0 | AA61: =SUMIFS(Plans!$AC$2:$AC$4957,Plans!$A$2:$A$4957,A61,Plans!$D$2:$D$4957,C61) -> 0 | AB61: =SUMIFS(Plans!$AD$2:$AD$4957,Plans!$A$2:$A$4957,A61,Plans!$D$2:$D$4957,C61) -> 0 | AC61: =SUMIFS(Plans!$AE$2:$AE$4957,Plans!$A$2:$A$4957,A61,Plans!$D$2:$D$4957,C61) -> 0 | AD61: =IFERROR((Y61+Z61)/SUM(Y61:AC61),"") | AE61: ** suppressed (small numbers) | AF61: https://www.bestlife.com/la/index.html
A62: Individual Dental | B62: LA | C62: 18802 | D62: Delta Dental Insurance Company | E62: No | F62: =COUNTIFS(Plans!$A$2:$A$4957,A62,Plans!$D$2:$D$4957,C62) -> 2 | G62: 998 | H62: 4870 | I62: =IF(COUNT(G62:H62)=0,"",SUM(G62:H62)) -> 5868 | J62: 323 | K62: 1350 | L62: =IF(COUNT(J62:K62)=0,"",SUM(J62:K62)) -> 1673 | M62: =IFERROR(L62/I62,"") -> 0.28510566 | N62: =IFERROR(J62/G62,"") -> 0.32364729 | O62: =IFERROR(K62/H62,"") -> 0.27720739 | Q62: 34 | S62: 0 | T62: =IFERROR(S62/R62,"") | U62: 0 | V62: 0 | W62: =IFERROR(V62/U62,"") | X62: =IFERROR((N(R62)+N(U62))/L62*1000,"") -> 0 | Y62: =SUMIFS(Plans!$AA$2:$AA$4957,Plans!$A$2:$A$4957,A62,Plans!$D$2:$D$4957,C62) -> 101 | Z62: =SUMIFS(Plans!$AB$2:$AB$4957,Plans!$A$2:$A$4957,A62,Plans!$D$2:$D$4957,C62) -> 0 | AA62: =SUMIFS(Plans!$AC$2:$AC$4957,Plans!$A$2:$A$4957,A62,Plans!$D$2:$D$4957,C62) -> 188 | AB62: =SUMIFS(Plans!$AD$2:$AD$4957,Plans!$A$2:$A$4957,A62,Plans!$D$2:$D$4957,C62) -> 903 | AC62: =SUMIFS(Plans!$AE$2:$AE$4957,Plans!$A$2:$A$4957,A62,Plans!$D$2:$D$4957,C62) -> 476 | AD62: =IFERROR((Y62+Z62)/SUM(Y62:AC62),"") -> 0.060551559 | AE62: ** suppressed (small numbers) | AF62: https://www1.deltadentalins.com/individuals-and-families/healthcare-reform-for-individuals/how-your-marketplace-plan-works.html
A63: Individual Dental | B63: LA | C63: 11904 | D63: DentaQuest USA Insurance Company, Inc. | E63: No | F63: =COUNTIFS(Plans!$A$2:$A$4957,A63,Plans!$D$2:$D$4957,C63) -> 3 | G63: 969 | H63: 867 | I63: =IF(COUNT(G63:H63)=0,"",SUM(G63:H63)) -> 1836 | J63: 583 | K63: 397 | L63: =IF(COUNT(J63:K63)=0,"",SUM(J63:K63)) -> 980 | M63: =IFERROR(L63/I63,"") -> 0.53376906 | N63: =IFERROR(J63/G63,"") -> 0.60165119 | O63: =IFERROR(K63/H63,"") -> 0.45790081 | R63: 12 | S63: 0 | T63: =IFERROR(S63/R63,"") -> 0 | U63: 0 | V63: 0 | W63: =IFERROR(V63/U63,"") | X63: =IFERROR((N(R63)+N(U63))/L63*1000,"") -> 12.244898 | Y63: =SUMIFS(Plans!$AA$2:$AA$4957,Plans!$A$2:$A$4957,A63,Plans!$D$2:$D$4957,C63) -> 13 | Z63: =SUMIFS(Plans!$AB$2:$AB$4957,Plans!$A$2:$A$4957,A63,Plans!$D$2:$D$4957,C63) -> 0 | AA63: =SUMIFS(Plans!$AC$2:$AC$4957,Plans!$A$2:$A$4957,A63,Plans!$D$2:$D$4957,C63) -> 0 | AB63: =SUMIFS(Plans!$AD$2:$AD$4957,Plans!$A$2:$A$4957,A63,Plans!$D$2:$D$4957,C63) -> 345 | AC63: =SUMIFS(Plans!$AE$2:$AE$4957,Plans!$A$2:$A$4957,A63,Plans!$D$2:$D$4957,C63) -> 595 | AD63: =IFERROR((Y63+Z63)/SUM(Y63:AC63),"") -> 0.013641133 | AE63: ** suppressed (small numbers) | AF63: https://www.dentaquest.com/en/members/marketplace/transparency-in-coverage
A64: Individual Dental | B64: LA | C64: 87390 | D64: Guardian Life Insurance Company of America | E64: No | F64: =COUNTIFS(Plans!$A$2:$A$4957,A64,Plans!$D$2:$D$4957,C64) -> 3 | G64: 1086 | H64: 1569 | I64: =IF(COUNT(G64:H64)=0,"",SUM(G64:H64)) -> 2655 | J64: 515 | K64: 652 | L64: =IF(COUNT(J64:K64)=0,"",SUM(J64:K64)) -> 1167 | M64: =IFERROR(L64/I64,"") -> 0.43954802 | N64: =IFERROR(J64/G64,"") -> 0.47421731 | O64: =IFERROR(K64/H64,"") -> 0.41555131 | P64: 0 | Q64: 0 | R64: 0 | S64: 0 | T64: =IFERROR(S64/R64,"") | U64: 0 | V64: 0 | W64: =IFERROR(V64/U64,"") | X64: =IFERROR((N(R64)+N(U64))/L64*1000,"") -> 0 | Y64: =SUMIFS(Plans!$AA$2:$AA$4957,Plans!$A$2:$A$4957,A64,Plans!$D$2:$D$4957,C64) -> 0 | Z64: =SUMIFS(Plans!$AB$2:$AB$4957,Plans!$A$2:$A$4957,A64,Plans!$D$2:$D$4957,C64) -> 0 | AA64: =SUMIFS(Plans!$AC$2:$AC$4957,Plans!$A$2:$A$4957,A64,Plans!$D$2:$D$4957,C64) -> 0 | AB64: =SUMIFS(Plans!$AD$2:$AD$4957,Plans!$A$2:$A$4957,A64,Plans!$D$2:$D$4957,C64) -> 0 | AC64: =SUMIFS(Plans!$AE$2:$AE$4957,Plans!$A$2:$A$4957,A64,Plans!$D$2:$D$4957,C64) -> 0 | AD64: =IFERROR((Y64+Z64)/SUM(Y64:AC64),"") | AF64: https://assets.ctfassets.net/jrhizl9l7csx/3AyKUByHZ9NSjeQMcwn8j8/53ce95a9baee7494befb828f7152268a/Exchange_Transparency_in_Coverage_8.11.25.pdf
A65: Individual Dental | B65: LA | C65: 44965 | D65: Humana Health Benefit Plan of Louisiana, Inc. | E65: No | F65: =COUNTIFS(Plans!$A$2:$A$4957,A65,Plans!$D$2:$D$4957,C65) -> 1 | G65: 1037 | H65: 3774 | I65: =IF(COUNT(G65:H65)=0,"",SUM(G65:H65)) -> 4811 | J65: 253 | K65: 737 | L65: =IF(COUNT(J65:K65)=0,"",SUM(J65:K65)) -> 990 | M65: =IFERROR(L65/I65,"") -> 0.20577842 | N65: =IFERROR(J65/G65,"") -> 0.243973 | O65: =IFERROR(K65/H65,"") -> 0.19528352 | P65: 0 | Q65: 11 | R65: 0 | S65: 0 | T65: =IFERROR(S65/R65,"") | U65: 0 | V65: 0 | W65: =IFERROR(V65/U65,"") | X65: =IFERROR((N(R65)+N(U65))/L65*1000,"") -> 0 | Y65: =SUMIFS(Plans!$AA$2:$AA$4957,Plans!$A$2:$A$4957,A65,Plans!$D$2:$D$4957,C65) -> 0 | Z65: =SUMIFS(Plans!$AB$2:$AB$4957,Plans!$A$2:$A$4957,A65,Plans!$D$2:$D$4957,C65) -> 0 | AA65: =SUMIFS(Plans!$AC$2:$AC$4957,Plans!$A$2:$A$4957,A65,Plans!$D$2:$D$4957,C65) -> 170 | AB65: =SUMIFS(Plans!$AD$2:$AD$4957,Plans!$A$2:$A$4957,A65,Plans!$D$2:$D$4957,C65) -> 758 | AC65: =SUMIFS(Plans!$AE$2:$AE$4957,Plans!$A$2:$A$4957,A65,Plans!$D$2:$D$4957,C65) -> 227 | AD65: =IFERROR((Y65+Z65)/SUM(Y65:AC65),"") -> 0 | AF65: https://www.humana.com/member/plain-language-policy
A66: Individual Dental | B66: LA | C66: 97176 | D66: Louisiana Health Service & Indemnity Company | E66: No | F66: =COUNTIFS(Plans!$A$2:$A$4957,A66,Plans!$D$2:$D$4957,C66) -> 3 | G66: 80498 | H66: 992770 | I66: =IF(COUNT(G66:H66)=0,"",SUM(G66:H66)) -> 1073268 | J66: 8666 | K66: 147920 | L66: =IF(COUNT(J66:K66)=0,"",SUM(J66:K66)) -> 156586 | M66: =IFERROR(L66/I66,"") -> 0.14589646 | N66: =IFERROR(J66/G66,"") -> 0.10765485 | O66: =IFERROR(K66/H66,"") -> 0.14899725 | P66: 226 | Q66: 314 | R66: 364 | S66: 117 | T66: =IFERROR(S66/R66,"") -> 0.32142857 | U66: 41 | W66: =IFERROR(V66/U66,"") -> 0 | X66: =IFERROR((N(R66)+N(U66))/L66*1000,"") -> 2.5864381 | Y66: =SUMIFS(Plans!$AA$2:$AA$4957,Plans!$A$2:$A$4957,A66,Plans!$D$2:$D$4957,C66) -> 18 | Z66: =SUMIFS(Plans!$AB$2:$AB$4957,Plans!$A$2:$A$4957,A66,Plans!$D$2:$D$4957,C66) -> 0 | AA66: =SUMIFS(Plans!$AC$2:$AC$4957,Plans!$A$2:$A$4957,A66,Plans!$D$2:$D$4957,C66) -> 52 | AB66: =SUMIFS(Plans!$AD$2:$AD$4957,Plans!$A$2:$A$4957,A66,Plans!$D$2:$D$4957,C66) -> 3324 | AC66: =SUMIFS(Plans!$AE$2:$AE$4957,Plans!$A$2:$A$4957,A66,Plans!$D$2:$D$4957,C66) -> 1700 | AD66: =IFERROR((Y66+Z66)/SUM(Y66:AC66),"") -> 0.0035335689 | AE66: ** suppressed (small numbers) | AF66: https://www.lablue.com/footer/transparencylahsic
A67: Individual Dental | B67: LA | C67: 28419 | D67: Renaissance Life & Health Insurance Company of America | E67: No | F67: =COUNTIFS(Plans!$A$2:$A$4957,A67,Plans!$D$2:$D$4957,C67) -> 4 | G67: 451 | H67: 643 | I67: =IF(COUNT(G67:H67)=0,"",SUM(G67:H67)) -> 1094 | J67: 172 | K67: 221 | L67: =IF(COUNT(J67:K67)=0,"",SUM(J67:K67)) -> 393 | M67: =IFERROR(L67/I67,"") -> 0.35923218 | N67: =IFERROR(J67/G67,"") -> 0.38137472 | O67: =IFERROR(K67/H67,"") -> 0.3437014 | P67: 39 | Q67: 28 | R67: 0 | S67: 0 | T67: =IFERROR(S67/R67,"") | U67: 0 | V67: 0 | W67: =IFERROR(V67/U67,"") | X67: =IFERROR((N(R67)+N(U67))/L67*1000,"") -> 0 | Y67: =SUMIFS(Plans!$AA$2:$AA$4957,Plans!$A$2:$A$4957,A67,Plans!$D$2:$D$4957,C67) -> 14 | Z67: =SUMIFS(Plans!$AB$2:$AB$4957,Plans!$A$2:$A$4957,A67,Plans!$D$2:$D$4957,C67) -> 0 | AA67: =SUMIFS(Plans!$AC$2:$AC$4957,Plans!$A$2:$A$4957,A67,Plans!$D$2:$D$4957,C67) -> 307 | AB67: =SUMIFS(Plans!$AD$2:$AD$4957,Plans!$A$2:$A$4957,A67,Plans!$D$2:$D$4957,C67) -> 89 | AC67: =SUMIFS(Plans!$AE$2:$AE$4957,Plans!$A$2:$A$4957,A67,Plans!$D$2:$D$4957,C67) -> 141 | AD67: =IFERROR((Y67+Z67)/SUM(Y67:AC67),"") -> 0.025408348 | AF67: https://renaissancebenefits.com/understanding-your-benefits/affordable-care-act-coverage/
A68: Individual Dental | B68: MI | C68: 35700 | D68: BEST Life and Health Insurance Company | E68: No | F68: =COUNTIFS(Plans!$A$2:$A$4957,A68,Plans!$D$2:$D$4957,C68) -> 4 | G68: 18 | H68: 121 | I68: =IF(COUNT(G68:H68)=0,"",SUM(G68:H68)) -> 139 | J68: 13 | K68: 81 | L68: =IF(COUNT(J68:K68)=0,"",SUM(J68:K68)) -> 94 | M68: =IFERROR(L68/I68,"") -> 0.67625899 | N68: =IFERROR(J68/G68,"") -> 0.72222222 | O68: =IFERROR(K68/H68,"") -> 0.66942149 | P68: 0 | Q68: 26 | R68: 0 | S68: 0 | T68: =IFERROR(S68/R68,"") | V68: 0 | W68: =IFERROR(V68/U68,"") | X68: =IFERROR((N(R68)+N(U68))/L68*1000,"") -> 0 | Y68: =SUMIFS(Plans!$AA$2:$AA$4957,Plans!$A$2:$A$4957,A68,Plans!$D$2:$D$4957,C68) -> 0 | Z68: =SUMIFS(Plans!$AB$2:$AB$4957,Plans!$A$2:$A$4957,A68,Plans!$D$2:$D$4957,C68) -> 0 | AA68: =SUMIFS(Plans!$AC$2:$AC$4957,Plans!$A$2:$A$4957,A68,Plans!$D$2:$D$4957,C68) -> 0 | AB68: =SUMIFS(Plans!$AD$2:$AD$4957,Plans!$A$2:$A$4957,A68,Plans!$D$2:$D$4957,C68) -> 56 | AC68: =SUMIFS(Plans!$AE$2:$AE$4957,Plans!$A$2:$A$4957,A68,Plans!$D$2:$D$4957,C68) -> 18 | AD68: =IFERROR((Y68+Z68)/SUM(Y68:AC68),"") -> 0 | AE68: ** suppressed (small numbers) | AF68: https://www.bestlife.com/MI/index.html
A69: Individual Dental | B69: MI | C69: 15560 | D69: Blue Cross Blue Shield of Michigan Mutual Insurance Company | E69: No | F69: =COUNTIFS(Plans!$A$2:$A$4957,A69,Plans!$D$2:$D$4957,C69) -> 6 | G69: 434890 | H69: 1807844 | I69: =IF(COUNT(G69:H69)=0,"",SUM(G69:H69)) -> 2242734 | J69: 74902 | K69: 236257 | L69: =IF(COUNT(J69:K69)=0,"",SUM(J69:K69)) -> 311159 | M69: =IFERROR(L69/I69,"") -> 0.13874093 | N69: =IFERROR(J69/G69,"") -> 0.17223206 | O69: =IFERROR(K69/H69,"") -> 0.1306844 | P69: 6489 | Q69: 110220 | R69: 203 | S69: 95 | T69: =IFERROR(S69/R69,"") -> 0.4679803 | U69: 78 | W69: =IFERROR(V69/U69,"") -> 0 | X69: =IFERROR((N(R69)+N(U69))/L69*1000,"") -> 0.90307528 | Y69: =SUMIFS(Plans!$AA$2:$AA$4957,Plans!$A$2:$A$4957,A69,Plans!$D$2:$D$4957,C69) -> 1240 | Z69: =SUMIFS(Plans!$AB$2:$AB$4957,Plans!$A$2:$A$4957,A69,Plans!$D$2:$D$4957,C69) -> 0 | AA69: =SUMIFS(Plans!$AC$2:$AC$4957,Plans!$A$2:$A$4957,A69,Plans!$D$2:$D$4957,C69) -> 140 | AB69: =SUMIFS(Plans!$AD$2:$AD$4957,Plans!$A$2:$A$4957,A69,Plans!$D$2:$D$4957,C69) -> 787 | AC69: =SUMIFS(Plans!$AE$2:$AE$4957,Plans!$A$2:$A$4957,A69,Plans!$D$2:$D$4957,C69) -> 26 | AD69: =IFERROR((Y69+Z69)/SUM(Y69:AC69),"") -> 0.56543548 | AE69: ** suppressed (small numbers) | AF69: https://www.bcbsm.com/what-to-know-about-aca-plans/index/
A70: Individual Dental | B70: MI | C70: 31256 | D70: DENCAP Dental Plans, Inc. | E70: No | F70: =COUNTIFS(Plans!$A$2:$A$4957,A70,Plans!$D$2:$D$4957,C70) -> 3 | G70: 20 | H70: 23 | I70: =IF(COUNT(G70:H70)=0,"",SUM(G70:H70)) -> 43 | L70: =IF(COUNT(J70:K70)=0,"",SUM(J70:K70)) | M70: =IFERROR(L70/I70,"") | N70: =IFERROR(J70/G70,"") -> 0 | O70: =IFERROR(K70/H70,"") -> 0 | P70: 0 | R70: 0 | S70: 0 | T70: =IFERROR(S70/R70,"") | U70: 0 | V70: 0 | W70: =IFERROR(V70/U70,"") | X70: =IFERROR((N(R70)+N(U70))/L70*1000,"") | Y70: =SUMIFS(Plans!$AA$2:$AA$4957,Plans!$A$2:$A$4957,A70,Plans!$D$2:$D$4957,C70) -> 0 | Z70: =SUMIFS(Plans!$AB$2:$AB$4957,Plans!$A$2:$A$4957,A70,Plans!$D$2:$D$4957,C70) -> 0 | AA70: =SUMIFS(Plans!$AC$2:$AC$4957,Plans!$A$2:$A$4957,A70,Plans!$D$2:$D$4957,C70) -> 0 | AB70: =SUMIFS(Plans!$AD$2:$AD$4957,Plans!$A$2:$A$4957,A70,Plans!$D$2:$D$4957,C70) -> 0 | AC70: =SUMIFS(Plans!$AE$2:$AE$4957,Plans!$A$2:$A$4957,A70,Plans!$D$2:$D$4957,C70) -> 0 | AD70: =IFERROR((Y70+Z70)/SUM(Y70:AC70),"") | AE70: ** suppressed (small numbers) | AF70: https://dencap.com/general-policies/
A71: Individual Dental | B71: MI | C71: 34930 | D71: Delta Dental Plan of Michigan, Inc. | E71: No | F71: =COUNTIFS(Plans!$A$2:$A$4957,A71,Plans!$D$2:$D$4957,C71) -> 5 | G71: 6077 | H71: 118261 | I71: =IF(COUNT(G71:H71)=0,"",SUM(G71:H71)) -> 124338 | J71: 1658 | K71: 19820 | L71: =IF(COUNT(J71:K71)=0,"",SUM(J71:K71)) -> 21478 | M71: =IFERROR(L71/I71,"") -> 0.17273882 | N71: =IFERROR(J71/G71,"") -> 0.27283199 | O71: =IFERROR(K71/H71,"") -> 0.1675954 | P71: 334 | Q71: 7890 | S71: 0 | T71: =IFERROR(S71/R71,"") | U71: 0 | V71: 0 | W71: =IFERROR(V71/U71,"") | X71: =IFERROR((N(R71)+N(U71))/L71*1000,"") -> 0 | Y71: =SUMIFS(Plans!$AA$2:$AA$4957,Plans!$A$2:$A$4957,A71,Plans!$D$2:$D$4957,C71) -> 3296 | Z71: =SUMIFS(Plans!$AB$2:$AB$4957,Plans!$A$2:$A$4957,A71,Plans!$D$2:$D$4957,C71) -> 33 | AA71: =SUMIFS(Plans!$AC$2:$AC$4957,Plans!$A$2:$A$4957,A71,Plans!$D$2:$D$4957,C71) -> 3287 | AB71: =SUMIFS(Plans!$AD$2:$AD$4957,Plans!$A$2:$A$4957,A71,Plans!$D$2:$D$4957,C71) -> 7892 | AC71: =SUMIFS(Plans!$AE$2:$AE$4957,Plans!$A$2:$A$4957,A71,Plans!$D$2:$D$4957,C71) -> 15435 | AD71: =IFERROR((Y71+Z71)/SUM(Y71:AC71),"") -> 0.1111779 | AE71: ** suppressed (small numbers) | AF71: https://www.deltadentalmi.com/Member/Using-Your-Benefits/Affordable-Care-Act
A72: Individual Dental | B72: MI | C72: 15676 | D72: Dominion Dental Services, Inc. | E72: No | F72: =COUNTIFS(Plans!$A$2:$A$4957,A72,Plans!$D$2:$D$4957,C72) -> 6 | G72: 1148 | H72: 3368 | I72: =IF(COUNT(G72:H72)=0,"",SUM(G72:H72)) -> 4516 | J72: 405 | K72: 733 | L72: =IF(COUNT(J72:K72)=0,"",SUM(J72:K72)) -> 1138 | M72: =IFERROR(L72/I72,"") -> 0.25199291 | N72: =IFERROR(J72/G72,"") -> 0.35278746 | O72: =IFERROR(K72/H72,"") -> 0.21763658 | P72: 0 | Q72: 119 | R72: 0 | S72: 0 | T72: =IFERROR(S72/R72,"") | U72: 0 | V72: 0 | W72: =IFERROR(V72/U72,"") | X72: =IFERROR((N(R72)+N(U72))/L72*1000,"") -> 0 | Y72: =SUMIFS(Plans!$AA$2:$AA$4957,Plans!$A$2:$A$4957,A72,Plans!$D$2:$D$4957,C72) -> 262 | Z72: =SUMIFS(Plans!$AB$2:$AB$4957,Plans!$A$2:$A$4957,A72,Plans!$D$2:$D$4957,C72) -> 0 | AA72: =SUMIFS(Plans!$AC$2:$AC$4957,Plans!$A$2:$A$4957,A72,Plans!$D$2:$D$4957,C72) -> 0 | AB72: =SUMIFS(Plans!$AD$2:$AD$4957,Plans!$A$2:$A$4957,A72,Plans!$D$2:$D$4957,C72) -> 681 | AC72: =SUMIFS(Plans!$AE$2:$AE$4957,Plans!$A$2:$A$4957,A72,Plans!$D$2:$D$4957,C72) -> 157 | AD72: =IFERROR((Y72+Z72)/SUM(Y72:AC72),"") -> 0.23818182 | AF72: https://www.dominionnational.com/wps/wcm/connect/prodnws.dominionnational.com-30097/a166049e-f578-4b90-8fda-60f3bf81a047/PY2026+Transparency+in+Coverage+Policy.pdf?MOD=AJPERES&CVID=pstswnr
A73: Individual Dental | B73: MI | C73: 88507 | D73: Educators Health Plans Life, Accident, and Health, Inc | E73: No | F73: =COUNTIFS(Plans!$A$2:$A$4957,A73,Plans!$D$2:$D$4957,C73) -> 4 | G73: 8844 | H73: 12310 | I73: =IF(COUNT(G73:H73)=0,"",SUM(G73:H73)) -> 21154 | J73: 3766 | K73: 3803 | L73: =IF(COUNT(J73:K73)=0,"",SUM(J73:K73)) -> 7569 | M73: =IFERROR(L73/I73,"") -> 0.35780467 | N73: =IFERROR(J73/G73,"") -> 0.42582542 | O73: =IFERROR(K73/H73,"") -> 0.30893582 | P73: 660 | Q73: 897 | T73: =IFERROR(S73/R73,"") | U73: 0 | V73: 0 | W73: =IFERROR(V73/U73,"") | X73: =IFERROR((N(R73)+N(U73))/L73*1000,"") -> 0 | Y73: =SUMIFS(Plans!$AA$2:$AA$4957,Plans!$A$2:$A$4957,A73,Plans!$D$2:$D$4957,C73) -> 4452 | Z73: =SUMIFS(Plans!$AB$2:$AB$4957,Plans!$A$2:$A$4957,A73,Plans!$D$2:$D$4957,C73) -> 0 | AA73: =SUMIFS(Plans!$AC$2:$AC$4957,Plans!$A$2:$A$4957,A73,Plans!$D$2:$D$4957,C73) -> 790 | AB73: =SUMIFS(Plans!$AD$2:$AD$4957,Plans!$A$2:$A$4957,A73,Plans!$D$2:$D$4957,C73) -> 2316 | AC73: =SUMIFS(Plans!$AE$2:$AE$4957,Plans!$A$2:$A$4957,A73,Plans!$D$2:$D$4957,C73) -> 0 | AD73: =IFERROR((Y73+Z73)/SUM(Y73:AC73),"") -> 0.58904472 | AE73: ** suppressed (small numbers) | AF73: https://emihealth.com/Policies/MichiganDental
A74: Individual Dental | B74: MI | C74: 66587 | D74: Guardian Life Insurance Company of America | E74: No | F74: =COUNTIFS(Plans!$A$2:$A$4957,A74,Plans!$D$2:$D$4957,C74) -> 3 | G74: 2431 | H74: 3957 | I74: =IF(COUNT(G74:H74)=0,"",SUM(G74:H74)) -> 6388 | J74: 1594 | K74: 1304 | L74: =IF(COUNT(J74:K74)=0,"",SUM(J74:K74)) -> 2898 | M74: =IFERROR(L74/I74,"") -> 0.45366312 | N74: =IFERROR(J74/G74,"") -> 0.65569724 | O74: =IFERROR(K74/H74,"") -> 0.32954258 | P74: 0 | Q74: 0 | R74: 0 | S74: 0 | T74: =IFERROR(S74/R74,"") | U74: 0 | V74: 0 | W74: =IFERROR(V74/U74,"") | X74: =IFERROR((N(R74)+N(U74))/L74*1000,"") -> 0 | Y74: =SUMIFS(Plans!$AA$2:$AA$4957,Plans!$A$2:$A$4957,A74,Plans!$D$2:$D$4957,C74) -> 0 | Z74: =SUMIFS(Plans!$AB$2:$AB$4957,Plans!$A$2:$A$4957,A74,Plans!$D$2:$D$4957,C74) -> 0 | AA74: =SUMIFS(Plans!$AC$2:$AC$4957,Plans!$A$2:$A$4957,A74,Plans!$D$2:$D$4957,C74) -> 0 | AB74: =SUMIFS(Plans!$AD$2:$AD$4957,Plans!$A$2:$A$4957,A74,Plans!$D$2:$D$4957,C74) -> 0 | AC74: =SUMIFS(Plans!$AE$2:$AE$4957,Plans!$A$2:$A$4957,A74,Plans!$D$2:$D$4957,C74) -> 0 | AD74: =IFERROR((Y74+Z74)/SUM(Y74:AC74),"") | AF74: https://assets.ctfassets.net/jrhizl9l7csx/3AyKUByHZ9NSjeQMcwn8j8/53ce95a9baee7494befb828f7152268a/Exchange_Transparency_in_Coverage_8.11.25.pdf
A75: Individual Dental | B75: MI | C75: 62294 | D75: Humana Insurance Company | E75: No | F75: =COUNTIFS(Plans!$A$2:$A$4957,A75,Plans!$D$2:$D$4957,C75) -> 1 | G75: 1052 | H75: 4925 | I75: =IF(COUNT(G75:H75)=0,"",SUM(G75:H75)) -> 5977 | J75: 273 | K75: 885 | L75: =IF(COUNT(J75:K75)=0,"",SUM(J75:K75)) -> 1158 | M75: =IFERROR(L75/I75,"") -> 0.19374268 | N75: =IFERROR(J75/G75,"") -> 0.2595057 | O75: =IFERROR(K75/H75,"") -> 0.17969543 | P75: 0 | Q75: 15 | R75: 11 | S75: 0 | T75: =IFERROR(S75/R75,"") -> 0 | U75: 0 | V75: 0 | W75: =IFERROR(V75/U75,"") | X75: =IFERROR((N(R75)+N(U75))/L75*1000,"") -> 9.4991364 | Y75: =SUMIFS(Plans!$AA$2:$AA$4957,Plans!$A$2:$A$4957,A75,Plans!$D$2:$D$4957,C75) -> 0 | Z75: =SUMIFS(Plans!$AB$2:$AB$4957,Plans!$A$2:$A$4957,A75,Plans!$D$2:$D$4957,C75) -> 14 | AA75: =SUMIFS(Plans!$AC$2:$AC$4957,Plans!$A$2:$A$4957,A75,Plans!$D$2:$D$4957,C75) -> 156 | AB75: =SUMIFS(Plans!$AD$2:$AD$4957,Plans!$A$2:$A$4957,A75,Plans!$D$2:$D$4957,C75) -> 931 | AC75: =SUMIFS(Plans!$AE$2:$AE$4957,Plans!$A$2:$A$4957,A75,Plans!$D$2:$D$4957,C75) -> 245 | AD75: =IFERROR((Y75+Z75)/SUM(Y75:AC75),"") -> 0.010401189 | AF75: https://www.humana.com/member/plain-language-policy
A76: Individual Dental | B76: MI | C76: 95233 | D76: Paramount Insurance Company | E76: No | F76: =COUNTIFS(Plans!$A$2:$A$4957,A76,Plans!$D$2:$D$4957,C76) -> 3 | G76: 102 | H76: 1695 | I76: =IF(COUNT(G76:H76)=0,"",SUM(G76:H76)) -> 1797 | J76: 97 | K76: 596 | L76: =IF(COUNT(J76:K76)=0,"",SUM(J76:K76)) -> 693 | M76: =IFERROR(L76/I76,"") -> 0.38564274 | N76: =IFERROR(J76/G76,"") -> 0.95098039 | O76: =IFERROR(K76/H76,"") -> 0.35162242 | Q76: 147 | T76: =IFERROR(S76/R76,"") | U76: 0 | V76: 0 | W76: =IFERROR(V76/U76,"") | X76: =IFERROR((N(R76)+N(U76))/L76*1000,"") -> 0 | Y76: =SUMIFS(Plans!$AA$2:$AA$4957,Plans!$A$2:$A$4957,A76,Plans!$D$2:$D$4957,C76) -> 0 | Z76: =SUMIFS(Plans!$AB$2:$AB$4957,Plans!$A$2:$A$4957,A76,Plans!$D$2:$D$4957,C76) -> 0 | AA76: =SUMIFS(Plans!$AC$2:$AC$4957,Plans!$A$2:$A$4957,A76,Plans!$D$2:$D$4957,C76) -> 126 | AB76: =SUMIFS(Plans!$AD$2:$AD$4957,Plans!$A$2:$A$4957,A76,Plans!$D$2:$D$4957,C76) -> 434 | AC76: =SUMIFS(Plans!$AE$2:$AE$4957,Plans!$A$2:$A$4957,A76,Plans!$D$2:$D$4957,C76) -> 134 | AD76: =IFERROR((Y76+Z76)/SUM(Y76:AC76),"") -> 0 | AE76: ** suppressed (small numbers) | AF76: https://www.insuringsmiles.com/find-a-plan/marketplace-dental/dental-transparency
A77: Individual Dental | B77: MI | C77: 63631 | D77: UnitedHealthcare Insurance Company | E77: No | F77: =COUNTIFS(Plans!$A$2:$A$4957,A77,Plans!$D$2:$D$4957,C77) -> 2 | G77: 301 | H77: 1364 | I77: =IF(COUNT(G77:H77)=0,"",SUM(G77:H77)) -> 1665 | J77: 179 | K77: 168 | L77: =IF(COUNT(J77:K77)=0,"",SUM(J77:K77)) -> 347 | M77: =IFERROR(L77/I77,"") -> 0.20840841 | N77: =IFERROR(J77/G77,"") -> 0.59468439 | O77: =IFERROR(K77/H77,"") -> 0.12316716 | P77: 0 | Q77: 0 | R77: 11 | T77: =IFERROR(S77/R77,"") -> 0 | U77: 0 | V77: 0 | W77: =IFERROR(V77/U77,"") | X77: =IFERROR((N(R77)+N(U77))/L77*1000,"") -> 31.700288 | Y77: =SUMIFS(Plans!$AA$2:$AA$4957,Plans!$A$2:$A$4957,A77,Plans!$D$2:$D$4957,C77) -> 0 | Z77: =SUMIFS(Plans!$AB$2:$AB$4957,Plans!$A$2:$A$4957,A77,Plans!$D$2:$D$4957,C77) -> 0 | AA77: =SUMIFS(Plans!$AC$2:$AC$4957,Plans!$A$2:$A$4957,A77,Plans!$D$2:$D$4957,C77) -> 235 | AB77: =SUMIFS(Plans!$AD$2:$AD$4957,Plans!$A$2:$A$4957,A77,Plans!$D$2:$D$4957,C77) -> 110 | AC77: =SUMIFS(Plans!$AE$2:$AE$4957,Plans!$A$2:$A$4957,A77,Plans!$D$2:$D$4957,C77) -> 0 | AD77: =IFERROR((Y77+Z77)/SUM(Y77:AC77),"") -> 0 | AE77: ** suppressed (small numbers) | AF77: https://www.solsticecare.com/claimsFaq.aspx
A78: Individual Dental | B78: MO | C78: 29416 | D78: BEST Life and Health Insurance Company | E78: No | F78: =COUNTIFS(Plans!$A$2:$A$4957,A78,Plans!$D$2:$D$4957,C78) -> 4 | G78: 13 | H78: 81 | I78: =IF(COUNT(G78:H78)=0,"",SUM(G78:H78)) -> 94 | K78: 36 | L78: =IF(COUNT(J78:K78)=0,"",SUM(J78:K78)) -> 36 | M78: =IFERROR(L78/I78,"") -> 0.38297872 | N78: =IFERROR(J78/G78,"") -> 0 | O78: =IFERROR(K78/H78,"") -> 0.44444444 | P78: 0 | R78: 0 | S78: 0 | T78: =IFERROR(S78/R78,"") | W78: =IFERROR(V78/U78,"") | X78: =IFERROR((N(R78)+N(U78))/L78*1000,"") -> 0 | Y78: =SUMIFS(Plans!$AA$2:$AA$4957,Plans!$A$2:$A$4957,A78,Plans!$D$2:$D$4957,C78) -> 0 | Z78: =SUMIFS(Plans!$AB$2:$AB$4957,Plans!$A$2:$A$4957,A78,Plans!$D$2:$D$4957,C78) -> 0 | AA78: =SUMIFS(Plans!$AC$2:$AC$4957,Plans!$A$2:$A$4957,A78,Plans!$D$2:$D$4957,C78) -> 0 | AB78: =SUMIFS(Plans!$AD$2:$AD$4957,Plans!$A$2:$A$4957,A78,Plans!$D$2:$D$4957,C78) -> 24 | AC78: =SUMIFS(Plans!$AE$2:$AE$4957,Plans!$A$2:$A$4957,A78,Plans!$D$2:$D$4957,C78) -> 0 | AD78: =IFERROR((Y78+Z78)/SUM(Y78:AC78),"") -> 0 | AE78: ** suppressed (small numbers) | AF78: https://www.bestlife.com/mo/index.html
A79: Individual Dental | B79: MO | C79: 58883 | D79: DentaQuest National Insurance Company, Inc. | E79: No | F79: =COUNTIFS(Plans!$A$2:$A$4957,A79,Plans!$D$2:$D$4957,C79) -> 3 | G79: 595 | H79: 466 | I79: =IF(COUNT(G79:H79)=0,"",SUM(G79:H79)) -> 1061 | J79: 281 | K79: 155 | L79: =IF(COUNT(J79:K79)=0,"",SUM(J79:K79)) -> 436 | M79: =IFERROR(L79/I79,"") -> 0.41093308 | N79: =IFERROR(J79/G79,"") -> 0.47226891 | O79: =IFERROR(K79/H79,"") -> 0.33261803 | P79: 0 | Q79: 0 | S79: 0 | T79: =IFERROR(S79/R79,"") | U79: 0 | V79: 0 | W79: =IFERROR(V79/U79,"") | X79: =IFERROR((N(R79)+N(U79))/L79*1000,"") -> 0 | Y79: =SUMIFS(Plans!$AA$2:$AA$4957,Plans!$A$2:$A$4957,A79,Plans!$D$2:$D$4957,C79) -> 0 | Z79: =SUMIFS(Plans!$AB$2:$AB$4957,Plans!$A$2:$A$4957,A79,Plans!$D$2:$D$4957,C79) -> 0 | AA79: =SUMIFS(Plans!$AC$2:$AC$4957,Plans!$A$2:$A$4957,A79,Plans!$D$2:$D$4957,C79) -> 0 | AB79: =SUMIFS(Plans!$AD$2:$AD$4957,Plans!$A$2:$A$4957,A79,Plans!$D$2:$D$4957,C79) -> 199 | AC79: =SUMIFS(Plans!$AE$2:$AE$4957,Plans!$A$2:$A$4957,A79,Plans!$D$2:$D$4957,C79) -> 197 | AD79: =IFERROR((Y79+Z79)/SUM(Y79:AC79),"") -> 0 | AE79: ** suppressed (small numbers) | AF79: https://www.dentaquest.com/en/members/marketplace/transparency-in-coverage
A80: Individual Dental | B80: MO | C80: 43512 | D80: Dominion Dental Services, Inc. | E80: No | F80: =COUNTIFS(Plans!$A$2:$A$4957,A80,Plans!$D$2:$D$4957,C80) -> 6 | G80: 926 | H80: 3308 | I80: =IF(COUNT(G80:H80)=0,"",SUM(G80:H80)) -> 4234 | J80: 314 | K80: 865 | L80: =IF(COUNT(J80:K80)=0,"",SUM(J80:K80)) -> 1179 | M80: =IFERROR(L80/I80,"") -> 0.27846009 | N80: =IFERROR(J80/G80,"") -> 0.33909287 | O80: =IFERROR(K80/H80,"") -> 0.2614873 | P80: 52 | Q80: 245 | S80: 0 | T80: =IFERROR(S80/R80,"") | U80: 0 | V80: 0 | W80: =IFERROR(V80/U80,"") | X80: =IFERROR((N(R80)+N(U80))/L80*1000,"") -> 0 | Y80: =SUMIFS(Plans!$AA$2:$AA$4957,Plans!$A$2:$A$4957,A80,Plans!$D$2:$D$4957,C80) -> 236 | Z80: =SUMIFS(Plans!$AB$2:$AB$4957,Plans!$A$2:$A$4957,A80,Plans!$D$2:$D$4957,C80) -> 32 | AA80: =SUMIFS(Plans!$AC$2:$AC$4957,Plans!$A$2:$A$4957,A80,Plans!$D$2:$D$4957,C80) -> 0 | AB80: =SUMIFS(Plans!$AD$2:$AD$4957,Plans!$A$2:$A$4957,A80,Plans!$D$2:$D$4957,C80) -> 680 | AC80: =SUMIFS(Plans!$AE$2:$AE$4957,Plans!$A$2:$A$4957,A80,Plans!$D$2:$D$4957,C80) -> 183 | AD80: =IFERROR((Y80+Z80)/SUM(Y80:AC80),"") -> 0.23695844 | AE80: ** suppressed (small numbers) | AF80: https://www.dominionnational.com/wps/wcm/connect/prodnws.dominionnational.com-30097/a166049e-f578-4b90-8fda-60f3bf81a047/PY2026+Transparency+in+Coverage+Policy.pdf?MOD=AJPERES&CVID=pstswnr
A81: Individual Dental | B81: MO | C81: 40519 | D81: Educators Health Plans Life, Accident, and Health, Inc | E81: No | F81: =COUNTIFS(Plans!$A$2:$A$4957,A81,Plans!$D$2:$D$4957,C81) -> 4 | G81: 2939 | H81: 4791 | I81: =IF(COUNT(G81:H81)=0,"",SUM(G81:H81)) -> 7730 | J81: 1392 | K81: 1911 | L81: =IF(COUNT(J81:K81)=0,"",SUM(J81:K81)) -> 3303 | M81: =IFERROR(L81/I81,"") -> 0.42729625 | N81: =IFERROR(J81/G81,"") -> 0.47363049 | O81: =IFERROR(K81/H81,"") -> 0.39887289 | P81: 243 | Q81: 445 | T81: =IFERROR(S81/R81,"") | U81: 0 | V81: 0 | W81: =IFERROR(V81/U81,"") | X81: =IFERROR((N(R81)+N(U81))/L81*1000,"") -> 0 | Y81: =SUMIFS(Plans!$AA$2:$AA$4957,Plans!$A$2:$A$4957,A81,Plans!$D$2:$D$4957,C81) -> 1441 | Z81: =SUMIFS(Plans!$AB$2:$AB$4957,Plans!$A$2:$A$4957,A81,Plans!$D$2:$D$4957,C81) -> 11 | AA81: =SUMIFS(Plans!$AC$2:$AC$4957,Plans!$A$2:$A$4957,A81,Plans!$D$2:$D$4957,C81) -> 307 | AB81: =SUMIFS(Plans!$AD$2:$AD$4957,Plans!$A$2:$A$4957,A81,Plans!$D$2:$D$4957,C81) -> 1542 | AC81: =SUMIFS(Plans!$AE$2:$AE$4957,Plans!$A$2:$A$4957,A81,Plans!$D$2:$D$4957,C81) -> 0 | AD81: =IFERROR((Y81+Z81)/SUM(Y81:AC81),"") -> 0.43986671 | AE81: ** suppressed (small numbers) | AF81: https://emihealth.com/Policies/MissouriDental
A82: Individual Dental | B82: MO | C82: 32753 | D82: Healthy Alliance Life Co(Anthem BCBS) | E82: No | F82: =COUNTIFS(Plans!$A$2:$A$4957,A82,Plans!$D$2:$D$4957,C82) -> 4 | G82: 307614 | H82: 3941746 | I82: =IF(COUNT(G82:H82)=0,"",SUM(G82:H82)) -> 4249360 | J82: 131639 | K82: 295802 | L82: =IF(COUNT(J82:K82)=0,"",SUM(J82:K82)) -> 427441 | M82: =IFERROR(L82/I82,"") -> 0.1005895 | N82: =IFERROR(J82/G82,"") -> 0.42793566 | O82: =IFERROR(K82/H82,"") -> 0.075043394 | P82: 33039 | Q82: 228345 | R82: 270 | S82: 98 | T82: =IFERROR(S82/R82,"") -> 0.36296296 | U82: 0 | V82: 0 | W82: =IFERROR(V82/U82,"") | X82: =IFERROR((N(R82)+N(U82))/L82*1000,"") -> 0.63166612 | Y82: =SUMIFS(Plans!$AA$2:$AA$4957,Plans!$A$2:$A$4957,A82,Plans!$D$2:$D$4957,C82) -> 0 | Z82: =SUMIFS(Plans!$AB$2:$AB$4957,Plans!$A$2:$A$4957,A82,Plans!$D$2:$D$4957,C82) -> 0 | AA82: =SUMIFS(Plans!$AC$2:$AC$4957,Plans!$A$2:$A$4957,A82,Plans!$D$2:$D$4957,C82) -> 13 | AB82: =SUMIFS(Plans!$AD$2:$AD$4957,Plans!$A$2:$A$4957,A82,Plans!$D$2:$D$4957,C82) -> 1463 | AC82: =SUMIFS(Plans!$AE$2:$AE$4957,Plans!$A$2:$A$4957,A82,Plans!$D$2:$D$4957,C82) -> 930 | AD82: =IFERROR((Y82+Z82)/SUM(Y82:AC82),"") -> 0 | AF82: https://www.anthem.com/ms/claims/home.html
A83: Individual Dental | B83: MO | C83: 30613 | D83: Humana Insurance Company | E83: No | F83: =COUNTIFS(Plans!$A$2:$A$4957,A83,Plans!$D$2:$D$4957,C83) -> 3 | G83: 898 | H83: 7393 | I83: =IF(COUNT(G83:H83)=0,"",SUM(G83:H83)) -> 8291 | J83: 281 | K83: 1856 | L83: =IF(COUNT(J83:K83)=0,"",SUM(J83:K83)) -> 2137 | M83: =IFERROR(L83/I83,"") -> 0.25774937 | N83: =IFERROR(J83/G83,"") -> 0.31291759 | O83: =IFERROR(K83/H83,"") -> 0.25104829 | P83: 0 | Q83: 13 | T83: =IFERROR(S83/R83,"") | U83: 0 | V83: 0 | W83: =IFERROR(V83/U83,"") | X83: =IFERROR((N(R83)+N(U83))/L83*1000,"") -> 0 | Y83: =SUMIFS(Plans!$AA$2:$AA$4957,Plans!$A$2:$A$4957,A83,Plans!$D$2:$D$4957,C83) -> 0 | Z83: =SUMIFS(Plans!$AB$2:$AB$4957,Plans!$A$2:$A$4957,A83,Plans!$D$2:$D$4957,C83) -> 29 | AA83: =SUMIFS(Plans!$AC$2:$AC$4957,Plans!$A$2:$A$4957,A83,Plans!$D$2:$D$4957,C83) -> 457 | AB83: =SUMIFS(Plans!$AD$2:$AD$4957,Plans!$A$2:$A$4957,A83,Plans!$D$2:$D$4957,C83) -> 1912 | AC83: =SUMIFS(Plans!$AE$2:$AE$4957,Plans!$A$2:$A$4957,A83,Plans!$D$2:$D$4957,C83) -> 254 | AD83: =IFERROR((Y83+Z83)/SUM(Y83:AC83),"") -> 0.010935143 | AE83: ** suppressed (small numbers) | AF83: https://www.humana.com/member/plain-language-policy
A84: Individual Dental | B84: MO | C84: 35853 | D84: Renaissance Life & Health Insurance Company of America | E84: No | F84: =COUNTIFS(Plans!$A$2:$A$4957,A84,Plans!$D$2:$D$4957,C84) -> 5 | G84: 1318 | H84: 6038 | I84: =IF(COUNT(G84:H84)=0,"",SUM(G84:H84)) -> 7356 | J84: 507 | K84: 1508 | L84: =IF(COUNT(J84:K84)=0,"",SUM(J84:K84)) -> 2015 | M84: =IFERROR(L84/I84,"") -> 0.27392605 | N84: =IFERROR(J84/G84,"") -> 0.38467375 | O84: =IFERROR(K84/H84,"") -> 0.24975157 | P84: 109 | Q84: 379 | R84: 0 | S84: 0 | T84: =IFERROR(S84/R84,"") | W84: =IFERROR(V84/U84,"") | X84: =IFERROR((N(R84)+N(U84))/L84*1000,"") -> 0 | Y84: =SUMIFS(Plans!$AA$2:$AA$4957,Plans!$A$2:$A$4957,A84,Plans!$D$2:$D$4957,C84) -> 198 | Z84: =SUMIFS(Plans!$AB$2:$AB$4957,Plans!$A$2:$A$4957,A84,Plans!$D$2:$D$4957,C84) -> 0 | AA84: =SUMIFS(Plans!$AC$2:$AC$4957,Plans!$A$2:$A$4957,A84,Plans!$D$2:$D$4957,C84) -> 801 | AB84: =SUMIFS(Plans!$AD$2:$AD$4957,Plans!$A$2:$A$4957,A84,Plans!$D$2:$D$4957,C84) -> 756 | AC84: =SUMIFS(Plans!$AE$2:$AE$4957,Plans!$A$2:$A$4957,A84,Plans!$D$2:$D$4957,C84) -> 940 | AD84: =IFERROR((Y84+Z84)/SUM(Y84:AC84),"") -> 0.073469388 | AE84: ** suppressed (small numbers) | AF84: https://renaissancebenefits.com/understanding-your-benefits/affordable-care-act-coverage/
A85: Individual Dental | B85: MO | C85: 82905 | D85: TRUASSURE INSURANCE COMPANY | E85: No | F85: =COUNTIFS(Plans!$A$2:$A$4957,A85,Plans!$D$2:$D$4957,C85) -> 3 | G85: 351 | H85: 1038 | I85: =IF(COUNT(G85:H85)=0,"",SUM(G85:H85)) -> 1389 | J85: 108 | K85: 317 | L85: =IF(COUNT(J85:K85)=0,"",SUM(J85:K85)) -> 425 | M85: =IFERROR(L85/I85,"") -> 0.30597552 | N85: =IFERROR(J85/G85,"") -> 0.30769231 | O85: =IFERROR(K85/H85,"") -> 0.30539499 | Q85: 21 | R85: 0 | S85: 0 | T85: =IFERROR(S85/R85,"") | U85: 0 | V85: 0 | W85: =IFERROR(V85/U85,"") | X85: =IFERROR((N(R85)+N(U85))/L85*1000,"") -> 0 | Y85: =SUMIFS(Plans!$AA$2:$AA$4957,Plans!$A$2:$A$4957,A85,Plans!$D$2:$D$4957,C85) -> 0 | Z85: =SUMIFS(Plans!$AB$2:$AB$4957,Plans!$A$2:$A$4957,A85,Plans!$D$2:$D$4957,C85) -> 0 | AA85: =SUMIFS(Plans!$AC$2:$AC$4957,Plans!$A$2:$A$4957,A85,Plans!$D$2:$D$4957,C85) -> 141 | AB85: =SUMIFS(Plans!$AD$2:$AD$4957,Plans!$A$2:$A$4957,A85,Plans!$D$2:$D$4957,C85) -> 21 | AC85: =SUMIFS(Plans!$AE$2:$AE$4957,Plans!$A$2:$A$4957,A85,Plans!$D$2:$D$4957,C85) -> 398 | AD85: =IFERROR((Y85+Z85)/SUM(Y85:AC85),"") -> 0 | AE85: ** suppressed (small numbers) | AF85: https://www.truassure.com/aca-plans
A86: Individual Dental | B86: MO | C86: 48786 | D86: The Guardian Life Insurance Company | E86: No | F86: =COUNTIFS(Plans!$A$2:$A$4957,A86,Plans!$D$2:$D$4957,C86) -> 3 | G86: 1220 | H86: 4191 | I86: =IF(COUNT(G86:H86)=0,"",SUM(G86:H86)) -> 5411 | J86: 593 | K86: 1673 | L86: =IF(COUNT(J86:K86)=0,"",SUM(J86:K86)) -> 2266 | M86: =IFERROR(L86/I86,"") -> 0.41877657 | N86: =IFERROR(J86/G86,"") -> 0.48606557 | O86: =IFERROR(K86/H86,"") -> 0.39918874 | P86: 0 | Q86: 0 | R86: 0 | S86: 0 | T86: =IFERROR(S86/R86,"") | U86: 0 | V86: 0 | W86: =IFERROR(V86/U86,"") | X86: =IFERROR((N(R86)+N(U86))/L86*1000,"") -> 0 | Y86: =SUMIFS(Plans!$AA$2:$AA$4957,Plans!$A$2:$A$4957,A86,Plans!$D$2:$D$4957,C86) -> 0 | Z86: =SUMIFS(Plans!$AB$2:$AB$4957,Plans!$A$2:$A$4957,A86,Plans!$D$2:$D$4957,C86) -> 0 | AA86: =SUMIFS(Plans!$AC$2:$AC$4957,Plans!$A$2:$A$4957,A86,Plans!$D$2:$D$4957,C86) -> 0 | AB86: =SUMIFS(Plans!$AD$2:$AD$4957,Plans!$A$2:$A$4957,A86,Plans!$D$2:$D$4957,C86) -> 0 | AC86: =SUMIFS(Plans!$AE$2:$AE$4957,Plans!$A$2:$A$4957,A86,Plans!$D$2:$D$4957,C86) -> 0 | AD86: =IFERROR((Y86+Z86)/SUM(Y86:AC86),"") | AF86: https://assets.ctfassets.net/jrhizl9l7csx/3AyKUByHZ9NSjeQMcwn8j8/53ce95a9baee7494befb828f7152268a/Exchange_Transparency_in_Coverage_8.11.25.pdf
A87: Individual Dental | B87: MS | C87: 11324 | D87: BEST Life and Health Insurance Company | E87: No | F87: =COUNTIFS(Plans!$A$2:$A$4957,A87,Plans!$D$2:$D$4957,C87) -> 4 | H87: 21 | I87: =IF(COUNT(G87:H87)=0,"",SUM(G87:H87)) -> 21 | K87: 13 | L87: =IF(COUNT(J87:K87)=0,"",SUM(J87:K87)) -> 13 | M87: =IFERROR(L87/I87,"") -> 0.61904762 | N87: =IFERROR(J87/G87,"") | O87: =IFERROR(K87/H87,"") -> 0.61904762 | P87: 0 | R87: 0 | S87: 0 | T87: =IFERROR(S87/R87,"") | V87: 0 | W87: =IFERROR(V87/U87,"") | X87: =IFERROR((N(R87)+N(U87))/L87*1000,"") -> 0 | Y87: =SUMIFS(Plans!$AA$2:$AA$4957,Plans!$A$2:$A$4957,A87,Plans!$D$2:$D$4957,C87) -> 0 | Z87: =SUMIFS(Plans!$AB$2:$AB$4957,Plans!$A$2:$A$4957,A87,Plans!$D$2:$D$4957,C87) -> 0 | AA87: =SUMIFS(Plans!$AC$2:$AC$4957,Plans!$A$2:$A$4957,A87,Plans!$D$2:$D$4957,C87) -> 0 | AB87: =SUMIFS(Plans!$AD$2:$AD$4957,Plans!$A$2:$A$4957,A87,Plans!$D$2:$D$4957,C87) -> 0 | AC87: =SUMIFS(Plans!$AE$2:$AE$4957,Plans!$A$2:$A$4957,A87,Plans!$D$2:$D$4957,C87) -> 0 | AD87: =IFERROR((Y87+Z87)/SUM(Y87:AC87),"") | AE87: ** suppressed (small numbers) | AF87: https://www.bestlife.com/ms/index.html
A88: Individual Dental | B88: MS | C88: 49374 | D88: Delta Dental Insurance Company | E88: No | F88: =COUNTIFS(Plans!$A$2:$A$4957,A88,Plans!$D$2:$D$4957,C88) -> 2 | G88: 1095 | H88: 7466 | I88: =IF(COUNT(G88:H88)=0,"",SUM(G88:H88)) -> 8561 | J88: 420 | K88: 1905 | L88: =IF(COUNT(J88:K88)=0,"",SUM(J88:K88)) -> 2325 | M88: =IFERROR(L88/I88,"") -> 0.27158042 | N88: =IFERROR(J88/G88,"") -> 0.38356164 | O88: =IFERROR(K88/H88,"") -> 0.25515671 | P88: 29 | Q88: 62 | S88: 0 | T88: =IFERROR(S88/R88,"") | U88: 0 | V88: 0 | W88: =IFERROR(V88/U88,"") | X88: =IFERROR((N(R88)+N(U88))/L88*1000,"") -> 0 | Y88: =SUMIFS(Plans!$AA$2:$AA$4957,Plans!$A$2:$A$4957,A88,Plans!$D$2:$D$4957,C88) -> 147 | Z88: =SUMIFS(Plans!$AB$2:$AB$4957,Plans!$A$2:$A$4957,A88,Plans!$D$2:$D$4957,C88) -> 0 | AA88: =SUMIFS(Plans!$AC$2:$AC$4957,Plans!$A$2:$A$4957,A88,Plans!$D$2:$D$4957,C88) -> 391 | AB88: =SUMIFS(Plans!$AD$2:$AD$4957,Plans!$A$2:$A$4957,A88,Plans!$D$2:$D$4957,C88) -> 833 | AC88: =SUMIFS(Plans!$AE$2:$AE$4957,Plans!$A$2:$A$4957,A88,Plans!$D$2:$D$4957,C88) -> 944 | AD88: =IFERROR((Y88+Z88)/SUM(Y88:AC88),"") -> 0.06349892 | AE88: ** suppressed (small numbers) | AF88: https://www1.deltadentalins.com/individuals-and-families/healthcare-reform-for-individuals/how-your-marketplace-plan-works.html
A89: Individual Dental | B89: MS | C89: 49327 | D89: Guardian Life Insurance Company of America | E89: No | F89: =COUNTIFS(Plans!$A$2:$A$4957,A89,Plans!$D$2:$D$4957,C89) -> 3 | G89: 1463 | H89: 3913 | I89: =IF(COUNT(G89:H89)=0,"",SUM(G89:H89)) -> 5376 | J89: 736 | K89: 1523 | L89: =IF(COUNT(J89:K89)=0,"",SUM(J89:K89)) -> 2259 | M89: =IFERROR(L89/I89,"") -> 0.42020089 | N89: =IFERROR(J89/G89,"") -> 0.50307587 | O89: =IFERROR(K89/H89,"") -> 0.38921544 | P89: 0 | Q89: 0 | R89: 0 | S89: 0 | T89: =IFERROR(S89/R89,"") | U89: 0 | V89: 0 | W89: =IFERROR(V89/U89,"") | X89: =IFERROR((N(R89)+N(U89))/L89*1000,"") -> 0 | Y89: =SUMIFS(Plans!$AA$2:$AA$4957,Plans!$A$2:$A$4957,A89,Plans!$D$2:$D$4957,C89) -> 0 | Z89: =SUMIFS(Plans!$AB$2:$AB$4957,Plans!$A$2:$A$4957,A89,Plans!$D$2:$D$4957,C89) -> 0 | AA89: =SUMIFS(Plans!$AC$2:$AC$4957,Plans!$A$2:$A$4957,A89,Plans!$D$2:$D$4957,C89) -> 0 | AB89: =SUMIFS(Plans!$AD$2:$AD$4957,Plans!$A$2:$A$4957,A89,Plans!$D$2:$D$4957,C89) -> 0 | AC89: =SUMIFS(Plans!$AE$2:$AE$4957,Plans!$A$2:$A$4957,A89,Plans!$D$2:$D$4957,C89) -> 0 | AD89: =IFERROR((Y89+Z89)/SUM(Y89:AC89),"") | AF89: https://assets.ctfassets.net/jrhizl9l7csx/3AyKUByHZ9NSjeQMcwn8j8/53ce95a9baee7494befb828f7152268a/Exchange_Transparency_in_Coverage_8.11.25.pdf
A90: Individual Dental | B90: MS | C90: 48963 | D90: Humana Insurance Company | E90: No | F90: =COUNTIFS(Plans!$A$2:$A$4957,A90,Plans!$D$2:$D$4957,C90) -> 2 | G90: 2611 | H90: 8788 | I90: =IF(COUNT(G90:H90)=0,"",SUM(G90:H90)) -> 11399 | J90: 799 | K90: 2593 | L90: =IF(COUNT(J90:K90)=0,"",SUM(J90:K90)) -> 3392 | M90: =IFERROR(L90/I90,"") -> 0.29756996 | N90: =IFERROR(J90/G90,"") -> 0.30601302 | O90: =IFERROR(K90/H90,"") -> 0.29506145 | Q90: 0 | S90: 0 | T90: =IFERROR(S90/R90,"") | U90: 0 | V90: 0 | W90: =IFERROR(V90/U90,"") | X90: =IFERROR((N(R90)+N(U90))/L90*1000,"") -> 0 | Y90: =SUMIFS(Plans!$AA$2:$AA$4957,Plans!$A$2:$A$4957,A90,Plans!$D$2:$D$4957,C90) -> 0 | Z90: =SUMIFS(Plans!$AB$2:$AB$4957,Plans!$A$2:$A$4957,A90,Plans!$D$2:$D$4957,C90) -> 67 | AA90: =SUMIFS(Plans!$AC$2:$AC$4957,Plans!$A$2:$A$4957,A90,Plans!$D$2:$D$4957,C90) -> 662 | AB90: =SUMIFS(Plans!$AD$2:$AD$4957,Plans!$A$2:$A$4957,A90,Plans!$D$2:$D$4957,C90) -> 2250 | AC90: =SUMIFS(Plans!$AE$2:$AE$4957,Plans!$A$2:$A$4957,A90,Plans!$D$2:$D$4957,C90) -> 1216 | AD90: =IFERROR((Y90+Z90)/SUM(Y90:AC90),"") -> 0.015971395 | AE90: ** suppressed (small numbers) | AF90: https://www.humana.com/member/plain-language-policy
A91: Individual Dental | B91: MS | C91: 84254 | D91: Renaissance Life & Health Insurance Company of America | E91: No | F91: =COUNTIFS(Plans!$A$2:$A$4957,A91,Plans!$D$2:$D$4957,C91) -> 3 | G91: 513 | H91: 1115 | I91: =IF(COUNT(G91:H91)=0,"",SUM(G91:H91)) -> 1628 | J91: 182 | K91: 285 | L91: =IF(COUNT(J91:K91)=0,"",SUM(J91:K91)) -> 467 | M91: =IFERROR(L91/I91,"") -> 0.28685504 | N91: =IFERROR(J91/G91,"") -> 0.35477583 | O91: =IFERROR(K91/H91,"") -> 0.25560538 | P91: 25 | Q91: 74 | R91: 0 | S91: 0 | T91: =IFERROR(S91/R91,"") | U91: 0 | V91: 0 | W91: =IFERROR(V91/U91,"") | X91: =IFERROR((N(R91)+N(U91))/L91*1000,"") -> 0 | Y91: =SUMIFS(Plans!$AA$2:$AA$4957,Plans!$A$2:$A$4957,A91,Plans!$D$2:$D$4957,C91) -> 45 | Z91: =SUMIFS(Plans!$AB$2:$AB$4957,Plans!$A$2:$A$4957,A91,Plans!$D$2:$D$4957,C91) -> 0 | AA91: =SUMIFS(Plans!$AC$2:$AC$4957,Plans!$A$2:$A$4957,A91,Plans!$D$2:$D$4957,C91) -> 264 | AB91: =SUMIFS(Plans!$AD$2:$AD$4957,Plans!$A$2:$A$4957,A91,Plans!$D$2:$D$4957,C91) -> 84 | AC91: =SUMIFS(Plans!$AE$2:$AE$4957,Plans!$A$2:$A$4957,A91,Plans!$D$2:$D$4957,C91) -> 214 | AD91: =IFERROR((Y91+Z91)/SUM(Y91:AC91),"") -> 0.074135091 | AF91: https://renaissancebenefits.com/understanding-your-benefits/affordable-care-act-coverage/
A92: Individual Dental | B92: MT | C92: 93895 | D92: BEST Life and Health Insurance Company | E92: No | F92: =COUNTIFS(Plans!$A$2:$A$4957,A92,Plans!$D$2:$D$4957,C92) -> 4 | G92: 148 | H92: 34 | I92: =IF(COUNT(G92:H92)=0,"",SUM(G92:H92)) -> 182 | J92: 69 | K92: 18 | L92: =IF(COUNT(J92:K92)=0,"",SUM(J92:K92)) -> 87 | M92: =IFERROR(L92/I92,"") -> 0.47802198 | N92: =IFERROR(J92/G92,"") -> 0.46621622 | O92: =IFERROR(K92/H92,"") -> 0.52941176 | Q92: 0 | R92: 0 | S92: 0 | T92: =IFERROR(S92/R92,"") | W92: =IFERROR(V92/U92,"") | X92: =IFERROR((N(R92)+N(U92))/L92*1000,"") -> 0 | Y92: =SUMIFS(Plans!$AA$2:$AA$4957,Plans!$A$2:$A$4957,A92,Plans!$D$2:$D$4957,C92) -> 0 | Z92: =SUMIFS(Plans!$AB$2:$AB$4957,Plans!$A$2:$A$4957,A92,Plans!$D$2:$D$4957,C92) -> 0 | AA92: =SUMIFS(Plans!$AC$2:$AC$4957,Plans!$A$2:$A$4957,A92,Plans!$D$2:$D$4957,C92) -> 0 | AB92: =SUMIFS(Plans!$AD$2:$AD$4957,Plans!$A$2:$A$4957,A92,Plans!$D$2:$D$4957,C92) -> 27 | AC92: =SUMIFS(Plans!$AE$2:$AE$4957,Plans!$A$2:$A$4957,A92,Plans!$D$2:$D$4957,C92) -> 0 | AD92: =IFERROR((Y92+Z92)/SUM(Y92:AC92),"") -> 0 | AE92: ** suppressed (small numbers) | AF92: https://www.bestlife.com/MT/index.html
A93: Individual Dental | B93: MT | C93: 30751 | D93: Blue Cross and Blue Shield of Montana | E93: No | F93: =COUNTIFS(Plans!$A$2:$A$4957,A93,Plans!$D$2:$D$4957,C93) -> 6 | G93: 80885 | H93: 1143888 | I93: =IF(COUNT(G93:H93)=0,"",SUM(G93:H93)) -> 1224773 | J93: 18878 | K93: 142689 | L93: =IF(COUNT(J93:K93)=0,"",SUM(J93:K93)) -> 161567 | M93: =IFERROR(L93/I93,"") -> 0.13191587 | N93: =IFERROR(J93/G93,"") -> 0.23339309 | O93: =IFERROR(K93/H93,"") -> 0.12474036 | P93: 2083 | Q93: 43421 | R93: 336 | S93: 104 | T93: =IFERROR(S93/R93,"") -> 0.30952381 | U93: 16 | W93: =IFERROR(V93/U93,"") -> 0 | X93: =IFERROR((N(R93)+N(U93))/L93*1000,"") -> 2.1786627 | Y93: =SUMIFS(Plans!$AA$2:$AA$4957,Plans!$A$2:$A$4957,A93,Plans!$D$2:$D$4957,C93) -> 659 | Z93: =SUMIFS(Plans!$AB$2:$AB$4957,Plans!$A$2:$A$4957,A93,Plans!$D$2:$D$4957,C93) -> 121 | AA93: =SUMIFS(Plans!$AC$2:$AC$4957,Plans!$A$2:$A$4957,A93,Plans!$D$2:$D$4957,C93) -> 59 | AB93: =SUMIFS(Plans!$AD$2:$AD$4957,Plans!$A$2:$A$4957,A93,Plans!$D$2:$D$4957,C93) -> 1466 | AC93: =SUMIFS(Plans!$AE$2:$AE$4957,Plans!$A$2:$A$4957,A93,Plans!$D$2:$D$4957,C93) -> 4852 | AD93: =IFERROR((Y93+Z93)/SUM(Y93:AC93),"") -> 0.10898421 | AE93: ** suppressed (small numbers) | AF93: https://www.bcbsmt.com/member/transparency-in-coverage
A94: Individual Dental | B94: MT | C94: 71788 | D94: Delta Dental Insurance Company | E94: No | F94: =COUNTIFS(Plans!$A$2:$A$4957,A94,Plans!$D$2:$D$4957,C94) -> 2 | G94: 4168 | H94: 11430 | I94: =IF(COUNT(G94:H94)=0,"",SUM(G94:H94)) -> 15598 | J94: 1199 | K94: 2673 | L94: =IF(COUNT(J94:K94)=0,"",SUM(J94:K94)) -> 3872 | M94: =IFERROR(L94/I94,"") -> 0.24823695 | N94: =IFERROR(J94/G94,"") -> 0.28766795 | O94: =IFERROR(K94/H94,"") -> 0.23385827 | P94: 56 | Q94: 60 | R94: 20 | T94: =IFERROR(S94/R94,"") -> 0 | U94: 0 | V94: 0 | W94: =IFERROR(V94/U94,"") | X94: =IFERROR((N(R94)+N(U94))/L94*1000,"") -> 5.1652893 | Y94: =SUMIFS(Plans!$AA$2:$AA$4957,Plans!$A$2:$A$4957,A94,Plans!$D$2:$D$4957,C94) -> 74 | Z94: =SUMIFS(Plans!$AB$2:$AB$4957,Plans!$A$2:$A$4957,A94,Plans!$D$2:$D$4957,C94) -> 0 | AA94: =SUMIFS(Plans!$AC$2:$AC$4957,Plans!$A$2:$A$4957,A94,Plans!$D$2:$D$4957,C94) -> 690 | AB94: =SUMIFS(Plans!$AD$2:$AD$4957,Plans!$A$2:$A$4957,A94,Plans!$D$2:$D$4957,C94) -> 1629 | AC94: =SUMIFS(Plans!$AE$2:$AE$4957,Plans!$A$2:$A$4957,A94,Plans!$D$2:$D$4957,C94) -> 1478 | AD94: =IFERROR((Y94+Z94)/SUM(Y94:AC94),"") -> 0.019116507 | AE94: ** suppressed (small numbers) | AF94: https://www1.deltadentalins.com/individuals-and-families/healthcare-reform-for-individuals/how-your-marketplace-plan-works.html
A95: Individual Dental | B95: MT | C95: 62818 | D95: Guardian Life Insurance Company of America | E95: No | F95: =COUNTIFS(Plans!$A$2:$A$4957,A95,Plans!$D$2:$D$4957,C95) -> 3 | G95: 194 | H95: 146 | I95: =IF(COUNT(G95:H95)=0,"",SUM(G95:H95)) -> 340 | J95: 69 | K95: 65 | L95: =IF(COUNT(J95:K95)=0,"",SUM(J95:K95)) -> 134 | M95: =IFERROR(L95/I95,"") -> 0.39411765 | N95: =IFERROR(J95/G95,"") -> 0.3556701 | O95: =IFERROR(K95/H95,"") -> 0.44520548 | P95: 0 | Q95: 0 | R95: 0 | S95: 0 | T95: =IFERROR(S95/R95,"") | U95: 0 | V95: 0 | W95: =IFERROR(V95/U95,"") | X95: =IFERROR((N(R95)+N(U95))/L95*1000,"") -> 0 | Y95: =SUMIFS(Plans!$AA$2:$AA$4957,Plans!$A$2:$A$4957,A95,Plans!$D$2:$D$4957,C95) -> 0 | Z95: =SUMIFS(Plans!$AB$2:$AB$4957,Plans!$A$2:$A$4957,A95,Plans!$D$2:$D$4957,C95) -> 0 | AA95: =SUMIFS(Plans!$AC$2:$AC$4957,Plans!$A$2:$A$4957,A95,Plans!$D$2:$D$4957,C95) -> 0 | AB95: =SUMIFS(Plans!$AD$2:$AD$4957,Plans!$A$2:$A$4957,A95,Plans!$D$2:$D$4957,C95) -> 0 | AC95: =SUMIFS(Plans!$AE$2:$AE$4957,Plans!$A$2:$A$4957,A95,Plans!$D$2:$D$4957,C95) -> 0 | AD95: =IFERROR((Y95+Z95)/SUM(Y95:AC95),"") | AF95: https://assets.ctfassets.net/jrhizl9l7csx/3AyKUByHZ9NSjeQMcwn8j8/53ce95a9baee7494befb828f7152268a/Exchange_Transparency_in_Coverage_8.11.25.pdf
A96: Individual Dental | B96: MT | C96: 23603 | D96: PacificSource Health Plans | E96: No | F96: =COUNTIFS(Plans!$A$2:$A$4957,A96,Plans!$D$2:$D$4957,C96) -> 3 | G96: 316 | H96: 41 | I96: =IF(COUNT(G96:H96)=0,"",SUM(G96:H96)) -> 357 | J96: 49 | L96: =IF(COUNT(J96:K96)=0,"",SUM(J96:K96)) -> 49 | M96: =IFERROR(L96/I96,"") -> 0.1372549 | N96: =IFERROR(J96/G96,"") -> 0.15506329 | O96: =IFERROR(K96/H96,"") -> 0 | Q96: 0 | R96: 39 | T96: =IFERROR(S96/R96,"") -> 0 | V96: 0 | W96: =IFERROR(V96/U96,"") | X96: =IFERROR((N(R96)+N(U96))/L96*1000,"") -> 795.91837 | Y96: =SUMIFS(Plans!$AA$2:$AA$4957,Plans!$A$2:$A$4957,A96,Plans!$D$2:$D$4957,C96) -> 52 | Z96: =SUMIFS(Plans!$AB$2:$AB$4957,Plans!$A$2:$A$4957,A96,Plans!$D$2:$D$4957,C96) -> 0 | AA96: =SUMIFS(Plans!$AC$2:$AC$4957,Plans!$A$2:$A$4957,A96,Plans!$D$2:$D$4957,C96) -> 170 | AB96: =SUMIFS(Plans!$AD$2:$AD$4957,Plans!$A$2:$A$4957,A96,Plans!$D$2:$D$4957,C96) -> 38 | AC96: =SUMIFS(Plans!$AE$2:$AE$4957,Plans!$A$2:$A$4957,A96,Plans!$D$2:$D$4957,C96) -> 18 | AD96: =IFERROR((Y96+Z96)/SUM(Y96:AC96),"") -> 0.18705036 | AE96: ** suppressed (small numbers) | AF96: https://pacificsource.com/yourplan/
A97: Individual Dental | B97: NC | C97: 94482 | D97: BEST Life and Health Insurance Company | E97: No | F97: =COUNTIFS(Plans!$A$2:$A$4957,A97,Plans!$D$2:$D$4957,C97) -> 4 | G97: 145 | H97: 142 | I97: =IF(COUNT(G97:H97)=0,"",SUM(G97:H97)) -> 287 | J97: 57 | K97: 61 | L97: =IF(COUNT(J97:K97)=0,"",SUM(J97:K97)) -> 118 | M97: =IFERROR(L97/I97,"") -> 0.41114983 | N97: =IFERROR(J97/G97,"") -> 0.39310345 | O97: =IFERROR(K97/H97,"") -> 0.42957746 | R97: 0 | S97: 0 | T97: =IFERROR(S97/R97,"") | W97: =IFERROR(V97/U97,"") | X97: =IFERROR((N(R97)+N(U97))/L97*1000,"") -> 0 | Y97: =SUMIFS(Plans!$AA$2:$AA$4957,Plans!$A$2:$A$4957,A97,Plans!$D$2:$D$4957,C97) -> 0 | Z97: =SUMIFS(Plans!$AB$2:$AB$4957,Plans!$A$2:$A$4957,A97,Plans!$D$2:$D$4957,C97) -> 0 | AA97: =SUMIFS(Plans!$AC$2:$AC$4957,Plans!$A$2:$A$4957,A97,Plans!$D$2:$D$4957,C97) -> 32 | AB97: =SUMIFS(Plans!$AD$2:$AD$4957,Plans!$A$2:$A$4957,A97,Plans!$D$2:$D$4957,C97) -> 60 | AC97: =SUMIFS(Plans!$AE$2:$AE$4957,Plans!$A$2:$A$4957,A97,Plans!$D$2:$D$4957,C97) -> 13 | AD97: =IFERROR((Y97+Z97)/SUM(Y97:AC97),"") -> 0 | AE97: ** suppressed (small numbers) | AF97: https://www.bestlife.com/NC/index.html
A98: Individual Dental | B98: NC | C98: 56891 | D98: Delta Dental of North Carolina | E98: No | F98: =COUNTIFS(Plans!$A$2:$A$4957,A98,Plans!$D$2:$D$4957,C98) -> 3 | G98: 21371 | H98: 140253 | I98: =IF(COUNT(G98:H98)=0,"",SUM(G98:H98)) -> 161624 | J98: 7501 | K98: 27837 | L98: =IF(COUNT(J98:K98)=0,"",SUM(J98:K98)) -> 35338 | M98: =IFERROR(L98/I98,"") -> 0.21864327 | N98: =IFERROR(J98/G98,"") -> 0.35098966 | O98: =IFERROR(K98/H98,"") -> 0.19847704 | P98: 1758 | Q98: 7740 | R98: 0 | S98: 0 | T98: =IFERROR(S98/R98,"") | U98: 0 | V98: 0 | W98: =IFERROR(V98/U98,"") | X98: =IFERROR((N(R98)+N(U98))/L98*1000,"") -> 0 | Y98: =SUMIFS(Plans!$AA$2:$AA$4957,Plans!$A$2:$A$4957,A98,Plans!$D$2:$D$4957,C98) -> 4937 | Z98: =SUMIFS(Plans!$AB$2:$AB$4957,Plans!$A$2:$A$4957,A98,Plans!$D$2:$D$4957,C98) -> 38 | AA98: =SUMIFS(Plans!$AC$2:$AC$4957,Plans!$A$2:$A$4957,A98,Plans!$D$2:$D$4957,C98) -> 14386 | AB98: =SUMIFS(Plans!$AD$2:$AD$4957,Plans!$A$2:$A$4957,A98,Plans!$D$2:$D$4957,C98) -> 13289 | AC98: =SUMIFS(Plans!$AE$2:$AE$4957,Plans!$A$2:$A$4957,A98,Plans!$D$2:$D$4957,C98) -> 17622 | AD98: =IFERROR((Y98+Z98)/SUM(Y98:AC98),"") -> 0.098961649 | AF98: https://deltadentalnc.com/members/understand-my-benefits/affordable-care-act-coverage
A99: Individual Dental | B99: NC | C99: 66759 | D99: Dominion Dental Services, Inc. | E99: No | F99: =COUNTIFS(Plans!$A$2:$A$4957,A99,Plans!$D$2:$D$4957,C99) -> 6 | G99: 3340 | H99: 5906 | I99: =IF(COUNT(G99:H99)=0,"",SUM(G99:H99)) -> 9246 | J99: 1076 | K99: 1206 | L99: =IF(COUNT(J99:K99)=0,"",SUM(J99:K99)) -> 2282 | M99: =IFERROR(L99/I99,"") -> 0.24680943 | N99: =IFERROR(J99/G99,"") -> 0.32215569 | O99: =IFERROR(K99/H99,"") -> 0.20419912 | P99: 49 | Q99: 110 | R99: 0 | S99: 0 | T99: =IFERROR(S99/R99,"") | U99: 0 | V99: 0 | W99: =IFERROR(V99/U99,"") | X99: =IFERROR((N(R99)+N(U99))/L99*1000,"") -> 0 | Y99: =SUMIFS(Plans!$AA$2:$AA$4957,Plans!$A$2:$A$4957,A99,Plans!$D$2:$D$4957,C99) -> 445 | Z99: =SUMIFS(Plans!$AB$2:$AB$4957,Plans!$A$2:$A$4957,A99,Plans!$D$2:$D$4957,C99) -> 23 | AA99: =SUMIFS(Plans!$AC$2:$AC$4957,Plans!$A$2:$A$4957,A99,Plans!$D$2:$D$4957,C99) -> 42 | AB99: =SUMIFS(Plans!$AD$2:$AD$4957,Plans!$A$2:$A$4957,A99,Plans!$D$2:$D$4957,C99) -> 1353 | AC99: =SUMIFS(Plans!$AE$2:$AE$4957,Plans!$A$2:$A$4957,A99,Plans!$D$2:$D$4957,C99) -> 388 | AD99: =IFERROR((Y99+Z99)/SUM(Y99:AC99),"") -> 0.2079076 | AF99: https://www.dominionnational.com/wps/wcm/connect/prodnws.dominionnational.com-30097/74db946e-43a9-454d-a02b-27859938f5e8/PY2023+Transparency+in+Coverage+Policy_Final.pdf?MOD=AJPERES&CONVERT_TO=url&CACHEID=ROOTWORKSPACE.Z18_4G00HA41L84V20QEHJUBR820G1-74db946e-43a9-454d-a02b-27859938f5e8-ow5N870
A100: Individual Dental | B100: NC | C100: 93383 | D100: Educators Health Plans Life, Accident, and Health, Inc | E100: No | F100: =COUNTIFS(Plans!$A$2:$A$4957,A100,Plans!$D$2:$D$4957,C100) -> 4 | G100: 12863 | H100: 11513 | I100: =IF(COUNT(G100:H100)=0,"",SUM(G100:H100)) -> 24376 | J100: 6512 | K100: 3662 | L100: =IF(COUNT(J100:K100)=0,"",SUM(J100:K100)) -> 10174 | M100: =IFERROR(L100/I100,"") -> 0.41737775 | N100: =IFERROR(J100/G100,"") -> 0.50625826 | O100: =IFERROR(K100/H100,"") -> 0.31807522 | P100: 1245 | Q100: 977 | T100: =IFERROR(S100/R100,"") | U100: 0 | V100: 0 | W100: =IFERROR(V100/U100,"") | X100: =IFERROR((N(R100)+N(U100))/L100*1000,"") -> 0 | Y100: =SUMIFS(Plans!$AA$2:$AA$4957,Plans!$A$2:$A$4957,A100,Plans!$D$2:$D$4957,C100) -> 5913 | Z100: =SUMIFS(Plans!$AB$2:$AB$4957,Plans!$A$2:$A$4957,A100,Plans!$D$2:$D$4957,C100) -> 26 | AA100: =SUMIFS(Plans!$AC$2:$AC$4957,Plans!$A$2:$A$4957,A100,Plans!$D$2:$D$4957,C100) -> 653 | AB100: =SUMIFS(Plans!$AD$2:$AD$4957,Plans!$A$2:$A$4957,A100,Plans!$D$2:$D$4957,C100) -> 3581 | AC100: =SUMIFS(Plans!$AE$2:$AE$4957,Plans!$A$2:$A$4957,A100,Plans!$D$2:$D$4957,C100) -> 0 | AD100: =IFERROR((Y100+Z100)/SUM(Y100:AC100),"") -> 0.58380026 | AE100: ** suppressed (small numbers) | AF100: https://emihealth.com/Policies/NorthCarolinaDental
...

Sheet Plans
A1: Market | B1: State | C1: Exchange Type | D1: Issuer ID | E1: Issuer Name | F1: Plan ID | G1: Plan Type | H1: Metal Level | I1: Claims Received OON | J1: Claims Received INN | K1: Claims Denied OON | L1: Claims Denied INN | M1: Claims Resubmitted OON | N1: Claims Resubmitted INN | O1: OON Denial Rate | P1: INN Denial Rate | Q1: Administrative [High] | R1: Not medically necessary (medical) [Medium-High] | S1: Not medically necessary (behavioral health) [Medium-High] | T1: Referral required [Medium] | U1: Member not covered [Medium] | V1: Out-of-network [Medium] | W1: Benefit limit reached [Low] | X1: Service excluded [Low] | Y1: Experimental / cosmetic [Low] | Z1: Other / unspecified [Unknown] | AA1: Tier 1 High | AB1: Tier 2 Medium-High | AC1: Tier 3 Medium | AD1: Tier 4 Low | AE1: Tier 5 Unknown | AF1: Denials With Reason (Total) | AG1: % Fixable (High + Med-High) | AH1: Avg Monthly Enrollment
A2: Individual Medical | B2: FL | C2: FFE | D2: 30252 | E2: Health Options, Inc. | F2: 30252FL0070070 | G2: HMO | H2: Silver | I2: 91724 | J2: 8195606 | K2: 12183 | L2: 2028395 | M2: 11161 | N2: 505015 | O2: =IFERROR(K2/I2,"") -> 0.13282238 | P2: =IFERROR(L2/J2,"") -> 0.24749787 | Q2: 1161084 | R2: 402 | S2: 0 | T2: 9868 | U2: 159 | V2: 12183 | W2: 21177 | X2: 12758 | Y2: 957 | Z2: 821990 | AA2: =IF(COUNT(Q2:Z2)=0,"",SUM(Q2:Q2)) -> 1161084 | AB2: =IF(COUNT(Q2:Z2)=0,"",SUM(R2:S2)) -> 402 | AC2: =IF(COUNT(Q2:Z2)=0,"",SUM(T2:V2)) -> 22210 | AD2: =IF(COUNT(Q2:Z2)=0,"",SUM(W2:Y2)) -> 34892 | AE2: =IF(COUNT(Q2:Z2)=0,"",SUM(Z2:Z2)) -> 821990 | AF2: =IF(COUNT(Q2:Z2)=0,"",SUM(Q2:Z2)) -> 2040578 | AG2: =IFERROR((AA2+AB2)/AF2,"") -> 0.56919461 | AH2: 20251
A3: Individual Medical | B3: FL | C3: FFE | D3: 30252 | E3: Health Options, Inc. | F3: 30252FL0070035 | G3: HMO | H3: Silver | I3: 47680 | J3: 7067928 | K3: 12456 | L3: 1811037 | M3: 5674 | N3: 403528 | O3: =IFERROR(K3/I3,"") -> 0.26124161 | P3: =IFERROR(L3/J3,"") -> 0.25623309 | Q3: 914347 | R3: 592 | T3: 7568 | U3: 155 | V3: 12456 | W3: 17256 | X3: 6003 | Y3: 973 | Z3: 864140 | AA3: =IF(COUNT(Q3:Z3)=0,"",SUM(Q3:Q3)) -> 914347 | AB3: =IF(COUNT(Q3:Z3)=0,"",SUM(R3:S3)) -> 592 | AC3: =IF(COUNT(Q3:Z3)=0,"",SUM(T3:V3)) -> 20179 | AD3: =IF(COUNT(Q3:Z3)=0,"",SUM(W3:Y3)) -> 24232 | AE3: =IF(COUNT(Q3:Z3)=0,"",SUM(Z3:Z3)) -> 864140 | AF3: =IF(COUNT(Q3:Z3)=0,"",SUM(Q3:Z3)) -> 1823490 | AG3: =IFERROR((AA3+AB3)/AF3,"") -> 0.50175159 | AH3: 10894
A4: Individual Medical | B4: FL | C4: FFE | D4: 16842 | E4: Blue Cross and Blue Shield of Florida | F4: 16842FL0120072 | G4: EPO | H4: Silver | I4: 259497 | J4: 7386117 | K4: 64492 | L4: 1501632 | M4: 29128 | N4: 406751 | O4: =IFERROR(K4/I4,"") -> 0.24852696 | P4: =IFERROR(L4/J4,"") -> 0.20330466 | Q4: 751239 | R4: 689 | T4: 2190 | U4: 31 | V4: 64492 | W4: 14284 | X4: 9604 | Y4: 1110 | Z4: 722479 | AA4: =IF(COUNT(Q4:Z4)=0,"",SUM(Q4:Q4)) -> 751239 | AB4: =IF(COUNT(Q4:Z4)=0,"",SUM(R4:S4)) -> 689 | AC4: =IF(COUNT(Q4:Z4)=0,"",SUM(T4:V4)) -> 66713 | AD4: =IF(COUNT(Q4:Z4)=0,"",SUM(W4:Y4)) -> 24998 | AE4: =IF(COUNT(Q4:Z4)=0,"",SUM(Z4:Z4)) -> 722479 | AF4: =IF(COUNT(Q4:Z4)=0,"",SUM(Q4:Z4)) -> 1566118 | AG4: =IFERROR((AA4+AB4)/AF4,"") -> 0.48012219 | AH4: 10210
A5: Individual Medical | B5: FL | C5: FFE | D5: 16842 | E5: Blue Cross and Blue Shield of Florida | F5: 16842FL0120091 | G5: EPO | H5: Bronze | I5: 177297 | J5: 3408347 | K5: 49416 | L5: 669161 | M5: 16281 | N5: 188277 | O5: =IFERROR(K5/I5,"") -> 0.27871876 | P5: =IFERROR(L5/J5,"") -> 0.19633007 | Q5: 359318 | R5: 301 | T5: 715 | U5: 19 | V5: 49416 | W5: 5964 | X5: 5367 | Y5: 584 | Z5: 296886 | AA5: =IF(COUNT(Q5:Z5)=0,"",SUM(Q5:Q5)) -> 359318 | AB5: =IF(COUNT(Q5:Z5)=0,"",SUM(R5:S5)) -> 301 | AC5: =IF(COUNT(Q5:Z5)=0,"",SUM(T5:V5)) -> 50150 | AD5: =IF(COUNT(Q5:Z5)=0,"",SUM(W5:Y5)) -> 11915 | AE5: =IF(COUNT(Q5:Z5)=0,"",SUM(Z5:Z5)) -> 296886 | AF5: =IF(COUNT(Q5:Z5)=0,"",SUM(Q5:Z5)) -> 718570 | AG5: =IFERROR((AA5+AB5)/AF5,"") -> 0.50046481 | AH5: 8068
A6: Individual Medical | B6: FL | C6: FFE | D6: 30252 | E6: Health Options, Inc. | F6: 30252FL0070078 | G6: HMO | H6: Silver | I6: 14730 | J6: 1887564 | K6: 1600 | L6: 552596 | M6: 2101 | N6: 118273 | O6: =IFERROR(K6/I6,"") -> 0.10862186 | P6: =IFERROR(L6/J6,"") -> 0.29275617 | Q6: 357338 | R6: 99 | S6: 0 | T6: 1652 | U6: 17 | V6: 1600 | W6: 2170 | X6: 2987 | Y6: 165 | Z6: 188168 | AA6: =IF(COUNT(Q6:Z6)=0,"",SUM(Q6:Q6)) -> 357338 | AB6: =IF(COUNT(Q6:Z6)=0,"",SUM(R6:S6)) -> 99 | AC6: =IF(COUNT(Q6:Z6)=0,"",SUM(T6:V6)) -> 3269 | AD6: =IF(COUNT(Q6:Z6)=0,"",SUM(W6:Y6)) -> 5322 | AE6: =IF(COUNT(Q6:Z6)=0,"",SUM(Z6:Z6)) -> 188168 | AF6: =IF(COUNT(Q6:Z6)=0,"",SUM(Q6:Z6)) -> 554196 | AG6: =IFERROR((AA6+AB6)/AF6,"") -> 0.64496496 | AH6: 4215
A7: Individual Medical | B7: FL | C7: FFE | D7: 30252 | E7: Health Options, Inc. | F7: 30252FL0070022 | G7: HMO | H7: Silver | I7: 7572 | J7: 1665790 | K7: 1329 | L7: 473192 | M7: 1102 | N7: 104599 | O7: =IFERROR(K7/I7,"") -> 0.17551506 | P7: =IFERROR(L7/J7,"") -> 0.28406462 | Q7: 291359 | R7: 136 | S7: 0 | T7: 1677 | V7: 1329 | W7: 2503 | X7: 2009 | Y7: 234 | Z7: 175268 | AA7: =IF(COUNT(Q7:Z7)=0,"",SUM(Q7:Q7)) -> 291359 | AB7: =IF(COUNT(Q7:Z7)=0,"",SUM(R7:S7)) -> 136 | AC7: =IF(COUNT(Q7:Z7)=0,"",SUM(T7:V7)) -> 3006 | AD7: =IF(COUNT(Q7:Z7)=0,"",SUM(W7:Y7)) -> 4746 | AE7: =IF(COUNT(Q7:Z7)=0,"",SUM(Z7:Z7)) -> 175268 | AF7: =IF(COUNT(Q7:Z7)=0,"",SUM(Q7:Z7)) -> 474515 | AG7: =IFERROR((AA7+AB7)/AF7,"") -> 0.61430092 | AH7: 2877
A8: Individual Medical | B8: FL | C8: FFE | D8: 30252 | E8: Health Options, Inc. | F8: 30252FL0070039 | G8: HMO | H8: Bronze | I8: 55615 | J8: 2383107 | K8: 4949 | L8: 566025 | M8: 7288 | N8: 127289 | O8: =IFERROR(K8/I8,"") -> 0.088986784 | P8: =IFERROR(L8/J8,"") -> 0.23751556 | Q8: 256798 | R8: 139 | S8: 0 | T8: 2554 | U8: 67 | V8: 4949 | W8: 2467 | X8: 2431 | Y8: 187 | Z8: 301382 | AA8: =IF(COUNT(Q8:Z8)=0,"",SUM(Q8:Q8)) -> 256798 | AB8: =IF(COUNT(Q8:Z8)=0,"",SUM(R8:S8)) -> 139 | AC8: =IF(COUNT(Q8:Z8)=0,"",SUM(T8:V8)) -> 7570 | AD8: =IF(COUNT(Q8:Z8)=0,"",SUM(W8:Y8)) -> 5085 | AE8: =IF(COUNT(Q8:Z8)=0,"",SUM(Z8:Z8)) -> 301382 | AF8: =IF(COUNT(Q8:Z8)=0,"",SUM(Q8:Z8)) -> 570974 | AG8: =IFERROR((AA8+AB8)/AF8,"") -> 0.44999772 | AH8: 8328
A9: Individual Medical | B9: AL | C9: FFE | D9: 46944 | E9: Blue Cross and Blue Shield of Alabama | F9: 46944AL0660001 | G9: PPO | H9: Silver | I9: 71386 | J9: 4077042 | K9: 66070 | L9: 791158 | M9: 15379 | N9: 320721 | O9: =IFERROR(K9/I9,"") -> 0.92553162 | P9: =IFERROR(L9/J9,"") -> 0.19405196 | Q9: 241344 | R9: 11874 | S9: 323 | T9: 104490 | U9: 202288 | V9: 79104 | W9: 153556 | X9: 251678 | Y9: 52 | Z9: 947 | AA9: =IF(COUNT(Q9:Z9)=0,"",SUM(Q9:Q9)) -> 241344 | AB9: =IF(COUNT(Q9:Z9)=0,"",SUM(R9:S9)) -> 12197 | AC9: =IF(COUNT(Q9:Z9)=0,"",SUM(T9:V9)) -> 385882 | AD9: =IF(COUNT(Q9:Z9)=0,"",SUM(W9:Y9)) -> 405286 | AE9: =IF(COUNT(Q9:Z9)=0,"",SUM(Z9:Z9)) -> 947 | AF9: =IF(COUNT(Q9:Z9)=0,"",SUM(Q9:Z9)) -> 1045656 | AG9: =IFERROR((AA9+AB9)/AF9,"") -> 0.24247076 | AH9: 6560
A10: Individual Medical | B10: MS | C10: FFE | D10: 90714 | E10: Ambetter of Magnolia Inc. | F10: 90714MS0010064 | G10: HMO | H10: Silver | I10: 410097 | J10: 5304017 | K10: 94157 | L10: 819581 | M10: 17512 | N10: 546609 | O10: =IFERROR(K10/I10,"") -> 0.2295969 | P10: =IFERROR(L10/J10,"") -> 0.15452081 | Q10: 239725 | R10: 108361 | S10: 2496 | T10: 131806 | U10: 110754 | V10: 93229 | W10: 85378 | X10: 171887 | Y10: 0 | Z10: 146349 | AA10: =IF(COUNT(Q10:Z10)=0,"",SUM(Q10:Q10)) -> 239725 | AB10: =IF(COUNT(Q10:Z10)=0,"",SUM(R10:S10)) -> 110857 | AC10: =IF(COUNT(Q10:Z10)=0,"",SUM(T10:V10)) -> 335789 | AD10: =IF(COUNT(Q10:Z10)=0,"",SUM(W10:Y10)) -> 257265 | AE10: =IF(COUNT(Q10:Z10)=0,"",SUM(Z10:Z10)) -> 146349 | AF10: =IF(COUNT(Q10:Z10)=0,"",SUM(Q10:Z10)) -> 1089985 | AG10: =IFERROR((AA10+AB10)/AF10,"") -> 0.32163929 | AH10: 8635
A11: Individual Medical | B11: FL | C11: FFE | D11: 16842 | E11: Blue Cross and Blue Shield of Florida | F11: 16842FL0120068 | G11: EPO | H11: Bronze | I11: 78969 | J11: 2035650 | K11: 24229 | L11: 444970 | M11: 7188 | N11: 106988 | O11: =IFERROR(K11/I11,"") -> 0.3068166 | P11: =IFERROR(L11/J11,"") -> 0.21858866 | Q11: 238110 | R11: 185 | T11: 348 | U11: 12 | V11: 24229 | W11: 2996 | X11: 2182 | Y11: 220 | Z11: 200916 | AA11: =IF(COUNT(Q11:Z11)=0,"",SUM(Q11:Q11)) -> 238110 | AB11: =IF(COUNT(Q11:Z11)=0,"",SUM(R11:S11)) -> 185 | AC11: =IF(COUNT(Q11:Z11)=0,"",SUM(T11:V11)) -> 24589 | AD11: =IF(COUNT(Q11:Z11)=0,"",SUM(W11:Y11)) -> 5398 | AE11: =IF(COUNT(Q11:Z11)=0,"",SUM(Z11:Z11)) -> 200916 | AF11: =IF(COUNT(Q11:Z11)=0,"",SUM(Q11:Z11)) -> 469198 | AG11: =IFERROR((AA11+AB11)/AF11,"") -> 0.50787727 | AH11: 4478
A12: Individual Medical | B12: FL | C12: FFE | D12: 30252 | E12: Health Options, Inc. | F12: 30252FL0070031 | G12: HMO | H12: Bronze | I12: 15994 | J12: 1774838 | K12: 2645 | L12: 453690 | M12: 1933 | N12: 105717 | O12: =IFERROR(K12/I12,"") -> 0.16537452 | P12: =IFERROR(L12/J12,"") -> 0.25562333 | Q12: 236748 | R12: 125 | S12: 0 | T12: 1596 | U12: 20 | V12: 2645 | W12: 2940 | X12: 1149 | Y12: 229 | Z12: 210883 | AA12: =IF(COUNT(Q12:Z12)=0,"",SUM(Q12:Q12)) -> 236748 | AB12: =IF(COUNT(Q12:Z12)=0,"",SUM(R12:S12)) -> 125 | AC12: =IF(COUNT(Q12:Z12)=0,"",SUM(T12:V12)) -> 4261 | AD12: =IF(COUNT(Q12:Z12)=0,"",SUM(W12:Y12)) -> 4318 | AE12: =IF(COUNT(Q12:Z12)=0,"",SUM(Z12:Z12)) -> 210883 | AF12: =IF(COUNT(Q12:Z12)=0,"",SUM(Q12:Z12)) -> 456335 | AG12: =IFERROR((AA12+AB12)/AF12,"") -> 0.51907699 | AH12: 4796
A13: Individual Medical | B13: FL | C13: FFE | D13: 30252 | E13: Health Options, Inc. | F13: 30252FL0070001 | G13: HMO | H13: Bronze | I13: 25738 | J13: 1774049 | K13: 3427 | L13: 468123 | M13: 3673 | N13: 94032 | O13: =IFERROR(K13/I13,"") -> 0.13314943 | P13: =IFERROR(L13/J13,"") -> 0.26387264 | Q13: 215396 | R13: 203 | T13: 1625 | U13: 184 | V13: 3427 | W13: 2577 | X13: 1912 | Y13: 225 | Z13: 245999 | AA13: =IF(COUNT(Q13:Z13)=0,"",SUM(Q13:Q13)) -> 215396 | AB13: =IF(COUNT(Q13:Z13)=0,"",SUM(R13:S13)) -> 203 | AC13: =IF(COUNT(Q13:Z13)=0,"",SUM(T13:V13)) -> 5236 | AD13: =IF(COUNT(Q13:Z13)=0,"",SUM(W13:Y13)) -> 4714 | AE13: =IF(COUNT(Q13:Z13)=0,"",SUM(Z13:Z13)) -> 245999 | AF13: =IF(COUNT(Q13:Z13)=0,"",SUM(Q13:Z13)) -> 471548 | AG13: =IFERROR((AA13+AB13)/AF13,"") -> 0.45721538 | AH13: 4844
A14: Individual Medical | B14: AL | C14: FFE | D14: 69461 | E14: UnitedHealthcare Insurance Company | F14: 69461AL0110014 | G14: EPO | H14: Silver | I14: 936763 | J14: 3621722 | K14: 517451 | L14: 629087 | M14: 81913 | N14: 409359 | O14: =IFERROR(K14/I14,"") -> 0.55238198 | P14: =IFERROR(L14/J14,"") -> 0.17369831 | Q14: 212204 | R14: 98 | S14: 67 | T14: 151593 | U14: 59035 | V14: 592801 | W14: 0 | X14: 140408 | Y14: 11 | Z14: 328499 | AA14: =IF(COUNT(Q14:Z14)=0,"",SUM(Q14:Q14)) -> 212204 | AB14: =IF(COUNT(Q14:Z14)=0,"",SUM(R14:S14)) -> 165 | AC14: =IF(COUNT(Q14:Z14)=0,"",SUM(T14:V14)) -> 803429 | AD14: =IF(COUNT(Q14:Z14)=0,"",SUM(W14:Y14)) -> 140419 | AE14: =IF(COUNT(Q14:Z14)=0,"",SUM(Z14:Z14)) -> 328499 | AF14: =IF(COUNT(Q14:Z14)=0,"",SUM(Q14:Z14)) -> 1484716 | AG14: =IFERROR((AA14+AB14)/AF14,"") -> 0.14303678 | AH14: 9644
A15: Individual Medical | B15: FL | C15: FFE | D15: 30252 | E15: Health Options, Inc. | F15: 30252FL0070076 | G15: HMO | H15: Silver | I15: 14413 | J15: 1649470 | K15: 3128 | L15: 421177 | M15: 1674 | N15: 88728 | O15: =IFERROR(K15/I15,"") -> 0.2170263 | P15: =IFERROR(L15/J15,"") -> 0.25534081 | Q15: 210859 | R15: 107 | S15: 0 | T15: 1500 | U15: 71 | V15: 3128 | W15: 2262 | X15: 1410 | Y15: 279 | Z15: 204689 | AA15: =IF(COUNT(Q15:Z15)=0,"",SUM(Q15:Q15)) -> 210859 | AB15: =IF(COUNT(Q15:Z15)=0,"",SUM(R15:S15)) -> 107 | AC15: =IF(COUNT(Q15:Z15)=0,"",SUM(T15:V15)) -> 4699 | AD15: =IF(COUNT(Q15:Z15)=0,"",SUM(W15:Y15)) -> 3951 | AE15: =IF(COUNT(Q15:Z15)=0,"",SUM(Z15:Z15)) -> 204689 | AF15: =IF(COUNT(Q15:Z15)=0,"",SUM(Q15:Z15)) -> 424305 | AG15: =IFERROR((AA15+AB15)/AF15,"") -> 0.49720366 | AH15: 2549
A16: Individual Medical | B16: TX | C16: FFE | D16: 29418 | E16: Celtic Insurance Company | F16: 29418TX0140108 | G16: EPO | H16: Silver | I16: 523014 | J16: 4856301 | K16: 78457 | L16: 754152 | M16: 17916 | N16: 517018 | O16: =IFERROR(K16/I16,"") -> 0.15000937 | P16: =IFERROR(L16/J16,"") -> 0.1552935 | Q16: 186602 | R16: 137928 | S16: 3003 | T16: 147807 | U16: 107036 | V16: 82453 | W16: 76268 | X16: 173005 | Y16: 72 | Z16: 130211 | AA16: =IF(COUNT(Q16:Z16)=0,"",SUM(Q16:Q16)) -> 186602 | AB16: =IF(COUNT(Q16:Z16)=0,"",SUM(R16:S16)) -> 140931 | AC16: =IF(COUNT(Q16:Z16)=0,"",SUM(T16:V16)) -> 337296 | AD16: =IF(COUNT(Q16:Z16)=0,"",SUM(W16:Y16)) -> 249345 | AE16: =IF(COUNT(Q16:Z16)=0,"",SUM(Z16:Z16)) -> 130211 | AF16: =IF(COUNT(Q16:Z16)=0,"",SUM(Q16:Z16)) -> 1044385 | AG16: =IFERROR((AA16+AB16)/AF16,"") -> 0.31361327 | AH16: 9374
A17: Individual Medical | B17: AR | C17: SBE-FP | D17: 75293 | E17: USAble Mutual Insurance Company | F17: 75293AR1200004 | G17: PPO | H17: Silver | I17: 1251 | J17: 2563697 | K17: 484 | L17: 382829 | N17: 133261 | O17: =IFERROR(K17/I17,"") -> 0.38689049 | P17: =IFERROR(L17/J17,"") -> 0.14932693 | Q17: 180119 | R17: 18 | S17: 12 | T17: 51906 | U17: 34360 | V17: 486 | W17: 305438 | X17: 107 | Z17: 12676 | AA17: =IF(COUNT(Q17:Z17)=0,"",SUM(Q17:Q17)) -> 180119 | AB17: =IF(COUNT(Q17:Z17)=0,"",SUM(R17:S17)) -> 30 | AC17: =IF(COUNT(Q17:Z17)=0,"",SUM(T17:V17)) -> 86752 | AD17: =IF(COUNT(Q17:Z17)=0,"",SUM(W17:Y17)) -> 305545 | AE17: =IF(COUNT(Q17:Z17)=0,"",SUM(Z17:Z17)) -> 12676 | AF17: =IF(COUNT(Q17:Z17)=0,"",SUM(Q17:Z17)) -> 585122 | AG17: =IFERROR((AA17+AB17)/AF17,"") -> 0.3078828 | AH17: 133
A18: Individual Medical | B18: TX | C18: FFE | D18: 29418 | E18: Celtic Insurance Company | F18: 29418TX0140100 | G18: EPO | H18: Silver | I18: 257480 | J18: 3598715 | K18: 35082 | L18: 559054 | M18: 10850 | N18: 434007 | O18: =IFERROR(K18/I18,"") -> 0.13625136 | P18: =IFERROR(L18/J18,"") -> 0.15534823 | Q18: 140521 | R18: 102403 | S18: 2071 | T18: 108776 | U18: 84329 | V18: 52040 | W18: 54702 | X18: 128614 | Y18: 85 | Z18: 95684 | AA18: =IF(COUNT(Q18:Z18)=0,"",SUM(Q18:Q18)) -> 140521 | AB18: =IF(COUNT(Q18:Z18)=0,"",SUM(R18:S18)) -> 104474 | AC18: =IF(COUNT(Q18:Z18)=0,"",SUM(T18:V18)) -> 245145 | AD18: =IF(COUNT(Q18:Z18)=0,"",SUM(W18:Y18)) -> 183401 | AE18: =IF(COUNT(Q18:Z18)=0,"",SUM(Z18:Z18)) -> 95684 | AF18: =IF(COUNT(Q18:Z18)=0,"",SUM(Q18:Z18)) -> 769225 | AG18: =IFERROR((AA18+AB18)/AF18,"") -> 0.31849589 | AH18: 5375
A19: Individual Medical | B19: OH | C19: SPE | D19: 29341 | E19: Oscar Buckeye State Insurance Corp. | F19: 29341OH0100052 | G19: HMO | H19: Silver | I19: 281056 | J19: 425418 | K19: 158433 | L19: 120181 | M19: 8147 | N19: 26986 | O19: =IFERROR(K19/I19,"") -> 0.56370617 | P19: =IFERROR(L19/J19,"") -> 0.28250098 | Q19: 135099 | R19: 0 | S19: 0 | T19: 29601 | U19: 3244 | V19: 102716 | W19: 45969 | X19: 2971 | Y19: 318 | Z19: 2451 | AA19: =IF(COUNT(Q19:Z19)=0,"",SUM(Q19:Q19)) -> 135099 | AB19: =IF(COUNT(Q19:Z19)=0,"",SUM(R19:S19)) -> 0 | AC19: =IF(COUNT(Q19:Z19)=0,"",SUM(T19:V19)) -> 135561 | AD19: =IF(COUNT(Q19:Z19)=0,"",SUM(W19:Y19)) -> 49258 | AE19: =IF(COUNT(Q19:Z19)=0,"",SUM(Z19:Z19)) -> 2451 | AF19: =IF(COUNT(Q19:Z19)=0,"",SUM(Q19:Z19)) -> 322369 | AG19: =IFERROR((AA19+AB19)/AF19,"") -> 0.41908186 | AH19: 2271
A20: Individual Medical | B20: AL | C20: FFE | D20: 46944 | E20: Blue Cross and Blue Shield of Alabama | F20: 46944AL0730001 | G20: PPO | H20: Silver | I20: 32218 | J20: 1975536 | K20: 26183 | L20: 413699 | M20: 7137 | N20: 170986 | O20: =IFERROR(K20/I20,"") -> 0.81268235 | P20: =IFERROR(L20/J20,"") -> 0.20941102 | Q20: 129171 | R20: 5472 | S20: 161 | T20: 53657 | U20: 91772 | V20: 32255 | W20: 77126 | X20: 144620 | Y20: 24 | Z20: 1592 | AA20: =IF(COUNT(Q20:Z20)=0,"",SUM(Q20:Q20)) -> 129171 | AB20: =IF(COUNT(Q20:Z20)=0,"",SUM(R20:S20)) -> 5633 | AC20: =IF(COUNT(Q20:Z20)=0,"",SUM(T20:V20)) -> 177684 | AD20: =IF(COUNT(Q20:Z20)=0,"",SUM(W20:Y20)) -> 221770 | AE20: =IF(COUNT(Q20:Z20)=0,"",SUM(Z20:Z20)) -> 1592 | AF20: =IF(COUNT(Q20:Z20)=0,"",SUM(Q20:Z20)) -> 535850 | AG20: =IFERROR((AA20+AB20)/AF20,"") -> 0.2515704 | AH20: 3280
A21: Individual Medical | B21: AR | C21: SBE-FP | D21: 62141 | E21: Celtic Insurance Company | F21: 62141AR0080007 | G21: PPO | H21: Silver | I21: 213867 | J21: 2815435 | K21: 18654 | L21: 448966 | M21: 2108 | N21: 322951 | O21: =IFERROR(K21/I21,"") -> 0.087222433 | P21: =IFERROR(L21/J21,"") -> 0.15946594 | Q21: 128986 | R21: 53052 | S21: 2272 | T21: 109461 | U21: 74603 | V21: 5823 | W21: 37625 | X21: 75304 | Y21: 0 | Z21: 76245 | AA21: =IF(COUNT(Q21:Z21)=0,"",SUM(Q21:Q21)) -> 128986 | AB21: =IF(COUNT(Q21:Z21)=0,"",SUM(R21:S21)) -> 55324 | AC21: =IF(COUNT(Q21:Z21)=0,"",SUM(T21:V21)) -> 189887 | AD21: =IF(COUNT(Q21:Z21)=0,"",SUM(W21:Y21)) -> 112929 | AE21: =IF(COUNT(Q21:Z21)=0,"",SUM(Z21:Z21)) -> 76245 | AF21: =IF(COUNT(Q21:Z21)=0,"",SUM(Q21:Z21)) -> 563371 | AG21: =IFERROR((AA21+AB21)/AF21,"") -> 0.32715564 | AH21: 26
A22: Individual Medical | B22: TX | C22: FFE | D22: 40788 | E22: Scott and White Health Plan | F22: 40788TX0460003 | G22: HMO | H22: Silver | I22: 595045 | J22: 3175557 | K22: 126288 | L22: 499865 | M22: 207842 | N22: 643527 | O22: =IFERROR(K22/I22,"") -> 0.21223269 | P22: =IFERROR(L22/J22,"") -> 0.15741018 | Q22: 120982 | R22: 0 | S22: 0 | T22: 56079 | U22: 66701 | V22: 126547 | X22: 137912 | Y22: 0 | Z22: 295134 | AA22: =IF(COUNT(Q22:Z22)=0,"",SUM(Q22:Q22)) -> 120982 | AB22: =IF(COUNT(Q22:Z22)=0,"",SUM(R22:S22)) -> 0 | AC22: =IF(COUNT(Q22:Z22)=0,"",SUM(T22:V22)) -> 249327 | AD22: =IF(COUNT(Q22:Z22)=0,"",SUM(W22:Y22)) -> 137912 | AE22: =IF(COUNT(Q22:Z22)=0,"",SUM(Z22:Z22)) -> 295134 | AF22: =IF(COUNT(Q22:Z22)=0,"",SUM(Q22:Z22)) -> 803355 | AG22: =IFERROR((AA22+AB22)/AF22,"") -> 0.15059594 | AH22: 9540
A23: Individual Medical | B23: TN | C23: FFE | D23: 70111 | E23: Celtic Insurance Company | F23: 70111TN0110034 | G23: EPO | H23: Silver | I23: 279065 | J23: 2665691 | K23: 44448 | L23: 470191 | M23: 1756 | N23: 244287 | O23: =IFERROR(K23/I23,"") -> 0.15927472 | P23: =IFERROR(L23/J23,"") -> 0.17638616 | Q23: 119910 | R23: 71854 | S23: 2461 | T23: 93253 | U23: 57596 | V23: 33385 | W23: 51598 | X23: 92176 | Y23: 0 | Z23: 85901 | AA23: =IF(COUNT(Q23:Z23)=0,"",SUM(Q23:Q23)) -> 119910 | AB23: =IF(COUNT(Q23:Z23)=0,"",SUM(R23:S23)) -> 74315 | AC23: =IF(COUNT(Q23:Z23)=0,"",SUM(T23:V23)) -> 184234 | AD23: =IF(COUNT(Q23:Z23)=0,"",SUM(W23:Y23)) -> 143774 | AE23: =IF(COUNT(Q23:Z23)=0,"",SUM(Z23:Z23)) -> 85901 | AF23: =IF(COUNT(Q23:Z23)=0,"",SUM(Q23:Z23)) -> 608134 | AG23: =IFERROR((AA23+AB23)/AF23,"") -> 0.31937862 | AH23: 6523
